Workbook
Name ____kl1: {#N/A,#N/A,FALSE,"Aging Summary";#N/A,#N/A,FALSE,"Ratio Analysis";#N/A,#N/A,FALSE,"Test 120 Day Accts";#N/A,#N/A,FALSE,"Tickmarks"}
Name ____kl1: {#N/A,#N/A,FALSE,"Aging Summary";#N/A,#N/A,FALSE,"Ratio Analysis";#N/A,#N/A,FALSE,"Test 120 Day Accts";#N/A,#N/A,FALSE,"Tickmarks"}
Name ___kl1: {#N/A,#N/A,FALSE,"Aging Summary";#N/A,#N/A,FALSE,"Ratio Analysis";#N/A,#N/A,FALSE,"Test 120 Day Accts";#N/A,#N/A,FALSE,"Tickmarks"}
Name ___kl1: {#N/A,#N/A,FALSE,"Aging Summary";#N/A,#N/A,FALSE,"Ratio Analysis";#N/A,#N/A,FALSE,"Test 120 Day Accts";#N/A,#N/A,FALSE,"Tickmarks"}
Name __123Graph_ACurrent: [1]Inventories!$A$4:$A$9
Name __123Graph_BCurrent: [1]Inventories!$B$4:$B$9
Name __123Graph_CCurrent: [1]Inventories!$C$4:$C$9
Name __123Graph_DCurrent: [1]Inventories!$D$4:$D$9
Name __123Graph_ECurrent: [1]Inventories!$E$4:$E$9
Name __123Graph_FCurrent: [1]Inventories!$F$4:$F$9
Name __aje2: 5
Name __CAc02: '[2]Customer accs'!#REF!
Name __CAc03: '[2]Customer accs'!#REF!
Name __FRX02: [2]Forex!#REF!
Name __FRX03: [2]Forex!#REF!
Name __kl1: {#N/A,#N/A,FALSE,"Aging Summary";#N/A,#N/A,FALSE,"Ratio Analysis";#N/A,#N/A,FALSE,"Test 120 Day Accts";#N/A,#N/A,FALSE,"Tickmarks"}
Name __kl1: {#N/A,#N/A,FALSE,"Aging Summary";#N/A,#N/A,FALSE,"Ratio Analysis";#N/A,#N/A,FALSE,"Test 120 Day Accts";#N/A,#N/A,FALSE,"Tickmarks"}
Name __LFB02: '[2]Loans from Banks'!#REF!
Name __LTB02: '[2]Loans to Banks'!#REF!
Name __LTC02: [2]Loans!#REF!
Name __OpE02: [2]OpExp!#REF!
Name __OpE03: [2]OpExp!#REF!
Name __Ref3: [3]Technical!#REF!
Name __SIs02: #REF!
Name __SIs03: #REF!
Name __xlnm._FilterDatabase_1_1: #REF!
Name __xlnm._FilterDatabase_1_1: #REF!
Name __xlnm._FilterDatabase_11: #REF!
Name __xlnm._FilterDatabase_11: #REF!
Name __xlnm._FilterDatabase_12: '[4]822200'!#REF!
Name __xlnm._FilterDatabase_12: '[4]822200'!#REF!
Name __xlnm._FilterDatabase_13: #REF!
Name __xlnm._FilterDatabase_13: #REF!
Name __xlnm._FilterDatabase_14: #REF!
Name __xlnm._FilterDatabase_14: #REF!
Name __xlnm._FilterDatabase_15: #REF!
Name __xlnm._FilterDatabase_15: #REF!
Name __xlnm._FilterDatabase_16: #REF!
Name __xlnm._FilterDatabase_16: #REF!
Name __xlnm._FilterDatabase_17: #REF!
Name __xlnm._FilterDatabase_17: #REF!
Name __xlnm._FilterDatabase_18: #REF!
Name __xlnm._FilterDatabase_18: #REF!
Name __xlnm._FilterDatabase_2: #REF!
Name __xlnm._FilterDatabase_2: #REF!
Name __xlnm._FilterDatabase_29: #REF!
Name __xlnm._FilterDatabase_29: #REF!
Name __xlnm._FilterDatabase_3: #REF!
Name __xlnm._FilterDatabase_3: #REF!
Name __xlnm._FilterDatabase_30: #REF!
Name __xlnm._FilterDatabase_30: #REF!
Name __xlnm._FilterDatabase_32: #REF!
Name __xlnm._FilterDatabase_32: #REF!
Name __xlnm._FilterDatabase_4: #REF!
Name __xlnm._FilterDatabase_4: #REF!
Name __xlnm._FilterDatabase_5: #REF!
Name __xlnm._FilterDatabase_5: #REF!
Name __xlnm._FilterDatabase_6: #REF!
Name __xlnm._FilterDatabase_6: #REF!
Name __xlnm._FilterDatabase_7: #REF!

Sheet Pivot
A3: Група | B3: Підгрупа
A4: Розвиток цифрових навичок населення | B4: Розвиток талантів в галузі ІКТ
B5: Розвиток цифрової грамотності населення
A6: Цифрова економіка в ТГ | B6: Привабливість для інвестицій в галузь ІТ
B7: Розвиток підприємств ІТ-сектору в ТГ
B8: Цифрові технології для бізнесу
A9: Цифрова інфраструктура в ТГ | B9: Кібербезпека
B10: Створення безпечного середовища
B11: Якість та доступність цифрової інфраструктури
A12: Цифрова трансформація ОМС | B12: Автоматизація управлінської діяльності та систем управління ресурсами
B13: Інституційна спроможність
B14: Публічності та прозорості ОМС/Інструменти е-Демократії
A15: Цифровізація публічних послуг | B15: Соціально вразливі групи населення
B16: Цифровий розвиток послуг галузей освіти і охорони здоров'я
B17: Цифровий розвиток публічних послуг для населення
B18: Цифровізація транспортної інфраструктури
A19: Загальний підсумок

Sheet Титульний аркуш
O3: Додаток 1
A12: ПАСПОРТ ІНДИКАТОРІВ Індексу цифрової трансформації ТГ
B36: Версія: | G36: 1.0
B37: Дата створення:
B38: Дата внесення змін:
K48: Київ 2022

Sheet Журнал змін
O13: Перелік внесених змін
O15: № | P15: Версія | Q15: Коментар
O16: 1 | P16: 1.00

Sheet Перелік Iндикаторiв
B3: Група | C3: Підгрупа | D3: # Індикатора | E3: Назва індикатора | G3: Одиниці вимірювання індикатора (Ов) | H3: Структура індексу | I3: вид індикатора | J3: Характер даних | K3: Цільове значення індикатора | L3: вага індикатора Розширений | M3: вага індикатора Базовий
B4: Цифрова економіка в ТГ | C4: Розвиток підприємств ІТ-сектору в ТГ | D4: A.1.1 | E4: % суб'єктів підприємницької діяльності (СПД) із КВЕДами ІТ-галузі у загальній кількості тих, які були відкриті та/або переміщені з інших ТГ протягом звітного періоду | G4: % | H4: Базовий | I4: Обов'язковий для вимірювання | J4: Кількісні дані | K4: 0.05 | L4: 0.15384615 | M4: 0.15384615
B5: Цифрова економіка в ТГ | C5: Розвиток підприємств ІТ-сектору в ТГ | D5: A.1.2 | E5: % у надходженнях від сплати ПДФО в бюджет ТГ, що надійшли від підприємств, що працюють в ІТ-галузі | F5: Частка у надходженнях від сплати ПДФО в бюджет ТГ, що надійшли від ІТ-підприємств | G5: % | H5: Базовий | I5: Обов'язковий для вимірювання | J5: Кількісні дані | K5: 0.05 | L5: 0.15384615 | M5: 0.15384615
B6: Цифрова економіка в ТГ | C6: Розвиток підприємств ІТ-сектору в ТГ | D6: A.1.3 | E6: % виручки від експорту послуг і товарів, яку отримали СПД, що працюють в ІТ-галузі, від загальної виручки від експорту послуг і товарів (в ТГ) | G6: % | I6: На майбутнє вимірювання | J6: Кількісні дані | L6: 0 | M6: 0
B7: Цифрова економіка в ТГ | C7: Розвиток підприємств ІТ-сектору в ТГ | D7: A.1.4 | E7: % виручки від внутрішнього споживання послуг і товарів, яку отримали СПД, що працюють в ІТ-галузі, від загальної виручки від послуг і товарів внутрішнього споживання (статистика) | G7: % | I7: На майбутнє вимірювання | J7: Кількісні дані | L7: 0 | M7: 0
B8: Цифрова економіка в ТГ | C8: Розвиток підприємств ІТ-сектору в ТГ | D8: A.1.5 | E8: % у надходженнях від сплати єдиного податку в бюджет ТГ, що надійшли від CПД з КВЕД ІТ-галузі | F8: Частка у надходженнях від сплати єдиного податку в бюджет ТГ, що надійшли від CПД з КВЕД ІТ-галузі | G8: % | H8: Базовий | I8: Обов'язковий для вимірювання | J8: Кількісні дані | K8: 0.1 | L8: 0.15384615 | M8: 0.15384615
B9: Цифрова економіка в ТГ | C9: Розвиток підприємств ІТ-сектору в ТГ | D9: A.1.6 | E9: % нових робочих місць, створених на підприємствах ІТ-галузі від загальної кількості нових робочих місць за звітній період | G9: % | H9: Базовий | I9: Обов'язковий для вимірювання | J9: Кількісні дані | K9: 0.1 | L9: 0.14285714 | M9: 0.14285714
B10: Цифрова економіка в ТГ | C10: Розвиток підприємств ІТ-сектору в ТГ | D10: A.1.7 | E10: Відношення середньої заробітної плати в ІТ-галузі у ТГ до середньої заробітної плати в ТГ | F10: Відношення середньої заробітної плати в ІТ-галузі у ТГ до середньої заробітної плати в ТГ | G10: % | H10: Базовий | I10: Обов'язковий для вимірювання | J10: Кількісні дані | K10: 1.5 | L10: 0.13186813 | M10: 0.13186813
B11: Цифрова економіка в ТГ | C11: Розвиток підприємств ІТ-сектору в ТГ | D11: A.1.8 | E11: Відношення середньої заробітної плати в ІТ-галузі у ТГ до середньої заробітної плати в ІТ-галузі в Україні | G11: % | H11: Базовий | I11: Обов'язковий для вимірювання | J11: Кількісні дані | K11: 1.2 | L11: 0.13186813 | M11: 0.13186813
B12: Цифрова економіка в ТГ | C12: Розвиток підприємств ІТ-сектору в ТГ | D12: A.1.9 | E12: Частка жінок на керівних посадах у підприємствах ІТ-галузі в ТГ | G12: % | I12: На майбутнє вимірювання | J12: Кількісні дані | K12: 0,5 | L12: 0 | M12: 0
B13: Цифрова економіка в ТГ | C13: Розвиток підприємств ІТ-сектору в ТГ | D13: A.1.10 | E13: Частка локальних ІТ підприємств, залучених до програми Дія Сіті, в загальній кількості ІТ підприємств | G13: % | H13: Базовий | I13: Обов'язковий для вимірювання | J13: Кількісні дані | K13: 0.005 | L13: 0.13186813 | M13: 0.13186813
B14: Цифрова економіка в ТГ | C14: Розвиток підприємств ІТ-сектору в ТГ | D14: A.1.11 | E14: % стартапів, заснованих на основі використання відкритих даних, до загальної кількості стартапів | G14: % | I14: На майбутнє вимірювання | J14: Кількісні дані | L14: 0 | M14: 0
B15: Цифрова економіка в ТГ | C15: Привабливість для інвестицій в галузь ІТ | D15: A.2.1 | E15: % залучених капітальних інвестицій в ІТ-галузі від загального обсягу інвестицій у підприємства у ТГ | G15: % | I15: На майбутнє вимірювання | J15: Кількісні дані | L15: 0 | M15: 0
B16: Цифрова економіка в ТГ | C16: Привабливість для інвестицій в галузь ІТ | D16: A.2.2 | E16: Кількість робочих місць в ІТ-хабах, які можуть орендувати/де можуть працювати ІТ-спеціалісти, на 1 тис населення | F16: Кількість робочих місць в ІТ-хабах, що можуть орендувати/де можуть працювати ІТ-спеціалісти, на 1 тис населення | G16: од/1000 населення | H16: Базовий | I16: Обов'язковий для вимірювання | J16: Кількісні дані | K16: 2 | L16: 0.19791667 | M16: 0.5
B17: Цифрова економіка в ТГ | C17: Привабливість для інвестицій в галузь ІТ | D17: A.2.3 | E17: Наявність та актуальність інформації про інвестиційні об'єкти ТГ | F17: Наявність та актуальність інформації про інвестиційні об'єкти ТГ | G17: Бал | H17: Базовий | I17: Обов'язковий для вимірювання | J17: Якісні дані | K17: 1 | L17: 0.19791667 | M17: 0.5
B18: Цифрова економіка в ТГ | C18: Привабливість для інвестицій в галузь ІТ | D18: A.2.4 | E18: % випускників вищих навчальних закладів (крім коледжів) за спеціальностями в ІТ-галузі від загальної кількості випускників | F18: Частка випускників ЗВО (крім коледжів) за спеціальностями в ІТ-галузі від загальної кількості випускників | G18: % | H18: Розширений | I18: Обов'язковий для вимірювання | J18: Кількісні дані | K18: 0.1 | L18: 0.33333333 | M18: 0
B19: Цифрова економіка в ТГ | C19: Привабливість для інвестицій в галузь ІТ | D19: A.2.5 | E19: % випускників коледжів за спеціальностями в ІТ-галузі від загальної кількості випускників | F19: Частка випускників коледжів за спеціальностями в ІТ-галузі від загальної кількості випускників | G19: % | H19: Розширений | I19: Обов'язковий для вимірювання | J19: Кількісні дані | K19: 0.1 | L19: 0.27083333 | M19: 0
B20: Цифрова економіка в ТГ | C20: Цифрові технології для бізнесу | D20: A.3.1 | E20: % заявок на реєстрацію СПД, поданих онлайн | G20: % | I20: На майбутнє вимірювання | J20: Кількісні дані | K20: 1 | L20: 0 | M20: 0
B21: Цифрова економіка в ТГ | C21: Цифрові технології для бізнесу | D21: A.3.2 | E21: % СПД, які подають звіти онлайн | G21: % | H21: Базовий | I21: На майбутнє вимірювання | J21: Кількісні дані | K21: 1 | L21: 0 | M21: 0
B22: Цифрова економіка в ТГ | C22: Цифрові технології для бізнесу | D22: A.3.3 | E22: % онлайн-послуг ОМС для бізнесу від загальної кількості послуг (послуги, суб'єктом надання яких є ОМС, комунальні підприємства, заклади) | F22: Частка онлайн-послуг ОМС для бізнесу від загальної кількості послуг | G22: % | H22: Базовий | I22: Обов'язковий для вимірювання | J22: Кількісні дані | K22: 1 | L22: 0.5 | M22: 0.5
B23: Цифрова економіка в ТГ | C23: Цифрові технології для бізнесу | D23: A.3.4 | E23: Створено центр підтримки підприємців Дія.Бізнес | F23: Створено центр Дія.Бізнес | G23: Балів | H23: Базовий | I23: Обов'язковий для вимірювання | J23: Якісні дані | K23: 1 | L23: 0.5 | M23: 0.5
B24: Розвиток цифрових навичок населення | C24: Розвиток цифрової грамотності населення | D24: В.1.2 | E24: % населення, що має застосунок Дія | G24: % | I24: На майбутнє вимірювання | J24: Кількісні дані | K24: 0.8 | L24: 0 | M24: 0
B25: Розвиток цифрових навичок населення | C25: Розвиток цифрової грамотності населення | D25: В.1.3 | E25: % населення у громаді, що використовує смартфони та/або планшети | G25: % | I25: На майбутнє вимірювання | J25: Кількісні дані | L25: 0 | M25: 0
B26: Розвиток цифрових навичок населення | C26: Розвиток цифрової грамотності населення | D26: В.1.4 | E26: % жителів поважного віку (60+ років), які пройшли навчання з цифрової грамотності / гігієни від загальної чисельності наявного населення поважного віку | G26: % | H26: Базовий | I26: Обов'язковий для вимірювання | J26: Кількісні дані | K26: 0.05 | L26: 0.070588235 | M26: 0.070588235
B27: Розвиток цифрових навичок населення | C27: Розвиток цифрової грамотності населення | D27: В.1.5 | E27: % середньозваженого значення балів Цифрограм (1.0 та 2.0) осіб, які пройшли тестування в застосунку Цифрограм 1.0 та 2.0 протягом звітного періоду, від максимальної кількості балів Цифрограм (1.0 та 2.0) | F27: Кількість осіб у ТГ, які пройшли тестування Цифрограм 1.0 та 2.0 на 1 тис. населення в ТГ | G27: % | I27: На майбутнє вимірювання | J27: Кількісні дані | K27: 0.75 | L27: 0 | M27: 0
B28: Розвиток цифрових навичок населення | C28: Розвиток цифрової грамотності населення | D28: В.1.6 | E28: Кількість осіб у ТГ, які пройшли тестування в застосунку Цифрограм 1.0 та 2.0/на 1000 населення в ТГ | G28: Осіб/1000 осіб | H28: Базовий | I28: Обов'язковий для вимірювання | J28: Кількісні дані | K28: 50 | L28: 0.16470588 | M28: 0.16470588
B29: Розвиток цифрових навичок населення | C29: Розвиток цифрової грамотності населення | D29: В.1.7 | E29: % жителів громади, які отримали ID-картки, від загальної кількості жителів ТГ відповідного віку | G29: % | H29: Базовий | I29: Обов'язковий для вимірювання | J29: Кількісні дані | K29: 1 | L29: 0.43529412 | M29: 0.43529412
B30: Розвиток цифрових навичок населення | C30: Розвиток цифрової грамотності населення | D30: В.1.8 | E30: % жителів ТГ, які зареєстрували своє місце проживання через портал Дія, від загальної кількості реєстрацій місць проживання за звітний період | G30: % | I30: На майбутнє вимірювання | J30: Кількісні дані | K30: 0.5 | L30: 0 | M30: 0
B31: Розвиток цифрових навичок населення | C31: Розвиток цифрової грамотності населення | D31: В.1.9 | E31: % дітей, зареєстрованих через єМалятко, від загальної кількості новонароджених | G31: % | H31: Базовий | I31: Обов'язковий для вимірювання | J31: Кількісні дані | K31: 1 | L31: 0.32941176 | M31: 0.32941176
B32: Розвиток цифрових навичок населення | C32: Розвиток талантів в галузі ІКТ | D32: В.2.1 | E32: Наявність школярів (6-11 класів), які стали призерами (1-3 місце) всеукраїнських олімпіад (4 етапу) з Математики та Інформатики | F32: Наявність школярів (6-11 класів), які стали призерами (1-3 місце) всеукраїнських олімпіад (4 етапу) з математики та інформатики | G32: Балів | H32: Базовий | I32: Обов'язковий для вимірювання | J32: Якісні дані | K32: 1 | L32: 0.33333333 | M32: 0.33333333
B33: Розвиток цифрових навичок населення | C33: Розвиток талантів в галузі ІКТ | D33: В.2.2 | E33: Кількість школярів (6-11 класів), які стали призерами (1-3 місце) олімпіад (2 та 3 етапів) з Математики та Інформатики, на 1000 тисячу школярів (6-11 класів) в ТГ | F33: Кількість школярів (6-11 класів), які стали призерами (1-3 місце) олімпіад (2 та 3 етапів) з математики та інформатики, на 1 тис тисячу школярів (6-11 класів) в ТГ | G33: Осіб/1000 осіб | H33: Базовий | I33: Обов'язковий для вимірювання | J33: Кількісні дані | K33: 5 | L33: 0.33333333 | M33: 0.33333333
B34: Розвиток цифрових навичок населення | C34: Розвиток талантів в галузі ІКТ | D34: В.2.3 | E34: Кількість хабів цифрової освіти на 10 000 осіб | G34: Хабів/10 000 осіб | H34: Базовий | I34: Обов'язковий для вимірювання | J34: Кількісні дані | K34: 1 | L34: 0.33333333 | M34: 0.33333333
B35: Цифрова інфраструктура в ТГ | C35: Якість та доступність цифрової інфраструктури | D35: С.1.1 | E35: % соціальних об'єктів ТГ, підключених до волоконно-оптичних мереж | F35: Частка соціальних об'єктів ТГ, підключених до волоконно-оптичних мереж | G35: % | H35: Базовий | I35: Обов'язковий для вимірювання | J35: Кількісні дані | K35: 1 | L35: 0.28776978 | M35: 0.28776978
B36: Цифрова інфраструктура в ТГ | C36: Якість та доступність цифрової інфраструктури | D36: С.1.2 | E36: % підрозділів та віддалених робочих місць ЦНАП, підключених до системи онлайн-моніторингу й оцінювання якості послуг Порталу Дія | F36: Частка підрозділів та віддалених робочих місць ЦНАП, підключених до системи онлайн-моніторингу й оцінювання якості послуг Порталу Дія | G36: % | H36: Базовий | I36: Обов'язковий для вимірювання | J36: Кількісні дані | K36: 1 | L36: 0.22302158 | M36: 0.22302158
B37: Цифрова інфраструктура в ТГ | C37: Якість та доступність цифрової інфраструктури | D37: С.1.3 | E37: % посадових осіб, які мають службовий персональний комп'ютер, від загальної кількості посадових осіб ОМС | F37: Частка посадових осіб, які мають службовий персональний комп'ютер, від загальної кількості посадових осіб ОМС | G37: % | H37: Базовий | I37: Обов'язковий для вимірювання | J37: Кількісні дані | K37: 1 | L37: 0.20143885 | M37: 0.20143885
B38: Цифрова інфраструктура в ТГ | C38: Якість та доступність цифрової інфраструктури | D38: С.1.4 | E38: % комп'ютерної техніки в закладах освіти, вік якої менше 7 років | F38: Частка комп'ютерної техніки в закладах освіти віком до 7 років | G38: % | H38: Базовий | I38: Обов'язковий для вимірювання | J38: Кількісні дані | K38: 1 | L38: 0.086330935 | M38: 0.086330935
B39: Цифрова інфраструктура в ТГ | C39: Якість та доступність цифрової інфраструктури | D39: С.1.5 | E39: % персональних комп'ютерів та серверів у ОМС віком до 7 років | F39: Частка персональних комп'ютерів та серверів у ОМС віком до 7 років | G39: % | H39: Базовий | I39: Обов'язковий для вимірювання | J39: Кількісні дані | K39: 1 | L39: 0.20143885 | M39: 0.20143885
B40: Цифрова інфраструктура в ТГ | C40: Кібербезпека | D40: С.2.1 | E40: Управління кіберінцидентами | G40: Балів | I40: На майбутнє вимірювання | J40: Якісні дані | L40: 0 | M40: 0
B41: Цифрова інфраструктура в ТГ | C41: Кібербезпека | D41: С.2.2 | E41: % посадових осіб ОМС, які пройшли навчання (підвищення кваліфікації) за програмами з кібербезпеки й кібергігієни, від загальної кількості посадових осіб ОМС | F41: Частка посадових осіб ОМС, які пройшли навчання (підвищення кваліфікації) за програмами з кібербезпеки й кібергігієни, від загальної кількості посадових осіб ОМС | G41: % | H41: Базовий | I41: Обов'язковий для вимірювання | J41: Кількісні дані | K41: 0.5 | L41: 0.22077922 | M41: 0.22077922
B42: Цифрова інфраструктура в ТГ | C42: Кібербезпека | D42: С.2.3 | E42: % комп'ютерної техніки в ОМС, на якій регулярно (1 раз на квартал) проводиться контроль оновлень ПЗ до останньої версії | F42: Частка комп'ютерної техніки в ОМС, на якій 1 раз на квартал проводиться контроль оновлень ПЗ до останньої версії | G42: % | H42: Базовий | I42: Обов'язковий для вимірювання | J42: Кількісні дані | K42: 1 | L42: 0.22077922 | M42: 0.22077922
B43: Цифрова інфраструктура в ТГ | C43: Кібербезпека | D43: С.2.4 | E43: Наявність Політики (ВНД) щодо кібербезпеки на рівні ОМС | F43: Наявність Політики (ВНД) щодо кібербезпеки на рівні ОМС | G43: Балів | H43: Базовий | I43: Обов'язковий для вимірювання | J43: Якісні дані | K43: 1 | L43: 0.27272727 | M43: 0.27272727
B44: Цифрова інфраструктура в ТГ | C44: Кібербезпека | D44: С.2.5 | E44: ТГ підключена до системи інформування про кіберінциденти MISP-UA та MISP CERT UA | F44: ТГ підключена до системи інформування про кіберінциденти MISP-UA та MISP CERT UA | G44: Балів | H44: Базовий | I44: Обов'язковий для вимірювання | J44: Якісні дані | K44: 1 | L44: 0.28571429 | M44: 0.28571429
B45: Цифрова інфраструктура в ТГ | C45: Кібербезпека | D45: С.2.6 | E45: % населення, що пройшло створені ОМС навчальні програми з кібербезпеки для населення ТГ, від загальної чисельності наявного населення ТГ | G45: % | I45: На майбутнє вимірювання | J45: Кількісні дані | L45: 0 | M45: 0
B46: Цифрова інфраструктура в ТГ | C46: Створення безпечного середовища | D46: С.3.1 | E46: Кількість активних камер відеоспостереження на площу населених пунктів у ТГ | F46: Кількість активних камер відеоспостереження на площу населених пунктів у ТГ | G46: коефіцієнт | H46: Базовий | I46: Обов'язковий для вимірювання | J46: Кількісні дані | K46: 10 | L46: 0.25 | M46: 0.33333333
B47: Цифрова інфраструктура в ТГ | C47: Створення безпечного середовища | D47: С.3.2 | E47: Наявність ситуаційного центру в ТГ | F47: Наявість ситуаційного центру в ТГ | G47: Балів | H47: Розширений | I47: Обов'язковий для вимірювання | J47: Якісні дані | K47: 1 | L47: 0.25 | M47: 0
B48: Цифрова інфраструктура в ТГ | C48: Створення безпечного середовища | D48: С.3.3 | E48: % населення ТГ, охоплене цифровою системою сповіщення цивільного захисту | G48: % | H48: Базовий | I48: Обов'язковий для вимірювання | J48: Кількісні дані | K48: 1 | L48: 0.25 | M48: 0.33333333
B49: Цифрова інфраструктура в ТГ | C49: Створення безпечного середовища | D49: С.3.4 | E49: Співвідношення кількості датчиків вимірювання якості повітря до площі населених пунктів ТГ | F49: Співвідношення кількості датчиків вимірювання якості повітря до площі населених пунктів ТГ | G49: коефіцієнт | H49: Базовий | I49: Обов'язковий для вимірювання | J49: Кількісні дані | K49: 1 | L49: 0.25 | M49: 0.33333333
B50: Цифровізація публічних послуг | C50: Цифровізація транспортної інфраструктури | D50: D.1.1 | E50: Частка одиниць маршрутних транспортних засобів, обладнаних пристроями відслідковування переміщення транспорту, в загальній кількості одиниць | F50: Частка одиниць маршрутних транспортних засобів, обладнаних пристроями відслідковування переміщення транспорту, в загальній кількості одиниць | G50: % | H50: Розширений | I50: Обов'язковий для вимірювання | J50: Кількісні дані | K50: 1 | L50: 0.26356589 | M50: 0
B51: Цифровізація публічних послуг | C51: Цифровізація транспортної інфраструктури | D51: D.1.2 | E51: Функціонування комплексної системи еКвиток з додатковими модулями | F51: Функціонування комплексної системи еКвиток з додатковими модулями | G51: Балів | H51: Розширений | I51: Обов'язковий для вимірювання | J51: Якісні дані | K51: 1 | L51: 0.18604651 | M51: 0
B52: Цифровізація публічних послуг | C52: Цифровізація транспортної інфраструктури | D52: D.1.3 | E52: % муніципальних відведених майданчиків для паркування, обладнаних електронними пристроями для оплати, зокрема інфокіосками, та/або з можливістю оплати через мобільний застосунок (QR) | F52: Частка муніципальних відведених майданчиків для паркування, обладнаних електронними пристроями для оплати, зокрема інфокіосками, та/або з можливістю оплати через мобільний застосунок (QR) | G52: % | H52: Розширений | I52: Обов'язковий для вимірювання | J52: Кількісні дані | K52: 1 | L52: 0.15503876 | M52: 0
B53: Цифровізація публічних послуг | C53: Цифровізація транспортної інфраструктури | D53: D.1.4 | E53: % Закон України пинок маршрутних транспортних засобів, обладнаних електронними табло розкладу руху | F53: Частка Закон України пинок маршрутних транспортних засобів, обладнаних електронними табло розкладу руху | G53: % | H53: Розширений | I53: Обов'язковий для вимірювання | J53: Кількісні дані | K53: 1 | L53: 0.17829457 | M53: 0
B54: Цифровізація публічних послуг | C54: Цифровізація транспортної інфраструктури | D54: D.1.5 | E54: % маршрутів громадського транспорту, доступних для онлайн-моніторингу з мобільних пристроїв | F54: Частка маршрутів громадського транспорту, доступних для онлайн-моніторингу з мобільних пристроїв | G54: % | H54: Розширений | I54: Обов'язковий для вимірювання | J54: Кількісні дані | K54: 1 | L54: 0.21705426 | M54: 0
B55: Цифровізація публічних послуг | C55: Цифровий розвиток публічних послуг для населення | D55: D.2.1 | E55: % найменувань адміністративних послуг, доступних для замовлення в режимі онлайн, суб'єктом надання яких є ОМС, від загальної кількості найменувань адміністративних послуг (РКМУ 523) | F55: Частка найменувань адміністративних послуг, доступних для замовлення в режимі онлайн, суб'єктом надання яких є ОМС, від загальної кількості найменувань адміністративних послуг | G55: % | H55: Базовий | I55: Обов'язковий для вимірювання | J55: Кількісні дані | K55: 0.5 | L55: 0.11428571 | M55: 0.11428571
B56: Цифровізація публічних послуг | C56: Цифровий розвиток публічних послуг для населення | D56: D.2.2 | E56: % найменувань адміністративних послуг, суб'єктом надання яких є ОМС і реЗакон України льтати яких надаються в цифровому вигляді (онлайн), від загальної кількості найменувань адміністративних послуг (РКМУ 523) | F56: Частка найменувань адміністративних послуг, суб'єктом надання яких є ОМС і реЗакон України льтати яких надаються в цифровому вигляді (онлайн), від загальної кількості найменувань адміністративних послуг | G56: % | H56: Базовий | I56: Обов'язковий для вимірювання | J56: Кількісні дані | K56: 1 | L56: 0.11428571 | M56: 0.11428571
B57: Цифровізація публічних послуг | C57: Цифровий розвиток публічних послуг для населення | D57: D.2.3 | E57: Наявність можливості онлайн-оплати за надання адміністративної послуги | F57: Наявність можливості онлайн-оплати за надання адміністративної послуги | G57: Балів | H57: Базовий | I57: Обов'язковий для вимірювання | J57: Якісні дані | K57: 1 | L57: 0.16326531 | M57: 0.16326531
B58: Цифровізація публічних послуг | C58: Цифровий розвиток публічних послуг для населення | D58: D.2.4 | E58: % підрозділів і віддалених робочих місць ЦНАП, обладнаних електронною чергою (включно з онлайн-реєстрацією) | F58: Частка підрозділів і віддалених робочих місць ЦНАП, обладнаних е-чергою (включно з онлайн-реєстрацією) | G58: % | H58: Базовий | I58: Обов'язковий для вимірювання | J58: Кількісні дані | K58: 1 | L58: 0.12653061 | M58: 0.12653061
B59: Цифровізація публічних послуг | C59: Цифровий розвиток публічних послуг для населення | D59: D.2.5 | E59: Наявність функціональних можливостей програмного забезпечення ЦНАП | F59: Наявність функціональних можливостей програмного забезпечення ЦНАП | G59: Балів | H59: Базовий | I59: Обов'язковий для вимірювання | J59: Якісні дані | K59: 1 | L59: 0.16326531 | M59: 0.16326531
B60: Цифровізація публічних послуг | C60: Цифровий розвиток публічних послуг для населення | D60: D.2.6 | E60: % робочих місць адміністраторів ЦНАП, обладнаних для QR валідації Дія (в т. ч. віддалені робочі місця) | F60: Частка робочих місць адміністраторів ЦНАП, обладнаних для QR валідації Дія (зокрема, віддалені робочі місця) | G60: % | H60: Базовий | I60: Обов'язковий для вимірювання | J60: Кількісні дані | K60: 1 | L60: 0.12653061 | M60: 0.12653061
... B62: Цифровізація публічних послуг | C62: Цифровий розвиток публічних послуг для населення | D62: D.2.8 | E62: Наявність IVR системи (в т. ч. для ЦНАП та інших підрозділів, що надають послуги) для надання інформації ОМС | F62: Наявність IVR системи для надання інформації ОМС | G62: Балів | H62: Базовий | I62: Обов'язковий для вимірювання | J62: Якісні дані | K62: 1 | L62: 0.065306122 | M62: 0.065306122
B63: Цифровізація публічних послуг | C63: Цифровий розвиток послуг галузей освіти і охорони здоров'я | D63: D.3.1 | E63: % шкіл та дитячих садочків ТГ, підключених до інформаційно-аналітичної системи НАССР | G63: % | I63: На майбутнє вимірювання | J63: Кількісні дані | K63: 1 | L63: 0 | M63: 0
B64: Цифровізація публічних послуг | C64: Цифровий розвиток послуг галузей освіти і охорони здоров'я | D64: D.3.2 | E64: % ЗЗО у ТГ, які використовують шкільні е-журнали та/або е-платформи для шкіл | F64: Частка ЗЗО у ТГ, що використовують шкільні е-журнали та/або е-платформи для шкіл | G64: % | H64: Базовий | I64: Обов'язковий для вимірювання | J64: Кількісні дані | K64: 1 | L64: 0.23846154 | M64: 0.23846154
B65: Цифровізація публічних послуг | C65: Цифровий розвиток послуг галузей освіти і охорони здоров'я | D65: D.3.3 | E65: % вчителів 5-11 класів ЗЗО у ТГ, зареєстрованих на онлайн-платформі ВШО | F65: Частка вчителів 5-11 класів ЗЗО у ТГ, зареєстрованих на онлайн-платформі ВШО | G65: % | H65: Базовий | I65: Обов'язковий для вимірювання | J65: Кількісні дані | K65: 1 | L65: 0.16153846 | M65: 0.16153846
B66: Цифровізація публічних послуг | C66: Цифровий розвиток послуг галузей освіти і охорони здоров'я | D66: D.3.4 | E66: % шкіл, забезпечених STEM/STEAM лабораторіями | F66: Частка шкіл, забезпечених STEM/STEAM лабораторіями | G66: % | H66: Базовий | I66: Обов'язковий для вимірювання | J66: Кількісні дані | K66: 1 | L66: 0.13846154 | M66: 0.13846154
B67: Цифровізація публічних послуг | C67: Цифровий розвиток послуг галузей освіти і охорони здоров'я | D67: D.3.5 | E67: Кількість персональної комп'ютерної техніки (планшети/ноутбуки) на 1 учня 5-11 класів | F67: Кількість персональної комп'ютерної техніки (планшети/ноутбуки) на 1 учня 5-11 класів | G67: % | H67: Базовий | I67: Обов'язковий для вимірювання | J67: Кількісні дані | K67: 0.2 | L67: 0.13846154 | M67: 0.13846154
B68: Цифровізація публічних послуг | C68: Цифровий розвиток послуг галузей освіти і охорони здоров'я | D68: D.3.6 | E68: % закладів дошкільної освіти, де запроваджено електронну чергу із зарахування дитини до закладу | F68: Частка закладів дошкільної освіти, де запроваджено е-чергу із зарахування дитини до закладу | G68: % | H68: Базовий | I68: Обов'язковий для вимірювання | J68: Кількісні дані | K68: 1 | L68: 0.14615385 | M68: 0.14615385
B69: Цифровізація публічних послуг | C69: Цифровий розвиток послуг галузей освіти і охорони здоров'я | D69: D.3.7 | E69: % ЗОЗ, які надають можливість онлайн-запису до лікаря | F69: Частка ЗОЗ, що надають можливість онлайн-запису до лікаря | G69: % | H69: Базовий | I69: Обов'язковий для вимірювання | J69: Кількісні дані | K69: 1 | L69: 0.17692308 | M69: 0.17692308
B70: Цифровізація публічних послуг | C70: Соціально вразливі групи населення | D70: D.4.1 | E70: % регульованих пішохідних переходів, обладнаних для осіб із вадами зору, від загальної кількості світлофорів на пішохідних переходах | F70: Частка регульованих пішохідних переходів, обладнаних для осіб із порушенням зору, від загальної кількості світлофорів на пішохідних переходах | G70: % | H70: Розширений | I70: Обов'язковий для вимірювання | J70: Кількісні дані | K70: 1 | L70: 0.25242718 | M70: 0
B71: Цифровізація публічних послуг | C71: Соціально вразливі групи населення | D71: D.4.2 | E71: Частка одиниць маршрутних транспортних засобів, обладнаних пристроями для зовнішнього звукового інформування про номер і кінцеву Закон України пинку маршруту й віЗакон України альними (текстовими) системами для пасажирів із порушенням зору та слуху, в загальній кількості одиниць маршрутних транспортних засобів | F71: Частка одиниць маршрутних транспортних засобів, обладнаних пристроями для зовішнього звукового інформування про номер і кінцеву Закон України пинку маршруту й віЗакон України альними системами для пасажирів із порушенням зору та слуху, в загальній кількості одиниць маршрутних транспортних засобів | G71: % | H71: Розширений | I71: Обов'язковий для вимірювання | J71: Кількісні дані | K71: 1 | L71: 0.2038835 | M71: 0
B72: Цифровізація публічних послуг | C72: Соціально вразливі групи населення | D72: D.4.3 | E72: Наявність та використання мобільної валізи ЦНАП | F72: Наявність та використання мобільної валізи ЦНАП | G72: балів | H72: Базовий | I72: Обов'язковий для вимірювання | J72: Якісні дані | K72: 1 | L72: 0.30097087 | M72: 0.55357143
B73: Цифровізація публічних послуг | C73: Соціально вразливі групи населення | D73: D.4.4 | E73: % шкіл, які провели шкільний громадський бюджет (за рік) | F73: Частка шкіл, що провели шкільний громадський бюджет за рік | G73: % | H73: Базовий | I73: Обов'язковий для вимірювання | J73: Кількісні дані | K73: 1 | L73: 0.14563107 | M73: 0.26785714
B74: Цифровізація публічних послуг | C74: Соціально вразливі групи населення | D74: D.4.5 | E74: Наявність розділу на порталі громади, що містить корисну інформацію та/або посилання для ВПО | F74: Наявність розділу на порталі ТГ, що містить корисну інформацію та/або посилання для ВПО | G74: Балів | H74: Базовий | I74: Обов'язковий для вимірювання | J74: Якісні дані | K74: 1 | L74: 0.097087379 | M74: 0.17857143
B75: Цифрова трансформація ОМС | C75: Публічності та прозорості ОМС/Інструменти е-Демократії | D75: Е.1.1 | E75: % проведених [висвітлених] відеотрансляцій пленарних засідань ради ТГ, засідань виконавчого комітету, від загальної кількості засідань, що підлягають оприлюдненню, упродовж звітного періоду | F75: Частка проведених [висвітлених] відеотрансляцій пленарних засідань ради ТГ, засідань виконавчого комітету, від загальної кількості засідань, що підлягають оприлюдненню, упродовж звітного періоду | G75: % | H75: Базовий | I75: Обов'язковий для вимірювання | J75: Кількісні дані | K75: 1 | L75: 0.14728682 | M75: 0.14728682
... B79: Цифрова трансформація ОМС | C79: Публічності та прозорості ОМС/Інструменти е-Демократії | D79: Е.1.5 | E79: % наборів даних, що перебувають у володінні ТГ, з Реєстру наборів даних, що перебувають у володінні розпорядника інформації, які були опубліковані онлайн згідно з абзацом 6 Порядку наборів даних, які підлягають оприлюдненню у формі відкритих даних відповідно до Постанови КМУ №835 | F79: Частка наборів даних, що перебувають у володінні ТГ, з Реєстру наборів даних, що перебувають у володінні розпорядника інформації, що були опубліковані онлайн | G79: % | H79: Базовий | I79: Обов'язковий для вимірювання | J79: Кількісні дані | K79: 1 | L79: 0.21705426 | M79: 0.21705426
B80: Цифрова трансформація ОМС | C80: Публічності та прозорості ОМС/Інструменти е-Демократії | D80: Е.1.6 | E80: Оприлюднення на Єдиному державному вебпорталі та, за наявності, порталах ОМС, наборів відкритих даних, публікація яких є необхідною для переходу на низьковуглецеву та циркулярну економіку | G80: Балів | I80: На майбутнє вимірювання | J80: Якісні дані | L80: 0 | M80: 0
B81: Цифрова трансформація ОМС | C81: Публічності та прозорості ОМС/Інструменти е-Демократії | D81: Е.1.7 | E81: Оприлюднення на Єдиному державному вебпорталі та, за наявності, порталах ОМС, наборів відкритих даних, які уможливлюють проведення моніторингу використання коштів міжнародної технічної допомоги (МТД) | G81: Балів | I81: На майбутнє вимірювання | J81: Якісні дані | L81: 0 | M81: 0
B82: Цифрова трансформація ОМС | C82: Публічності та прозорості ОМС/Інструменти е-Демократії | D82: Е.1.8 | E82: ОМС є зареєстрованим як розпорядник інформації на Єдиному державному вебпорталі відкритих даних та оприлюднює публічну інформацію у формі відкритих даних відповідно до законодавства | F82: ОМС є зареєстрованим як розпорядник інформації на Єдиному державному вебпорталі відкритих даних та оприлюднює публічну інформацію у формі відкритих даних відповідно до законодавства | G82: Балів | H82: Базовий | I82: Обов'язковий для вимірювання | J82: Якісні дані | K82: 1 | L82: 0.10077519 | M82: 0.10077519
B83: Цифрова трансформація ОМС | C83: Публічності та прозорості ОМС/Інструменти е-Демократії | D83: Е.1.9 | E83: ОМС як розпорядник інформації щороку заповнює та вчасно подає картку оцінки стану оприлюднення й оновлення відкритих даних | G83: Балів | I83: На майбутнє вимірювання | J83: Якісні дані | L83: 0 | M83: 0
B84: Цифрова трансформація ОМС | C84: Публічності та прозорості ОМС/Інструменти е-Демократії | D84: Е.1.10 | E84: Кількість скачувань та звернень наборів даних до кількості населення | G84: % | I84: На майбутнє вимірювання | J84: Кількісні дані | L84: 0 | M84: 0
B85: Цифрова трансформація ОМС | C85: Автоматизація управлінської діяльності та систем управління ресурсами | D85: Е.2.1 | E85: % посадових осіб ОМС, підключених до системи електронного документообігу | F85: Частка посадових осіб ОМС, підключених до системи е-документообігу | G85: % | H85: Базовий | I85: Обов'язковий для вимірювання | J85: Кількісні дані | K85: 1 | L85: 0.2259887 | M85: 0.30769231
B86: Цифрова трансформація ОМС | C86: Автоматизація управлінської діяльності та систем управління ресурсами | D86: Е.2.2 | E86: % комунальних закладів та установ, включно з їхніми підрозділами, підключених до системи електронного документообігу | F86: Частка комунальних закладів та установ, включно з їхніми підрозділами, підключених до системи е-документообігу | G86: % | H86: Базовий | I86: Обов'язковий для вимірювання | J86: Кількісні дані | K86: 1 | L86: 0.1920904 | M86: 0.26153846
B87: Цифрова трансформація ОМС | C87: Автоматизація управлінської діяльності та систем управління ресурсами | D87: Е.2.3 | E87: % зареєстрованих документів структурних підрозділів ОМС, які підписуються цифровим підписом Керівника | G87: % | H87: Базовий | I87: Обов'язковий для вимірювання | J87: Кількісні дані | K87: 1 | L87: 0.15819209 | M87: 0.21538462
B88: Цифрова трансформація ОМС | C88: Автоматизація управлінської діяльності та систем управління ресурсами | D88: Е.2.4 | E88: Інтеграція СЕД ОМС із СЕВ ОВВ | F88: Інтеграція СЕД ОМС із СЕВ ОВВ | G88: Балів | H88: Базовий | I88: Обов'язковий для вимірювання | J88: Якісні дані | K88: 1 | L88: 0.15819209 | M88: 0.21538462
B89: Цифрова трансформація ОМС | C89: Автоматизація управлінської діяльності та систем управління ресурсами | D89: Е.2.5 | E89: % об'єктів комунальної власності, обладнаних системами моніторингу енергоефективності | F89: Частка об'єктів комунальної власності, обладнаних системами моніторингу енергоефективності | G89: % | H89: Розширений | I89: Обов'язковий для вимірювання | J89: Кількісні дані | K89: 1 | L89: 0.13559322 | M89: 0
B90: Цифрова трансформація ОМС | C90: Автоматизація управлінської діяльності та систем управління ресурсами | D90: Е.2.6 | E90: % об'єктів комунальної власності, обладнаних системами енергозбереження (автоматичне вимикання освітлення тощо) | F90: Частка об'єктів комунальної власності, обладнаних системами енергозбереження | G90: % | H90: Розширений | I90: Обов'язковий для вимірювання | J90: Кількісні дані | K90: 1 | L90: 0.1299435 | M90: 0
B91: Цифрова трансформація ОМС | C91: Інституційна спроможність | D91: Е.3.1 | E91: Наявність Програми інформатизації | F91: Наявність Програми інформатизації | G91: Балів | H91: Базовий | I91: Обов'язковий для вимірювання | J91: Якісні дані | K91: 1 | L91: 0.27586207 | M91: 0.38095238
B92: Цифрова трансформація ОМС | C92: Інституційна спроможність | D92: Е.3.2 | E92: Наявність підрозділу, до функцій якого належить цифрова трансформація ТГ | F92: Наявність підрозділу, до функцій якого належить цифрова трансформація ТГ | G92: Балів | H92: Розширений | I92: Обов'язковий для вимірювання | J92: Якісні дані | K92: 1 | L92: 0.27586207 | M92: 0
B93: Цифрова трансформація ОМС | C93: Інституційна спроможність | D93: Е.3.3 | E93: Наявність офіційного цифрового лідера | F93: Наявність офіційно призначеного цифрового лідера | G93: Балів | H93: Базовий | I93: Обов'язковий для вимірювання | J93: Якісні дані | K93: 1 | L93: 0.27586207 | M93: 0.38095238
B94: Цифрова трансформація ОМС | C94: Інституційна спроможність | D94: Е.3.4 | E94: % видатків із місцевого бюджету, спрямованих на зв'язок, телекомунікації та інформатику, в бюджеті ТГ | F94: Частка видатків із місцевого бюджету, спрямованих на інформатизацію, зокрема електронна комунікацію та зв'язок в бюджеті ТГ | G94: % | H94: Базовий | I94: Обов'язковий для вимірювання | J94: Кількісні дані | K94: 0.1 | L94: 0.17241379 | M94: 0.23809524
B95: Цифрова трансформація ОМС | C95: Онлайн ресурси ОМС | D95: Е.4.1 | E95: Наявність туристичної інформації на ресурсах, які адмініструє ОМС | F95: Наявність туристичної інформації на ресурсах, що адмініструє ОМС | G95: Балів | H95: Базовий | I95: Обов'язковий для вимірювання | J95: Якісні дані | K95: 1 | L95: 0.15909091 | M95: 0.15909091
B96: Цифрова трансформація ОМС | C96: Онлайн ресурси ОМС | D96: Е.4.2 | E96: Наявність інформації про культурні заходи на порталі ТГ (або на інших офіційних сторінках ТГ) | F96: Наявність інформації про культурні заходи на вебпорталі ТГ | G96: Балів | H96: Базовий | I96: Обов'язковий для вимірювання | J96: Якісні дані | K96: 1 | L96: 0.15909091 | M96: 0.15909091
B97: Цифрова трансформація ОМС | C97: Онлайн ресурси ОМС | D97: Е.4.3 | E97: % туристичних ресурсів і пам'яток, маркованих QR-кодом, від загальної кількості туристичних ресурсів і пам'яток | F97: Частка туристичних ресурсів і пам'яток, маркованих QR-кодом, від загальної кількості туристичних ресурсів і пам'яток | G97: % | H97: Базовий | I97: Обов'язковий для вимірювання | J97: Кількісні дані | K97: 1 | L97: 0.18181818 | M97: 0.18181818
B98: Цифрова трансформація ОМС | C98: Онлайн ресурси ОМС | D98: Е.4.4 | E98: Наявність у публічному доступі геопорталу ТГ | F98: Наявність геопорталу ТГ | G98: Балів | H98: Базовий | I98: Обов'язковий для вимірювання | J98: Якісні дані | K98: 1 | L98: 0.25 | M98: 0.25
B99: Цифрова трансформація ОМС | C99: Онлайн ресурси ОМС | D99: Е.4.5 | E99: Відповідність офіційного сайту ОМС дизайн-коду Дія | F99: Відповідність офіційного сайту ОМС дизайн-коду Дія | G99: Балів | H99: Базовий | I99: Обов'язковий для вимірювання | J99: Якісні дані | K99: 1 | L99: 0.25 | M99: 0.25

Sheet Паспорт Iндикаторiв
B3: Група | C3: Підгрупа | D3: # Індика-тора | E3: Назва індикатора | F3: Фінальна назва Індикатора на ДЦГ | G3: Одиниці вимірювання індикатора (ОВ) | H3: Структура індексу | I3: Вид індикатора | J3: Характер даних | K3: Цільове значення індикатора | L3: Вага індикатора Розширений | M3: Вага індикатора Базовий | O3: # Показника | P3: Назва Показника | Q3: Присвоєння балів (в роботі) | R3: Формула розрахунку та ОВ | T3: Визначення складових і термінів | U3: Періодичність вимірювання | V3: Документ, що лежить в основі індикатора | W3: Джерело даних Показника
B4: Цифрова економіка в ТГ | C4: Розвиток підприємств ІТ-сектору в ТГ | D4: A.1.1 | E4: % СПД із КВЕДами ІТ-галузі у загальній кількості тих, які були відкриті та/або переміщені з інших ТГ протягом звітного періоду | G4: % | H4: Базовий | I4: На майбутнє вимірювання | J4: Кількісні дані | K4: 0.15 | L4: =VLOOKUP(D4,'Перелік Iндикаторiв'!$D$4:$M$99,8,FALSE) -> 0.05 | M4: =VLOOKUP(D4,'Перелік Iндикаторiв'!$D$4:$M$99,9,FALSE) -> 0.15384615 | O4: A.1.1.1 | P4: Кількість СПД в ІТ-галузі, які були відкриті та/або переміщені з інших ТГ (ОВ: СПД) | Q4: Бал індикатора присвоюється пропорційно до розрахованого значення у відношенні до цільового з кроком 1 бал, де 100 - максимальний бал, коли розраховане значення дорівнює цільовому, 0 - мінімальний бал | R4: Формула розрахунку - [((Показник 1.1-Показник 1.2)/Показник 1.3)*100%], де Показник 1.1 - Кількість СПД в ІТ-галузі, які були відкриті та/або переміщені з інших ТГ, шт Показник 1.2 - Кількість СПД в ІТ-галузі, які припинили діяльність в ТГ, шт Показник 1.3 - Загальна кількість СПД в ІТ-галузі в ТГ станом на кінець звітного року, шт | T4: Суб'єкти підприємницької діяльності (СПД) в ІТ-галузі, зареєстровані на території ТГ – кількість СПД, що на території ТГ отримали послугу державної реєстрації суб'єкта підприємницької діяльності відповідно до Розділу 4 Закону України "Про державну реєстрацію юридичних осіб, фізичних осіб-підприємців та громадських формувань" і зазначили основним видом діяльності один із нижчезазначених КВЕД: 62.01 Комп’ютерне програмування; 62.02 Консультування з питань інформатизації; 62.09 Інша діяльність у сфері інформаційних технологій і комп'ютерних систем. 58.21 Видання комп'ютерних ігор; 58.29 Видання іншого програмного забезпечення; 63.11 Оброблення даних, розміщення інформації на веб-вузлах і пов’язана з ними діяльність; 18.20 Тиражування звуко-, відеозаписів і програмного забезпечення; 47.41 Роздрібна торгівля комп’ютерами, периферійним устаткуванням і програмним забезпеченням у спеціалізованих магазинах; | U4: за рік | V4: Закону України "Про державну реєстрацію юридичних осіб, фізичних осіб-підприємців та громадських формувань" https://zakon.rada.gov.ua/laws/show/755-15#Text | W4: Дані Державної податкової служби
B5: Цифрова економіка в ТГ | C5: Розвиток підприємств ІТ-сектору в ТГ | D5: A.1.1 | G5: % | H5: Базовий | I5: На майбутнє вимірювання | J5: Кількісні дані | K5: 0.15 | L5: =VLOOKUP(D5,'Перелік Iндикаторiв'!$D$4:$M$99,8,FALSE) -> 0.05 | M5: =VLOOKUP(D5,'Перелік Iндикаторiв'!$D$4:$M$99,9,FALSE) -> 0.15384615 | O5: A.1.1.2 | P5: Кількість СПД в ІТ-галузі, які припинили діяльність в ТГ (ОВ: СПД) | Q5: Бал індикатора присвоюється пропорційно до розрахованого значення у відношенні до цільового з кроком 1 бал, де 100 - максимальний бал, коли розраховане значення дорівнює цільовому, 0 - мінімальний бал | R5: Формула розрахунку - [((Показник 1.1-Показник 1.2)/Показник 1.3)*100%], де Показник 1.1 - Кількість СПД в ІТ-галузі, які були відкриті та/або переміщені з інших ТГ, шт Показник 1.2 - Кількість СПД в ІТ-галузі, які припинили діяльність в ТГ, шт Показник 1.3 - Загальна кількість СПД в ІТ-галузі в ТГ станом на кінець звітного року, шт | T5: Суб'єкти підприємницької діяльності (окрім державних та комунальних підприємств), зареєстровані на території ТГ, що припинили діяльність – кількість СПД на території ТГ, які отримали послугу з припинення підприємницької діяльності відповідно до Розділу 4 Закону України "Про державну реєстрацію юридичних осіб, фізичних осіб-підприємців та громадських формувань" і зазначили основним видом діяльності один із нижчезазначених КВЕД: 62.01 Комп’ютерне програмування; 62.02 Консультування з питань інформатизації; 62.09 Інша діяльність у сфері інформаційних технологій і комп'ютерних систем. 58.21 Видання комп'ютерних ігор; 58.29 Видання іншого програмного забезпечення; 63.11 Оброблення даних, розміщення інформації на веб-вузлах і пов’язана з ними діяльність; 18.20 Тиражування звуко-, відеозаписів і програмного забезпечення; 47.41 Роздрібна торгівля комп’ютерами, периферійним устаткуванням і програмним забезпеченням у спеціалізованих магазинах; | U5: за рік | V5: Закону України "Про державну реєстрацію юридичних осіб, фізичних осіб-підприємців та громадських формувань" https://zakon.rada.gov.ua/laws/show/755-15#Text | W5: Дані Державної податкової служби
B6: Цифрова економіка в ТГ | C6: Розвиток підприємств ІТ-сектору в ТГ | D6: A.1.1 | G6: % | H6: Базовий | I6: На майбутнє вимірювання | J6: Кількісні дані | K6: 0.15 | L6: =VLOOKUP(D6,'Перелік Iндикаторiв'!$D$4:$M$99,8,FALSE) -> 0.05 | M6: =VLOOKUP(D6,'Перелік Iндикаторiв'!$D$4:$M$99,9,FALSE) -> 0.15384615 | O6: A.1.1.3 | P6: Загальна кількість СПД в ІТ-галузі в ТГ (ОВ: СПД) | Q6: Бал індикатора присвоюється пропорційно до розрахованого значення у відношенні до цільового з кроком 1 бал, де 100 - максимальний бал, коли розраховане значення дорівнює цільовому, 0 - мінімальний бал | R6: Формула розрахунку - [((Показник 1.1-Показник 1.2)/Показник 1.3)*100%], де Показник 1.1 - Кількість СПД в ІТ-галузі, які були відкриті та/або переміщені з інших ТГ, шт Показник 1.2 - Кількість СПД в ІТ-галузі, які припинили діяльність в ТГ, шт Показник 1.3 - Загальна кількість СПД в ІТ-галузі в ТГ станом на кінець звітного року, шт | T6: Суб'єкти підприємницької діяльності в ІТ-галузі – вітчизняні та іноземні юридичні особи, а також фізичні особи-підприємці, які провадять діяльність в Україні та зазначили основним видом діяльності один із нижчезазначених КВЕД: 62.01 Комп’ютерне програмування; 62.02 Консультування з питань інформатизації; 62.09 Інша діяльність у сфері інформаційних технологій і комп'ютерних систем. 58.21 Видання комп'ютерних ігор; 58.29 Видання іншого програмного забезпечення; 63.11 Оброблення даних, розміщення інформації на веб-вузлах і пов’язана з ними діяльність; 18.20 Тиражування звуко-, відеозаписів і програмного забезпечення; 47.41 Роздрібна торгівля комп’ютерами, периферійним устаткуванням і програмним забезпеченням у спеціалізованих магазинах; | U6: станом на 01.01.2022 | V6: Закону України "Про державну реєстрацію юридичних осіб, фізичних осіб-підприємців та громадських формувань" https://zakon.rada.gov.ua/laws/show/755-15#Text | W6: Дані Державної податкової служби
B7: Цифрова економіка в ТГ | C7: Розвиток підприємств ІТ-сектору в ТГ | D7: A.1.2 | E7: % у надходженнях від сплати ПДФО в бюджет ТГ, що надійшли від підприємств, що працюють в ІТ-галузі | F7: Частка у надходженнях від сплати ПДФО в бюджет ТГ, що надійшли від ІТ-підприємств | G7: % | H7: Базовий | I7: Обов'язковий для вимірювання | J7: Кількісні дані | K7: 0.15 | L7: =VLOOKUP(D7,'Перелік Iндикаторiв'!$D$4:$M$99,8,FALSE) -> 0.05 | M7: =VLOOKUP(D7,'Перелік Iндикаторiв'!$D$4:$M$99,9,FALSE) -> 0.15384615 | O7: A.1.2.1 | P7: Обсяг надходжень до бюджету ТГ від сплати ПДФО підприємствами ІТ-галузі за звітний рік (ОВ: грн) | Q7: Бал індикатора присвоюється пропорційно до розрахованого значення у відношенні до цільового з кроком 1 бал, де 100 - максимальний бал, коли розраховане значення дорівнює цільовому, 0 - мінімальний бал | R7: Формула розрахунку - [((Показник 1.1/Показник 1.2)*100%], де Показник 1.1 – обсяг надходжень до бюджету ТГ від сплати ПДФО підприємствами ІТ-галузі за звітний рік, грн Показник 1.2 - Загальний обсяг надходжень до бюджету ТГ від сплати ПДФО за звітний рік, грн | T7: Обсяг надходжень до бюджету ТГ від сплати ПДФО підприємствами ІТ-галузі – обсяг коштів, що надійшли до бюджету ТГ від сплати суб'єктами податку на доходи фізичних осіб суб'єктами підприємницької діяльності, основною діяльністю яких є такі КВЕД: 62.01 Комп’ютерне програмування; 62.02 Консультування з питань інформатизації; 62.09 Інша діяльність у сфері інформаційних технологій і комп'ютерних систем. 58.21 Видання комп'ютерних ігор; 58.29 Видання іншого програмного забезпечення; 63.11 Оброблення даних, розміщення інформації на веб-вузлах і пов’язана з ними діяльність; 18.20 Тиражування звуко-, відеозаписів і програмного забезпечення; 47.41 Роздрібна торгівля комп’ютерами, периферійним устаткуванням і програмним забезпеченням у спеціалізованих магазинах; Обсяг надходжень від сплати ПДФО – обсяг коштів, що надійшли до бюджету ТГ від сплати суб'єктами податку на доходи фізичних осіб за такими кодами класифікації доходів: 11010100, 11010200, 11010400, 11010500, 11010600, 11010700, 11010900. | U7: за рік | V7: Бюджетний кодекс України https://zakon.rada.gov.ua/laws/show/2456-17#Text Наказ Міністерства фінансів "Про бюджетну класифікацію" №11 від 14 січня 2011 https://zakon.rada.gov.ua/rada/show/v0011201-11#Text | W7: Дані Державної податкової служби
B8: Цифрова економіка в ТГ | C8: Розвиток підприємств ІТ-сектору в ТГ | D8: A.1.2 | E8: % у надходженнях від сплати ПДФО в бюджет ТГ, що надійшли від підприємств, що працюють в ІТ-галузі | G8: % | H8: Базовий | I8: Обов'язковий для вимірювання | J8: Кількісні дані | K8: 0.15 | L8: =VLOOKUP(D8,'Перелік Iндикаторiв'!$D$4:$M$99,8,FALSE) -> 0.05 | M8: =VLOOKUP(D8,'Перелік Iндикаторiв'!$D$4:$M$99,9,FALSE) -> 0.15384615 | O8: A.1.2.2 | P8: Загальний обсяг надходжень до бюджету ТГ від сплати ПДФО за звітний рік (ОВ: грн) | Q8: Бал індикатора присвоюється пропорційно до розрахованого значення у відношенні до цільового з кроком 1 бал, де 100 - максимальний бал, коли розраховане значення дорівнює цільовому, 0 - мінімальний бал | R8: Формула розрахунку - [((Показник 1.1/Показник 1.2)*100%], де Показник 1.1 – обсяг надходжень до бюджету ТГ від сплати ПДФО підприємствами ІТ-галузі за звітний рік, грн Показник 1.2 - Загальний обсяг надходжень до бюджету ТГ від сплати ПДФО за звітний рік, грн | T8: Обсяг надходжень від сплати ПДФО – обсяг коштів, що надійшли до бюджету ТГ від сплати суб'єктами податку на доходи фізичних осіб за такими кодами класифікації доходів: 11010100, 11010200, 11010400, 11010500, 11010600, 11010700, 11010900. | U8: за рік | V8: Бюджетний кодекс України https://zakon.rada.gov.ua/laws/show/2456-17#Text Наказ Міністерства фінансів "Про бюджетну класифікацію" №11 від 14 січня 2011 https://zakon.rada.gov.ua/rada/show/v0011201-11#Text | W8: Дані Державної податкової служби
B9: Цифрова економіка в ТГ | C9: Розвиток підприємств ІТ-сектору в ТГ | D9: A.1.3 | E9: % виручки від експорту послуг і товарів, яку отримали СПД, що працюють в ІТ-галузі, від загальної виручки від експорту послуг і товарів (в ТГ) | G9: % | I9: На майбутнє вимірювання | J9: Кількісні дані | L9: =VLOOKUP(D9,'Перелік Iндикаторiв'!$D$4:$M$99,8,FALSE) -> 0 | M9: =VLOOKUP(D9,'Перелік Iндикаторiв'!$D$4:$M$99,9,FALSE) -> 0 | O9: A.1.3.1 | P9: Обсяг доходу від експорту товарів і послуг, отриманого СПД ІТ-галузі, зареєстрованими в ТГ, за звітний рік (ОВ: грн) | Q9: Бал індикатора присвоюється пропорційно до розрахованого значення у відношенні до цільового з кроком 1 бал, де 100 - максимальний бал, коли розраховане значення дорівнює цільовому, 0 - мінімальний бал | R9: Формула розрахунку - [((Показник 1.1/Показник 1.2)*100%], де Показник 1.1 – обсяг доходу від експорту товарів і послуг, отриманого СПД ІТ-галузі, зареєстрованими в ТГ, за звітний рік, грн Показник 1.2 - Загальний обсяг доходу від експорту товарів і послуг, отриманого СПД ІТ-галузі, зареєстрованими в ТГ, за звітний рік, грн | T9: Дохід від експорту ІТ-галузі – вартість операцій із надання товарів і послуг резидентами, зареєстрованими у ТГ, основною діяльністю яких є такі КВЕД: 62.01 Комп’ютерне програмування; 62.02 Консультування з питань інформатизації; 62.09 Інша діяльність у сфері інформаційних технологій і комп'ютерних систем. 58.21 Видання комп'ютерних ігор; 58.29 Видання іншого програмного забезпечення; 63.11 Оброблення даних, розміщення інформації на веб-вузлах і пов’язана з ними діяльність; 18.20 Тиражування звуко-, відеозаписів і програмного забезпечення; 47.41 Роздрібна торгівля комп’ютерами, периферійним устаткуванням і програмним забезпеченням у спеціалізованих магазинах; нерезиденту згідно з договорами (контрактами) або в усній формі договору за датою їх фактичного надання за принципом нарахування (за виписаними рахунками) | U9: за рік | V9: Наказ Державної служби статистики України 03.10.2014 № 284 https://ukrstat.gov.ua/metod_polog/metod_doc/2014/284/284_2014.htm | W9: Дані структурного підрозділу ОМС
B10: Цифрова економіка в ТГ | C10: Розвиток підприємств ІТ-сектору в ТГ | D10: A.1.3 | E10: % виручки від експорту послуг і товарів, яку отримали СПД, що працюють в ІТ-галузі, від загальної виручки від експорту послуг і товарів (в ТГ) | G10: % | I10: На майбутнє вимірювання | J10: Кількісні дані | L10: =VLOOKUP(D10,'Перелік Iндикаторiв'!$D$4:$M$99,8,FALSE) -> 0 | M10: =VLOOKUP(D10,'Перелік Iндикаторiв'!$D$4:$M$99,9,FALSE) -> 0 | O10: A.1.3.2 | P10: Загальний обсяг доходу від експорту товарів і послуг, отриманого СПД, зареєстрованими в ТГ, за звітний рік (ОВ: грн) | Q10: Бал індикатора присвоюється пропорційно до розрахованого значення у відношенні до цільового з кроком 1 бал, де 100 - максимальний бал, коли розраховане значення дорівнює цільовому, 0 - мінімальний бал | R10: Формула розрахунку - [((Показник 1.1/Показник 1.2)*100%], де Показник 1.1 – обсяг доходу від експорту товарів і послуг, отриманого СПД ІТ-галузі, зареєстрованими в ТГ, за звітний рік, грн Показник 1.2 - Загальний обсяг доходу від експорту товарів і послуг, отриманого СПД ІТ-галузі, зареєстрованими в ТГ, за звітний рік, грн | T10: Дохід від експорту – вартість операцій із надання товарів і послуг резидентом, зареєстрованим у ТГ, нерезиденту згідно з договорами (контрактами) або в усній формі договору за датою їх фактичного надання за принципом нарахування (за виписаними рахунками) | U10: за рік | V10: Наказ Державної служби статистики України 03.10.2014 № 284 https://ukrstat.gov.ua/metod_polog/metod_doc/2014/284/284_2014.htm | W10: Дані структурного підрозділу ОМС
B11: Цифрова економіка в ТГ | C11: Розвиток підприємств ІТ-сектору в ТГ | D11: A.1.4 | E11: % виручки від внутрішнього споживання послуг і товарів, яку отримали СПД, що працюють в ІТ-галузі, від загальної виручки від послуг і товарів внутрішнього споживання (статистика) | G11: % | I11: На майбутнє вимірювання | J11: Кількісні дані | L11: =VLOOKUP(D11,'Перелік Iндикаторiв'!$D$4:$M$99,8,FALSE) -> 0 | M11: =VLOOKUP(D11,'Перелік Iндикаторiв'!$D$4:$M$99,9,FALSE) -> 0 | O11: A.1.4.1 | P11: Обсяг доходу від внутрішнього споживання послуг і товарів, отриманого СПД ІТ-галузі, зареєстрованими в ТГ, за звітний рік (ОВ: грн) | Q11: Бал індикатора присвоюється пропорційно до розрахованого значення у відношенні до цільового з кроком 1 бал, де 100 - максимальний бал, коли розраховане значення дорівнює цільовому, 0 - мінімальний бал | R11: Формула розрахунку - [((Показник 1.1/Показник 1.2)*100%], де Показник 1.1 – обсяг доходу від внутрішнього споживання послуг і товарів, отриманого СПД ІТ-галузі, зареєстрованими в ТГ, за звітний рік, грн Показник 1.2 - Загальний обсяг доходу від внутрішнього споживання товарів і послуг, отриманого СПД, зареєстрованими в ТГ, за звітний рік, грн | T11: Дохід від внутрішнього споживання ІТ-галузі – вартість операцій із надання товарів і послуг резидентом, зареєстрованим у ТГ, основною діяльністю якого є нижченаведені КВЕД: 62.01 Комп’ютерне програмування; 62.02 Консультування з питань інформатизації; 62.09 Інша діяльність у сфері інформаційних технологій і комп'ютерних систем. 58.21 Видання комп'ютерних ігор; 58.29 Видання іншого програмного забезпечення; 63.11 Оброблення даних, розміщення інформації на веб-вузлах і пов’язана з ними діяльність; 18.20 Тиражування звуко-, відеозаписів і програмного забезпечення; 47.41 Роздрібна торгівля комп’ютерами, периферійним устаткуванням і програмним забезпеченням у спеціалізованих магазинах; іншому резиденту згідно з договорами (контрактами) або в усній формі договору за датою їх фактичного надання за принципом нарахування (за виписаними рахунками). | U11: за рік | V11: Потребує визначення в законодавстві | W11: Дані структурного підрозділу ОМС
B12: Цифрова економіка в ТГ | C12: Розвиток підприємств ІТ-сектору в ТГ | D12: A.1.4 | E12: % виручки від внутрішнього споживання послуг і товарів, яку отримали СПД, що працюють в ІТ-галузі, від загальної виручки від послуг і товарів внутрішнього споживання (статистика) | G12: % | I12: На майбутнє вимірювання | J12: Кількісні дані | L12: =VLOOKUP(D12,'Перелік Iндикаторiв'!$D$4:$M$99,8,FALSE) -> 0 | M12: =VLOOKUP(D12,'Перелік Iндикаторiв'!$D$4:$M$99,9,FALSE) -> 0 | O12: A.1.4.2 | P12: Загальний обсяг доходу від внутрішнього споживання товарів і послуг, отриманого СПД, зареєстрованими в ТГ, за звітний рік (ОВ: грн) | Q12: Бал індикатора присвоюється пропорційно до розрахованого значення у відношенні до цільового з кроком 1 бал, де 100 - максимальний бал, коли розраховане значення дорівнює цільовому, 0 - мінімальний бал | R12: Формула розрахунку - [(Показник 1.1/Показник 1.2)*100%], де Показник 1.1 – обсяг доходу від внутрішнього споживання послуг і товарів, отриманого СПД ІТ-галузі, зареєстрованими в ТГ, за звітний рік, грн Показник 1.2 - Загальний обсяг доходу від внутрішнього споживання товарів і послуг, отриманий СПД, зареєстрованими в ТГ за звітний рік, грн | T12: Дохід від внутрішнього споживання – вартість операцій із надання товарів і послуг резидентом, зареєстрованим у ТГ, іншому резиденту згідно з договорами (контрактами) або в усній формі договору за датою їх фактичного надання за принципом нарахування (за виписаними рахунками). | U12: за рік | V12: Потребує визначення в законодавстві | W12: Дані структурного підрозділу ОМС
B13: Цифрова економіка в ТГ | C13: Розвиток підприємств ІТ-сектору в ТГ | D13: A.1.5 | E13: % у надходженнях від сплати єдиного податку в бюджет ТГ, що надійшли від CПД з КВЕД ІТ-галузі | F13: Частка у надходженнях від сплати єдиного податку в бюджет ТГ, що надійшли від CПД з КВЕД ІТ-галузі | G13: % | H13: Базовий | I13: Обов'язковий для вимірювання | J13: Кількісні дані | K13: 0.1 | L13: =VLOOKUP(D13,'Перелік Iндикаторiв'!$D$4:$M$99,8,FALSE) -> 0.1 | M13: =VLOOKUP(D13,'Перелік Iндикаторiв'!$D$4:$M$99,9,FALSE) -> 0.15384615 | O13: A.1.5.1 | P13: Обсяг надходжень до бюджету ТГ від сплати єдиного податку СПД в ІТ-галузі за звітний рік (ОВ: грн) | Q13: Бал індикатора присвоюється пропорційно до розрахованого значення у відношенні до цільового з кроком 1 бал, де 100 - максимальний бал, коли розраховане значення дорівнює цільовому, 0 - мінімальний бал | R13: Формула розрахунку - [(Показник 1.1/Показник 1.2)*100%], де Показник 1.1 – обсяг надходжень до бюджету ТГ від сплати єдиного податку СПД ІТ-галузі за звітний рік, грн Показник 1.2 - Загальний обсяг надходжень до бюджету ТГ від сплати єдиного податку СПД за звітний рік, грн | T13: Обсяг надходжень від сплати єдиного податку СПД в ІТ-галузі – обсяг коштів, що надійшли до бюджету ТГ від сплати суб'єктами податку на доходи фізичних осіб суб'єктами підприємницької діяльності, основною діяльністю яких є такі КВЕД: 62.01 Комп’ютерне програмування; 62.02 Консультування з питань інформатизації; 62.09 Інша діяльність у сфері інформаційних технологій і комп'ютерних систем. 58.21 Видання комп'ютерних ігор; 58.29 Видання іншого програмного забезпечення; 63.11 Оброблення даних, розміщення інформації на веб-вузлах і пов’язана з ними діяльність; 18.20 Тиражування звуко-, відеозаписів і програмного забезпечення; 47.41 Роздрібна торгівля комп’ютерами, периферійним устаткуванням і програмним забезпеченням у спеціалізованих магазинах; Обсяг надходжень від сплати єдиного податку – обсяг коштів, що надійшли до бюджету ТГ від сплати суб'єктами єдиного податку за такими кодами класифікації доходів: 18050100 18050200 18050300 18050301 18050400 18050401 18050500 18050501 | U13: за рік | V13: Бюджетний кодекс України https://zakon.rada.gov.ua/laws/show/2456-17#Text Наказ Міністерства фінансів "Про бюджетну класифікацію" №11 від 14 січня 2011 https://zakon.rada.gov.ua/rada/show/v0011201-11#Text | W13: Дані Державної податкової служби
B14: Цифрова економіка в ТГ | C14: Розвиток підприємств ІТ-сектору в ТГ | D14: A.1.5 | E14: % у надходженнях від сплати єдиного податку в бюджет ТГ, що надійшли від CПД з КВЕД ІТ-галузі | G14: % | H14: Базовий | I14: Обов'язковий для вимірювання | J14: Кількісні дані | K14: 0.1 | L14: =VLOOKUP(D14,'Перелік Iндикаторiв'!$D$4:$M$99,8,FALSE) -> 0.1 | M14: =VLOOKUP(D14,'Перелік Iндикаторiв'!$D$4:$M$99,9,FALSE) -> 0.15384615 | O14: A.1.5.2 | P14: Загальний обсяг надходжень до бюджету ТГ від сплати єдиного податку СПД за звітний рік (ОВ: грн) | Q14: Бал індикатора присвоюється пропорційно до розрахованого значення у відношенні до цільового з кроком 1 бал, де 100 - максимальний бал, коли розраховане значення дорівнює цільовому, 0 - мінімальний бал | R14: Формула розрахунку - [(Показник 1.1/Показник 1.2)*100%], де Показник 1.1 – обсяг надходжень до бюджету ТГ від сплати єдиного податку СПД в ІТ-галузі за звітний рік, грн Показник 1.2 - Загальний обсяг надходжень до бюджету ТГ від сплати єдиного податку СПД за звітний рік, грн | T14: Обсяг надходжень від сплати єдиного податку – обсяг коштів, що надійшли до бюджету ТГ від сплати суб'єктами єдиного податку за такими кодами класифікації доходів: 18050100 18050200 18050300 18050301 18050400 18050401 18050500 18050502 | U14: за рік | V14: Бюджетний кодекс України https://zakon.rada.gov.ua/laws/show/2456-17#Text Наказ Міністерства фінансів "Про бюджетну класифікацію" №11 від 14 січня 2011 https://zakon.rada.gov.ua/rada/show/v0011201-11#Text | W14: Дані Державної податкової служби
B15: Цифрова економіка в ТГ | C15: Розвиток підприємств ІТ-сектору в ТГ | D15: A.1.6 | E15: % нових робочих місць, створених у підприємствах ІТ-галузі у загальній кількості нових робочих місць за звітній період | G15: % | H15: Базовий | I15: На майбутнє вимірювання | J15: Кількісні дані | K15: 0.15 | L15: =VLOOKUP(D15,'Перелік Iндикаторiв'!$D$4:$M$99,8,FALSE) -> 0.1 | M15: =VLOOKUP(D15,'Перелік Iндикаторiв'!$D$4:$M$99,9,FALSE) -> 0.14285714 | O15: A.1.6.1 | P15: Кількість створених нових робочих місць в ІТ-галузі у ТГ за звітний період (ОВ: робочих місць) | Q15: Бал індикатора присвоюється пропорційно до розрахованого значення у відношенні до цільового з кроком 1 бал, де 100 - максимальний бал, коли розраховане значення дорівнює цільовому, 0 - мінімальний бал | R15: Формула розрахунку - [((Показник 1.1/Показник 1.2)*100%], де Показник 1.1 - Кількість створених нових робочих місць в ІТ-галузі в ТГ за звітний період, робочих місць Показник 1.2 - Загальна кількість створених нових робочих місць у ТГ за звітний період, робочих місць | T15: Нове робоче місце на підприємствах в ІТ-галузі – утворення штатної кількості працівників у зв’язку зі створенням нового суб’єкта господарювання (окрім створеного шляхом припинення) або збільшенням штатної кількості працівників на підприємствах, основною діяльністю яких є такі КВЕД: 62.01 Комп’ютерне програмування; 62.02 Консультування з питань інформатизації; 62.09 Інша діяльність у сфері інформаційних технологій і комп'ютерних систем. 58.21 Видання комп'ютерних ігор; 58.29 Видання іншого програмного забезпечення; 63.11 Оброблення даних, розміщення інформації на веб-вузлах і пов’язана з ними діяльність; 18.20 Тиражування звуко-, відеозаписів і програмного забезпечення; 47.41 Роздрібна торгівля комп’ютерами, периферійним устаткуванням і програмним забезпеченням у спеціалізованих магазинах; | U15: за рік | V15: Закон України "Про зайнятість населення" https://zakon.rada.gov.ua/laws/show/5067-17#Text | W15: Дані Державної служби зайнятості
B16: Цифрова економіка в ТГ | C16: Розвиток підприємств ІТ-сектору в ТГ | D16: A.1.6 | E16: % нових робочих місць, створених на підприємствах ІТ-галузі від загальної кількості нових робочих місць за звітній період | G16: % | H16: Базовий | I16: На майбутнє вимірювання | J16: Кількісні дані | K16: 0.15 | L16: =VLOOKUP(D16,'Перелік Iндикаторiв'!$D$4:$M$99,8,FALSE) -> 0.1 | M16: =VLOOKUP(D16,'Перелік Iндикаторiв'!$D$4:$M$99,9,FALSE) -> 0.14285714 | O16: A.1.6.2 | P16: Загальна кількість створених нових робочих місць у ТГ за звітний період (ОВ: робочих місць) | Q16: Бал індикатора присвоюється пропорційно до розрахованого значення у відношенні до цільового з кроком 1 бал, де 100 - максимальний бал, коли розраховане значення дорівнює цільовому, 0 - мінімальний бал | R16: Формула розрахунку - [((Показник 1.1/Показник 1.2)*100%], де Показник 1.1 - Кількість створених нових робочих місць в ІТ-галузі в ТГ за звітний період, робочих місць Показник 1.2 - Загальна кількість створених нових робочих місць у ТГ за звітний період, робочих місць | T16: Нове робоче місце – утворення штатної кількості працівників у зв’язку зі створенням нового суб’єкта господарювання (окрім створеного шляхом припинення) або збільшенням штатної кількості працівників за умови, що за попередні 12 місяців середньомісячна чисельність не скорочувалася (не зменшувалася). Новим робоче місце вважається й тоді, коли воно створене шляхом модернізації або зміни технології виробництва, що потребує нових знань та вмінь працівника. | U16: за рік | V16: Закон України "Про зайнятість населення" https://zakon.rada.gov.ua/laws/show/5067-17#Text | W16: Дані Державної служби зайнятості
B17: Цифрова економіка в ТГ | C17: Розвиток підприємств ІТ-сектору в ТГ | D17: A.1.7 | E17: Відношення середньої заробітної плати в ІТ-галузі у ТГ до середньої заробітної плати в ТГ | F17: Відношення середньої заробітної плати в ІТ-галузі у ТГ до середньої заробітної плати в ТГ | G17: % | H17: Базовий | I17: Обов'язковий для вимірювання | J17: Кількісні дані | K17: 1.5 | L17: =VLOOKUP(D17,'Перелік Iндикаторiв'!$D$4:$M$99,8,FALSE) -> 1.5 | M17: =VLOOKUP(D17,'Перелік Iндикаторiв'!$D$4:$M$99,9,FALSE) -> 0.13186813 | O17: A.1.7.1 | P17: Середньомісячна заробітна плата найманих працівників на підприємствах, які провадять діяльність в ІТ-галузі на території ТГ, у звітному році (ОВ: грн) | Q17: Бал індикатора присвоюється пропорційно до розрахованого значення у відношенні до цільового з кроком 1 бал, де 100 - максимальний бал, коли розраховане значення дорівнює цільовому, 0 - мінімальний бал | R17: Формула розрахунку - [(Показник 1.1/Показник 1.2)*100%] де, Показник 1.1 - Середньомісячна заробітна плата найманих працівників на підприємствах, які провадять діяльність в ІТ-галузі на території ТГ, у звітному році, грн Показник 1.2 - Середньомісячна заробітна плата найманих працівників на підприємствах та в організаціях, які провадять діяльність на території ТГ, у звітному році, грн | T17: Середньомісячна (номінальна) заробітна плата працівників ІТ-галузі – обсяг коштів, визначений шляхом ділення нарахованого фонду оплати праці за відповідний період на середньооблікову кількість працівників та на кількість місяців у звітному році, на підприємствах, основною діяльністю яких є такі КВЕД: 62.01 Комп’ютерне програмування; 62.02 Консультування з питань інформатизації; 62.09 Інша діяльність у сфері інформаційних технологій і комп'ютерних систем. 58.21 Видання комп'ютерних ігор; 58.29 Видання іншого програмного забезпечення; 63.11 Оброблення даних, розміщення інформації на веб-вузлах і пов’язана з ними діяльність; 18.20 Тиражування звуко-, відеозаписів і програмного забезпечення; 47.41 Роздрібна торгівля комп’ютерами, периферійним устаткуванням і програмним забезпеченням у спеціалізованих магазинах. | U17: за рік | V17: Наказ Державного комітету статистики України "Про затвердження Інструкції зі статистики заробітної плати" №5 від 13 січня 2004 https://zakon.rada.gov.ua/laws/show/z0114-04#Text | W17: Дані Державної податкової служби
B18: Цифрова економіка в ТГ | C18: Розвиток підприємств ІТ-сектору в ТГ | D18: A.1.7 | E18: Відношення середньої заробітної плати в ІТ-галузі у ТГ до середньої заробітної плати в ТГ | G18: % | H18: Базовий | I18: Обов'язковий для вимірювання | J18: Кількісні дані | K18: 1.5 | L18: =VLOOKUP(D18,'Перелік Iндикаторiв'!$D$4:$M$99,8,FALSE) -> 1.5 | M18: =VLOOKUP(D18,'Перелік Iндикаторiв'!$D$4:$M$99,9,FALSE) -> 0.13186813 | O18: A.1.7.2 | P18: Середньомісячна заробітна плата найманих працівників на підприємствах і в організаціях, які провадять діяльність на території ТГ, у звітному році (ОВ: грн) | Q18: Бал індикатора присвоюється пропорційно до розрахованого значення у відношенні до цільового з кроком 1 бал, де 100 - максимальний бал, коли розраховане значення дорівнює цільовому, 0 - мінімальний бал | R18: Формула розрахунку - [(Показник 1.1/Показник 1.2)*100%] де, Показник 1.1 - Середньомісячна заробітна плата найманих працівників на підприємствах, які провадять діяльність в ІТ-галузі на території ТГ, у звітному році, грн Показник 1.2 - Середньомісячна заробітна плата найманих працівників на підприємствах та в організаціях, які провадять діяльність на території ТГ, у звітному році, грн | T18: Середньомісячна (номінальна) заробітна плата працівників на підприємствах, зареєстрованими в ТГ – обсяг коштів, визначений шляхом ділення нарахованого фонду оплати праці за відповідний період на середньооблікову кількість працівників та на кількість місяців у звітному році. | U18: за рік | V18: Наказ Державного комітету статистики України "Про затвердження Інструкції зі статистики заробітної плати" №5 від 13 січня 2004 https://zakon.rada.gov.ua/laws/show/z0114-04#Text | W18: Дані Державної податкової служби
B19: Цифрова економіка в ТГ | C19: Розвиток підприємств ІТ-сектору в ТГ | D19: A.1.8 | E19: Відношення середньої заробітної плати в ІТ-галузі у ТГ до середньої заробітної плати в ІТ-галузі в Україні | G19: % | H19: Базовий | I19: На майбутнє вимірювання | J19: Кількісні дані | K19: 1.2 | L19: =VLOOKUP(D19,'Перелік Iндикаторiв'!$D$4:$M$99,8,FALSE) -> 1.2 | M19: =VLOOKUP(D19,'Перелік Iндикаторiв'!$D$4:$M$99,9,FALSE) -> 0.13186813 | O19: A.1.8.1 | P19: Середньомісячна заробітна плата найманих працівників на підприємствах, які провадять діяльність в ІТ-галузі на території ТГ (ОВ: грн) | Q19: Бал індикатора присвоюється пропорційно до розрахованого значення у відношенні до цільового з кроком 1 бал, де 100 - максимальний бал, коли розраховане значення дорівнює цільовому, 0 - мінімальний бал | R19: Формула розрахунку - [(Показник 1.1/Показник 1.2)*100%] де, Показник 1.1 - Середньомісячна заробітна плата найманих працівників на підприємствах, які провадять діяльність в ІТ-галузі на території ТГ, грн Показник 1.2 - Середньомісячна заробітна плата найманих працівників на підприємствах, які провадять діяльність в ІТ-галузі на території України, грн | T19: Середньомісячна (номінальна) заробітна плата працівників ІТ-галузі у ТГ – обсяг коштів, визначений шляхом ділення нарахованого фонду оплати праці за відповідний період на середньооблікову кількість працівників та на кількість місяців у звітному році, на підприємствах, основною діяльністю яких є такі КВЕД: 62.01 Комп’ютерне програмування; 62.02 Консультування з питань інформатизації; 62.09 Інша діяльність у сфері інформаційних технологій і комп'ютерних систем. 58.21 Видання комп'ютерних ігор; 58.29 Видання іншого програмного забезпечення; 63.11 Оброблення даних, розміщення інформації на веб-вузлах і пов’язана з ними діяльність; 18.20 Тиражування звуко-, відеозаписів і програмного забезпечення; 47.41 Роздрібна торгівля комп’ютерами, периферійним устаткуванням і програмним забезпеченням у спеціалізованих магазинах; | U19: за рік | V19: Наказ Державного комітету статистики України "Про затвердження Інструкції зі статистики заробітної плати" №5 від 13 січня 2004 https://zakon.rada.gov.ua/laws/show/z0114-04#Text | W19: Дані Державної податкової служби
B20: Цифрова економіка в ТГ | C20: Розвиток підприємств ІТ-сектору в ТГ | D20: A.1.8 | E20: Відношення середньої заробітної плати в ІТ-галузі у ТГ до середньої заробітної плати в ІТ-галузі в Україні | G20: % | H20: Базовий | I20: На майбутнє вимірювання | J20: Кількісні дані | K20: 1.2 | L20: =VLOOKUP(D20,'Перелік Iндикаторiв'!$D$4:$M$99,8,FALSE) -> 1.2 | M20: =VLOOKUP(D20,'Перелік Iндикаторiв'!$D$4:$M$99,9,FALSE) -> 0.13186813 | O20: A.1.8.2 | P20: Середньомісячна заробітна плата найманих працівників на підприємствах, які провадять діяльність в ІТ-галузі на території України (ОВ: грн) | Q20: Бал індикатора присвоюється пропорційно до розрахованого значення у відношенні до цільового з кроком 1 бал, де 100 - максимальний бал, коли розраховане значення дорівнює цільовому, 0 - мінімальний бал | R20: Формула розрахунку - [(Показник 1.1/Показник 1.2)*100%] де, Показник 1.1 - Середньомісячна заробітна плата найманих працівників на підприємствах, які провадять діяльність в ІТ-галузі на території ТГ, грн Показник 1.2 - Середньомісячна заробітна плата найманих працівників на підприємствах, які провадять діяльність в ІТ-галузі на території України, грн | T20: Середньомісячна (номінальна) заробітна плата працівників ІТ-галузі в Україні – обсяг коштів, визначений шляхом ділення нарахованого фонду оплати праці за відповідний період на середньооблікову кількість працівників та на кількість місяців у звітному році, на підприємствах в Україні, основною діяльністю яких є такі КВЕД: 62.01 Комп’ютерне програмування; 62.02 Консультування з питань інформатизації; 62.09 Інша діяльність у сфері інформаційних технологій і комп'ютерних систем. 58.21 Видання комп'ютерних ігор; 58.29 Видання іншого програмного забезпечення; 63.11 Оброблення даних, розміщення інформації на веб-вузлах і пов’язана з ними діяльність; 18.20 Тиражування звуко-, відеозаписів і програмного забезпечення; 47.41 Роздрібна торгівля комп’ютерами, периферійним устаткуванням і програмним забезпеченням у спеціалізованих магазинах; | U20: за рік | V20: Наказ Державного комітету статистики України "Про затвердження Інструкції зі статистики заробітної плати" №5 від 13 січня 2004 https://zakon.rada.gov.ua/laws/show/z0114-04#Text | W20: Дані Державної податкової служби
B21: Цифрова економіка в ТГ | C21: Розвиток підприємств ІТ-сектору в ТГ | D21: A.1.9 | E21: Частка жінок на керівних посадах у підприємствах ІТ-галузі в ТГ | G21: % | I21: На майбутнє вимірювання | J21: Кількісні дані | K21: 0.5 | L21: =VLOOKUP(D21,'Перелік Iндикаторiв'!$D$4:$M$99,8,FALSE) -> 0,5 | M21: =VLOOKUP(D21,'Перелік Iндикаторiв'!$D$4:$M$99,9,FALSE) -> 0 | O21: A.1.9.1 | P21: Працівники жіночої статі, зазначеніi в реєстрi ЄДРПОУ як керівники підприємств в ІТ-галузі (ОВ: осіб) | Q21: Бал індикатора присвоюється пропорційно до розрахованого значення у відношенні до цільового з кроком 1 бал, де 100 - максимальний бал, коли розраховане значення дорівнює цільовому, 0 - мінімальний бал | R21: Формула розрахунку - [(Показник 1.1/Показник 1.2)*100%] де, Показник 1.1 - Працівники жіночої статі, зазначеніi в реєстрi ЄДРПОУ як керівники підприємств у ІТ-галузі, осіб Показник 1.2 - Працівники чоловічої статі, зазначеніi в реєстрi ЄДРПОУ як керівники підприємств у ІТ-галузі, осіб | T21: Працівники жіночої статі, зазначеніi в реєстрi ЄДРПОУ як керівники підприємств в ІТ-галузі – наймані працівниці, займані посади яких пов'язані зі здійсненням різноманітних функцій управління та керівництва та відповідають розділу 1 Класифікатора професій ДК 003:2010 на підприємствах, зареєстрованих на території ТГ, основною діяльністю яких є такі КВЕД: 62.01 Комп’ютерне програмування; 62.02 Консультування з питань інформатизації; 62.09 Інша діяльність у сфері інформаційних технологій і комп'ютерних систем. 58.21 Видання комп'ютерних ігор; 58.29 Видання іншого програмного забезпечення; 63.11 Оброблення даних, розміщення інформації на веб-вузлах і пов’язана з ними діяльність; 18.20 Тиражування звуко-, відеозаписів і програмного забезпечення; 47.41 Роздрібна торгівля комп’ютерами, периферійним устаткуванням і програмним забезпеченням у спеціалізованих магазинах. | U21: станом на 01.01.2022 | V21: Наказ Державного Комітету УКРАЇНИ З ПИТАНЬ ТЕХНІЧНОГО РЕГУЛЮВАННЯ ТА СПОЖИВЧОЇ ПОЛІТИКИ № 327 від 28.07.2010 Про затвердження, внесення зміни та скасування нормативних документів https://zakon.rada.gov.ua/rada/show/v0327609-10#Text | W21: Дані Державної податкової служби
B22: Цифрова економіка в ТГ | C22: Розвиток підприємств ІТ-сектору в ТГ | D22: A.1.9 | E22: Частка жінок на керівних посадах у підприємствах ІТ-галузі в ТГ | G22: % | I22: На майбутнє вимірювання | J22: Кількісні дані | K22: 0.5 | L22: =VLOOKUP(D22,'Перелік Iндикаторiв'!$D$4:$M$99,8,FALSE) -> 0,5 | M22: =VLOOKUP(D22,'Перелік Iндикаторiв'!$D$4:$M$99,9,FALSE) -> 0 | O22: A.1.9.2 | P22: Працівники чоловічої статі, зазначеніi в реєстрi ЄДРПОУ як керівники підприємств в ІТ-галузі (ОВ: осіб) | Q22: Бал індикатора присвоюється пропорційно до розрахованого значення у відношенні до цільового з кроком 1 бал, де 100 - максимальний бал, коли розраховане значення дорівнює цільовому, 0 - мінімальний бал | R22: Формула розрахунку - [(Показник 1.1/Показник 1.2)*100%] де, Показник 1.1 - Працівники жіночої статі, зазначеніi в реєстрi ЄДРПОУ як керівники підприємств в ІТ-галузі, осіб Показник 1.2 - Працівники чоловічої статі, зазначеніi в реєстрi ЄДРПОУ як керівники підприємств в ІТ-галузі, осіб | T22: Працівники чоловічої статі, зазначеніi в реєстрi ЄДРПОУ як керівники підприємств в ІТ-галузі – наймані працівники, займані посади яких пов'язані із здійсненням різноманітних функцій управління та керівництва та відповідають розділу 1 Класифікатора професій ДК 003:2010 на підприємствах, зареєстрованих на території ТГ, основною діяльністю яких є такі КВЕД: 62.01 Комп’ютерне програмування; 62.02 Консультування з питань інформатизації; 62.09 Інша діяльність у сфері інформаційних технологій і комп'ютерних систем. 58.21 Видання комп'ютерних ігор; 58.29 Видання іншого програмного забезпечення; 63.11 Оброблення даних, розміщення інформації на веб-вузлах і пов’язана з ними діяльність; 18.20 Тиражування звуко-, відеозаписів і програмного забезпечення; 47.41 Роздрібна торгівля комп’ютерами, периферійним устаткуванням і програмним забезпеченням у спеціалізованих магазинах; | U22: станом на 01.01.2022 | V22: Наказ Державного Комітету УКРАЇНИ З ПИТАНЬ ТЕХНІЧНОГО РЕГУЛЮВАННЯ ТА СПОЖИВЧОЇ ПОЛІТИКИ № 327 від 28.07.2010 Про затвердження, внесення зміни та скасування нормативних документів https://zakon.rada.gov.ua/rada/show/v0327609-10#Text | W22: Дані Державної податкової служби
B23: Цифрова економіка в ТГ | C23: Розвиток підприємств ІТ-сектору в ТГ | D23: A.1.10 | E23: Частка локальних ІТ підприємств, залучених до програми Дія Сіті, в загальній кількості ІТ-підприємств | G23: % | H23: Базовий | I23: На майбутнє вимірювання | J23: Кількісні дані | K23: 0.005 | L23: =VLOOKUP(D23,'Перелік Iндикаторiв'!$D$4:$M$99,8,FALSE) -> 0.005 | M23: =VLOOKUP(D23,'Перелік Iндикаторiв'!$D$4:$M$99,9,FALSE) -> 0.13186813 | O23: A.1.10.1 | P23: Кількість СПД в ІТ-галузі, залучених до програми Дія Сіті, які є резидентами Дія Сіті (ОВ: резидентів) | Q23: Бал індикатора присвоюється пропорційно до розрахованого значення у відношенні до цільового з кроком 1 бал, де 100 - максимальний бал, коли розраховане значення дорівнює цільовому, 0 - мінімальний бал | R23: Формула розрахунку - [(Показник 1.1/Показник 1.2)*100%] де, Показник 1.1 - Кількість СПД в ІТ-галузі, залучених до програми Дія Сіті, які є резидентами Дія Сіті, СПД Показник 1.2 - Загальна кількість СПД в ІТ-галузі на території ТГ, СПД | T23: Резидент Дія Сіті – юридична особа, яка відповідно до цього Закону набула статусу резидента Дія Сіті та згідно з інформацією, що міститься у реєстрі Дія Сіті, перебуває у зазначеному статусі. | U23: станом на 01.01.2022 | V23: Закон України «Про стимулювання розвитку цифрової економіки в Україні» https://zakon.rada.gov.ua/laws/show/1667-20#Text Закон України «Про внесення змін до Податкового кодексу України щодо стимулювання розвитку цифрової економіки в Україні» https://zakon.rada.gov.ua/laws/show/1946-20#Text | W23: Дані підрозділу Міністерства цифрової трансформації
B24: Цифрова економіка в ТГ | C24: Розвиток підприємств ІТ-сектору в ТГ | D24: A.1.10 | E24: Частка локальних ІТ підприємств, залучених до програми Дія Сіті, в загальній кількості ІТ підприємств | G24: % | H24: Базовий | I24: На майбутнє вимірювання | J24: Кількісні дані | K24: 0.005 | L24: =VLOOKUP(D24,'Перелік Iндикаторiв'!$D$4:$M$99,8,FALSE) -> 0.005 | M24: =VLOOKUP(D24,'Перелік Iндикаторiв'!$D$4:$M$99,9,FALSE) -> 0.13186813 | O24: A.1.10.2 | P24: Загальна кількість СПД в ІТ-галузі на території ТГ (ОВ: СПД) | Q24: Бал індикатора присвоюється пропорційно до розрахованого значення у відношенні до цільового з кроком 1 бал, де 100 - максимальний бал, коли розраховане значення дорівнює цільовому, 0 - мінімальний бал | R24: Формула розрахунку - [(Показник 1.1/Показник 1.2)*100%] де, Показник 1.1 - Кількість СПД в ІТ-галузі, залучених до програми Дія Сіті, які є резидентами Дія Сіті, СПД Показник 1.2 - Загальна кількість СПД в ІТ-галузі на території ТГ, СПД | T24: Суб'єкт підприємницької діяльності в ІТ-галузі – вітчизняні та іноземні юридичні особи, а також фізичні особи-підприємці, які провадять діяльність в Україні та зазначили основним видом діяльності один із нижчезазначених КВЕД: 62.01 Комп’ютерне програмування; 62.02 Консультування з питань інформатизації; 62.09 Інша діяльність у сфері інформаційних технологій і комп'ютерних систем. 58.21 Видання комп'ютерних ігор; 58.29 Видання іншого програмного забезпечення; 63.11 Оброблення даних, розміщення інформації на веб-вузлах і пов’язана з ними діяльність; 18.20 Тиражування звуко-, відеозаписів і програмного забезпечення; 47.41 Роздрібна торгівля комп’ютерами, периферійним устаткуванням і програмним забезпеченням у спеціалізованих магазинах; | U24: станом на 01.01.2022 | V24: Закон України «Про стимулювання розвитку цифрової економіки в Україні» https://zakon.rada.gov.ua/laws/show/1667-20#Text Закон України «Про внесення змін до Податкового кодексу України щодо стимулювання розвитку цифрової економіки в Україні» https://zakon.rada.gov.ua/laws/show/1946-20#Text | W24: Дані Державної податкової служби
B25: Цифрова економіка в ТГ | C25: Розвиток підприємств ІТ-сектору в ТГ | D25: A.1.11 | E25: % стартапів, заснованих на основі використання відкритих даних, до загальної кількості стартапів | G25: % | I25: На майбутнє вимірювання | J25: Кількісні дані | L25: =VLOOKUP(D25,'Перелік Iндикаторiв'!$D$4:$M$99,8,FALSE) -> 0 | M25: =VLOOKUP(D25,'Перелік Iндикаторiв'!$D$4:$M$99,9,FALSE) -> 0 | O25: A.1.11.1 | P25: Кількість стартапів у ТГ, заснованих на основі використання відкритих даних (ОВ: стартапів) | Q25: Бал індикатора присвоюється пропорційно до розрахованого значення у відношенні до цільового з кроком 1 бал, де 100 - максимальний бал, коли розраховане значення дорівнює цільовому, 0 - мінімальний бал | R25: Формула розрахунку - [(Показник 1.1/Показник 1.2)*100%] де, Показник 1.1 - Кількість стартапів у ТГ, заснованих на основі використання відкритих даних, стартапів Показник 1.2 - Загальна кількість стартапів, зареєстрованих у ТГ, стартапів | T25: Публічна інформація у формі відкритих даних – це публічна інформація у форматі, який уможливлює її автоматизоване оброблення електронними засобами, а також забезпечує вільний та безоплатний доступ до неї та її подальше використання. Стартап, заснований на основі використання відкритих даних – це нещодавно створена компанія (іноді навіть ще не юридична особа), яка перебуває на стадії розвитку і будує свою діяльність на основі використання публічної інформації у формі відкритих даних. | U25: станом на 01.01.2022 | V25: Закон України "Про доступ до публічної інформації" https://zakon.rada.gov.ua/laws/show/2939-17#Text | W25: Дані структурного підрозділу ОМС
B26: Цифрова економіка в ТГ | C26: Розвиток підприємств ІТ-сектору в ТГ | D26: A.1.11 | E26: % стартапів, заснованих на основі використання відкритих даних, до загальної кількості стартапів | G26: % | I26: На майбутнє вимірювання | J26: Кількісні дані | L26: =VLOOKUP(D26,'Перелік Iндикаторiв'!$D$4:$M$99,8,FALSE) -> 0 | M26: =VLOOKUP(D26,'Перелік Iндикаторiв'!$D$4:$M$99,9,FALSE) -> 0 | O26: A.1.11.2 | P26: Загальна кількість стартапів, зареєстрованих у ТГ (ОВ: стартапів) | Q26: Бал індикатора присвоюється пропорційно до розрахованого значення у відношенні до цільового з кроком 1 бал, де 100 - максимальний бал, коли розраховане значення дорівнює цільовому, 0 - мінімальний бал | R26: Формула розрахунку - [(Показник 1.1/Показник 1.2)*100%] де, Показник 1.1 - Кількість стартапів у ТГ, заснованих на основі використання відкритих даних, стартапів Показник 1.2 - Загальна кількість стартапів, зареєстрованих у ТГ, стартапів | T26: Стартап – це нещодавно створена компанія (іноді навіть ще не юридична особа), яка перебуває на стадії розвитку і будує свій бізнес або на основі нових інноваційних ідей, або на основі новітніх технологій. | U26: станом на 01.01.2022 | V26: Закон України "Про доступ до публічної інформації" https://zakon.rada.gov.ua/laws/show/2939-17#Text | W26: Дані структурного підрозділу ОМС
B27: Цифрова економіка в ТГ | C27: Привабливість для інвестицій в галузь ІТ | D27: A.2.1 | E27: % залучених капітальних інвестицій в ІТ-галузі від загального обсягу інвестицій у підприємства у ТГ | G27: % | I27: На майбутнє вимірювання | J27: Кількісні дані | L27: =VLOOKUP(D27,'Перелік Iндикаторiв'!$D$4:$M$99,8,FALSE) -> 0 | M27: =VLOOKUP(D27,'Перелік Iндикаторiв'!$D$4:$M$99,9,FALSE) -> 0 | O27: A.2.1.1 | P27: Сума капітальних інвестицій, здійснених СПД в ІТ-галузі (ОВ: грн) | Q27: Бал індикатора присвоюється пропорційно до розрахованого значення у відношенні до цільового з кроком 1 бал, де 100 - максимальний бал, коли розраховане значення дорівнює цільовому, 0 - мінімальний бал | R27: Формула розрахунку - [(Показник 1.1/Показник 1.2)*100%], де Показник 1.1 - Сума капітальних інвестицій, здійснених СПД в ІТ-галузі, млн грн Показник 1.2 - Сума капітальних інвестицій, здійснених СПД, зареєстрованими на території ТГ, млн грн | T27: Капітальні інвестиції – витрати на придбання або виготовлення (створення) матеріальних і нематеріальних необоротних активів. Капітальні інвестиції обліковуються підприємствами-юридичними особами за їхнім основним видом економічної діяльності та територією місцезнаходження (юридичною адресою). Суб'єкти підприємницької діяльності в ІТ-галузі – суб'єкти підприємницької діяльності, що на території ТГ отримали послугу державної реєстрації суб'єкта підприємницької діяльності відповідно до Розділу 4 Закону України "Про державну реєстрацію юридичних осіб, фізичних осіб-підприємців та громадських формувань" та зазначили основним видом діяльності один із нижчезазначених (але не обмежуючись) КВЕД: 62.01 Комп’ютерне програмування; 62.02 Консультування з питань інформатизації; 62.09 Інша діяльність у сфері інформаційних технологій і комп'ютерних систем. 58.21 Видання комп'ютерних ігор; 58.29 Видання іншого програмного забезпечення; 63.11 Оброблення даних, розміщення інформації на веб-вузлах і пов’язана з ними діяльність; 18.20 Тиражування звуко-, відеозаписів і програмного забезпечення; 47.41 Роздрібна торгівля комп’ютерами, периферійним устаткуванням і програмним забезпеченням у спеціалізованих магазинах; | U27: за рік | V27: Закон України "Про інвестиційну діяльність" | W27: Дані з Державної служби статистики
B28: Цифрова економіка в ТГ | C28: Привабливість для інвестицій в галузь ІТ | D28: A.2.1 | E28: % залучених капітальних інвестицій в ІТ-галузі від загального обсягу інвестицій у підприємства у ТГ | G28: % | I28: На майбутнє вимірювання | J28: Кількісні дані | L28: =VLOOKUP(D28,'Перелік Iндикаторiв'!$D$4:$M$99,8,FALSE) -> 0 | M28: =VLOOKUP(D28,'Перелік Iндикаторiв'!$D$4:$M$99,9,FALSE) -> 0 | O28: A.2.1.2 | P28: Сума капітальних інвестицій, здійснених СПД, зареєстрованими на території ТГ (ОВ: грн) | Q28: Бал індикатора присвоюється пропорційно до розрахованого значення у відношенні до цільового з кроком 1 бал, де 100 - максимальний бал, коли розраховане значення дорівнює цільовому, 0 - мінімальний бал | R28: Формула розрахунку - [(Показник 1.1/Показник 1.2)*100%], де Показник 1.1 - Сума капітальних інвестицій, здійснених СПД в ІТ-галузі, млн грн Показник 1.2 - Сума капітальних інвестицій, здійснених СПД, зареєстрованими на території ТГ, млн грн | T28: Капітальні інвестиції – витрати на придбання або виготовлення (створення) матеріальних і нематеріальних необоротних активів. Капітальні інвестиції обліковуються підприємствами-юридичними особами за їхнім основним видом економічної діяльності та територією місцезнаходження (юридичною адресою). Суб'єкти підприємницької діяльності – суб'єкти підприємницької діяльності, що на території ТГ отримали послугу державної реєстрації суб'єкта підприємницької діяльності відповідно до Розділу 4 Закону України "Про державну реєстрацію юридичних осіб, фізичних осіб-підприємців та громадських формувань" | U28: за рік | V28: Закон України "Про інвестиційну діяльність" | W28: Дані з Державної служби статистики
B29: Цифрова економіка в ТГ | C29: Привабливість для інвестицій в галузь ІТ | D29: A.2.2 | E29: Кількість робочих місць в ІТ-хабах, які можуть орендувати/де можуть працювати ІТ-спеціалісти, на 1 тис. населення | F29: Кількість робочих місць в ІТ-хабах, що можуть орендувати/де можуть працювати ІТ-спеціалісти, на 1 тис населення | G29: од/1000 населення | H29: Базовий | I29: Обов'язковий для вимірювання | J29: Кількісні дані | K29: 2 | L29: =VLOOKUP(D29,'Перелік Iндикаторiв'!$D$4:$M$99,8,FALSE) -> 2 | M29: =VLOOKUP(D29,'Перелік Iндикаторiв'!$D$4:$M$99,9,FALSE) -> 0.19791667 | O29: A.2.2.1 | P29: Максимальна кількість місць в ІТ-хабах (ОВ: одиниць) | Q29: Бал індикатора присвоюється пропорційно до розрахованого значення у відношенні до цільового з кроком 1 бал, де 100 - максимальний бал, коли розраховане значення дорівнює цільовому, 0 - мінімальний бал | R29: Формула розрахунку - [(Показник 1.1/Показник 1.2)*1000], де Показник 1.1 - Максимальна кількість місць в ІТ-хабах, одиниць Показник 1.2 - Загальна чисельність наявного населення у ТГ, осіб | T29: ІТ-хаби – це заклади, які надають послуги для спільної роботи, проведення заходів та бізнес-Закон України стрічей для працівників в ІТ-секторі. Максимальна кількість місць в ІТ-хабах – кількість відвідувачів, які одночасно в комфортних умовах можуть перебувати в ІТ-хабі | U29: станом на 01.01.2022 | V29: Потребує визначення в законодавстві | W29: Дані структурного підрозділу ОМС
B30: Цифрова економіка в ТГ | C30: Привабливість для інвестицій в галузь ІТ | D30: A.2.2 | E30: Кількість робочих місць в ІТ-хабах, які можуть орендувати/де можуть працювати ІТ-спеціалісти, на 1 тис. населення | G30: од/1000 населення | H30: Базовий | I30: Обов'язковий для вимірювання | J30: Кількісні дані | K30: 2 | L30: =VLOOKUP(D30,'Перелік Iндикаторiв'!$D$4:$M$99,8,FALSE) -> 2 | M30: =VLOOKUP(D30,'Перелік Iндикаторiв'!$D$4:$M$99,9,FALSE) -> 0.19791667 | O30: A.2.2.2 | P30: Загальна кількість осіб, місце проживання яких зареєстровано у ТГ (ОВ: осіб) | Q30: Бал індикатора присвоюється пропорційно до розрахованого значення у відношенні до цільового з кроком 1 бал, де 100 - максимальний бал, коли розраховане значення дорівнює цільовому, 0 - мінімальний бал | R30: Формула розрахунку - [(Показник 1.1/Показник 1.2)*1000], де Показник 1.1 - Максимальна кількість місць в ІТ-хабах, одиниць Показник 1.2 - Загальна кількість осіб, місце проживання яких зареєстровано в ТГ, осіб | T30: Реєстрація місця проживання (перебування) особи – це внесення за заявою про реєстрацію місця проживання (перебування), поданою особою в паперовій формі, до реєстру територіальної громади інформації про місце проживання (перебування) особи. | U30: станом на 01.01.2022 | V30: Потребує визначення в законодавстві | W30: Дані підрозділу Міграційної служби
B31: Цифрова економіка в ТГ | C31: Привабливість для інвестицій в галузь ІТ | D31: A.2.3 | E31: Наявність та актуальність інформації про інвестиційні об'єкти ТГ | F31: Наявність та актуальність інформації про інвестиційні об'єкти ТГ | G31: Бал | H31: Базовий | I31: Обов'язковий для вимірювання | J31: Якісні дані | K31: 1 | L31: =VLOOKUP(D31,'Перелік Iндикаторiв'!$D$4:$M$99,8,FALSE) -> 1 | M31: =VLOOKUP(D31,'Перелік Iндикаторiв'!$D$4:$M$99,9,FALSE) -> 0.19791667 | O31: A.2.3.1 | P31: Наявність на офіційних ресурсах ОМС інформації про інвестиційні об'єкти, яка була оновлена протягом звітного року (ОВ: Так/Ні) | Q31: 0 - балів, якщо на офіційних ресурсах ОМС відсутня інформація про інвестиційні об'єкти та/або якщо інформація не оновлювалась у звітному році 0.5 - бал, якщо на офіційних ресурсах ОМС наявна інформація про інвестиційні об'єкти та була оновлена протягом звітного року 0.5 - бал, якщо на офіційних ресурсах ОМС наявна інформація про інвестиційні об'єкти у вигляді шару ГІС та була оновлена протягом звітного року | R31: Формула розрахунку - [Показник 1.1+Показник 1.2], де Показник 1.1 - Наявність на офіційних ресурсах ОМС інформації про інвестиційні об'єкти, яка була оновлена протягом звітного року, Так-0.5 бала, Ні-0 балів Показник 1.2 - Наявність на офіційних ресурсах ОМС інформації про інвестиційні об'єкти у вигляді шару ГІС, яка була оновлена протягом звітного року, Так-0.5 бала, Ні-0 балів | T31: Об'єктами інвестиційної діяльності може бути будь-яке майно, зокрема основні фонди й оборотні кошти, в усіх галузях економіки, цінні папери (крім векселів), цільові грошові вклади, науково-технічна продукція, інтелектуальні цінності, інші об'єкти власності, а також майнові права. | U31: станом на 01.01.2022 | V31: Закон України "Про доступ до публічної інформації" | W31: Дані структурного підрозділу ОМС
B32: Цифрова економіка в ТГ | C32: Привабливість для інвестицій в галузь ІТ | D32: A.2.3 | E32: Наявність та актуальність інформації про інвестиційні об'єкти ТГ | G32: Бал | H32: Базовий | I32: Обов'язковий для вимірювання | J32: Якісні дані | K32: 1 | L32: =VLOOKUP(D32,'Перелік Iндикаторiв'!$D$4:$M$99,8,FALSE) -> 1 | M32: =VLOOKUP(D32,'Перелік Iндикаторiв'!$D$4:$M$99,9,FALSE) -> 0.19791667 | O32: A.2.3.2 | P32: Наявність на офіційних ресурсах ОМС інформації про інвестиційні об'єкти у вигляді шару ГІС, яка була оновлена протягом звітного року (ОВ: Так/Ні) | Q32: 0 - балів, якщо на офіційних ресурсах ОМС відсутня інформація про інвестиційні об'єкти та/або якщо інформація не оновлювалась у звітному році 0.5 - бал, якщо на офіційних ресурсах ОМС наявна інформація про інвестиційні об'єкти та була оновлена протягом звітного року 0.5 - бал, якщо на офіційних ресурсах ОМС наявна інформація про інвестиційні об'єкти у вигляді шару ГІС та була оновлена протягом звітного року | R32: Формула розрахунку - [Показник 1.1+Показник 1.2], де Показник 1.1 - Наявність на офіційних ресурсах ОМС інформації про інвестиційні об'єкти, яка була оновлена протягом звітного року, Так-0.5 бала, Ні-0 балів Показник 1.2 - Наявність на офіційних ресурсах ОМС інформації про інвестиційні об'єкти у вигляді шару ГІС, яка була оновлена протягом звітного року, Так-0.5 бала, Ні-0 балів | T32: Об'єктами інвестиційної діяльності може бути будь-яке майно, зокрема основні фонди й оборотні кошти, в усіх галузях економіки, цінні папери (крім векселів), цільові грошові вклади, науково-технічна продукція, інтелектуальні цінності, інші об'єкти власності, а також майнові права. | U32: станом на 01.01.2022 | V32: Закон України "Про доступ до публічної інформації" | W32: Дані структурного підрозділу ОМС
B33: Цифрова економіка в ТГ | C33: Привабливість для інвестицій в галузь ІТ | D33: A.2.4 | E33: % випускників вищих навчальних закладів (крім коледжів) за спеціальностями в ІТ-галузі від загальної кількості випускників | F33: Частка випускників ЗВО (крім коледжів) за спеціальностями в ІТ-галузі від загальної кількості випускників | G33: % | H33: Розширений | I33: Обов'язковий для вимірювання | J33: Кількісні дані | K33: 0.2 | L33: =VLOOKUP(D33,'Перелік Iндикаторiв'!$D$4:$M$99,8,FALSE) -> 0.1 | M33: =VLOOKUP(D33,'Перелік Iндикаторiв'!$D$4:$M$99,9,FALSE) -> 0.33333333 | O33: A.2.4.1 | P33: Випускники вищих навчальних закладів за спеціальностями в ІТ-галузі очної форми навчання (ОВ: осіб) | Q33: Бал індикатора присвоюється пропорційно до розрахованого значення у відношенні до цільового з кроком 1 бал, де 100 - максимальний бал, коли розраховане значення дорівнює цільовому, 0 - мінімальний бал | R33: Формула розрахунку - [(Показник 1.1+Показник 1.2+Показник 1.3)/(Показник 1.4+Показник 1.5+Показник 1.6)*100%], де Показник 1.1 - Випускники вищих навчальних закладів за спеціальностями в ІТ-галузі очної форми навчання, осіб Показник 1.2 - Випускники вищих навчальних закладів за спеціальностями в ІТ-галузі заочної форми навчання, осіб Показник 1.3 - Випускники вищих навчальних закладів за спеціальностями в ІТ-галузі вечірньої форми навчання, осіб Показник 1.4 - Загальна кількість випускників вищих навчальних закладів очної форми навчання, осіб Показник 1.5 - Загальна кількість випускників вищих навчальних закладів заочної форми навчання, осіб Показник 1.6 - Загальна кількість випускників вищих навчальних закладів вечірньої форми навчання, осіб | T33: Випускники вищих навчальних закладів очної форми навчання в ІТ-галузі – особи, що навчаються за спеціальностями згідно з визначеним переліком галузей знань і спеціальностей, за якими здійснюється підготовка здобувачів вищої освіти в нижченаведених напрямах: 111 Математика 113 Прикладна математика 12 Інформаційні технології 151 Автоматизація та комп’ютерно-інтегровані технології, | U33: станом на 01.01.2022 | V33: Постанова КМУ від 29 квітня 2015 р. № 266 "Про затвердження переліку галузей знань і спеціальностей, за якими здійснюється підготовка здобувачів вищої освіти" | W33: Дані підрозділу Міністерства освіти і науки
B34: Цифрова економіка в ТГ | C34: Привабливість для інвестицій в галузь ІТ | D34: A.2.4 | E34: % випускників вищих навчальних закладів (крім коледжів) за спеціальностями в ІТ-галузі від загальної кількості випускників | G34: % | H34: Розширений | I34: Обов'язковий для вимірювання | J34: Кількісні дані | K34: 0.2 | L34: =VLOOKUP(D34,'Перелік Iндикаторiв'!$D$4:$M$99,8,FALSE) -> 0.1 | M34: =VLOOKUP(D34,'Перелік Iндикаторiв'!$D$4:$M$99,9,FALSE) -> 0.33333333 | O34: A.2.4.2 | P34: Випускники вищих навчальних закладів за спеціальностями в ІТ-галузі заочної форми навчання (ОВ: осіб) | Q34: Бал індикатора присвоюється пропорційно до розрахованого значення у відношенні до цільового з кроком 1 бал, де 100 - максимальний бал, коли розраховане значення дорівнює цільовому, 0 - мінімальний бал | R34: Формула розрахунку - [(Показник 1.1+Показник 1.2+Показник 1.3)/(Показник 1.4+Показник 1.5+Показник 1.6)*100%], де Показник 1.1 - Випускники вищих навчальних закладів за спеціальностями в ІТ-галузі очної форми навчання, осіб Показник 1.2 - Випускники вищих навчальних закладів за спеціальностями в ІТ-галузі заочної форми навчання, осіб Показник 1.3 - Випускники вищих навчальних закладів за спеціальностями в ІТ-галузі вечірньої форми навчання, осіб Показник 1.4 - Загальна кількість випускників вищих навчальних закладів очної форми навчання, осіб Показник 1.5 - Загальна кількість випускників вищих навчальних закладів заочної форми навчання, осіб Показник 1.6 - Загальна кількість випускників вищих навчальних закладів вечірньої форми навчання, осіб | T34: Випускники вищих навчальних закладів заочної форми навчання в ІТ-галузі – особи, що навчаються за спеціальностями згідно з визначеним переліком галузей знань і спеціальностей, за якими здійснюється підготовка здобувачів вищої освіти в нижченаведених напрямах: 111 Математика 113 Прикладна математика 12 Інформаційні технології 151 Автоматизація та комп’ютерно-інтегровані технології, | U34: станом на 01.01.2022 | V34: Постанова КМУ від 29 квітня 2015 р. № 266 "Про затвердження переліку галузей знань і спеціальностей, за якими здійснюється підготовка здобувачів вищої освіти" | W34: Дані підрозділу Міністерства освіти і науки
B35: Цифрова економіка в ТГ | C35: Привабливість для інвестицій в галузь ІТ | D35: A.2.4 | E35: % випускників вищих навчальних закладів (крім коледжів) за спеціальностями в ІТ-галузі від загальної кількості випускників | G35: % | H35: Розширений | I35: Обов'язковий для вимірювання | J35: Кількісні дані | K35: 0.2 | L35: =VLOOKUP(D35,'Перелік Iндикаторiв'!$D$4:$M$99,8,FALSE) -> 0.1 | M35: =VLOOKUP(D35,'Перелік Iндикаторiв'!$D$4:$M$99,9,FALSE) -> 0.33333333 | O35: A.2.4.3 | P35: Випускники вищих навчальних закладів за спеціальностями в ІТ-галузі вечірньої форми навчання (ОВ: осіб) | Q35: Бал індикатора присвоюється пропорційно до розрахованого значення у відношенні до цільового з кроком 1 бал, де 100 - максимальний бал, коли розраховане значення дорівнює цільовому, 0 - мінімальний бал | R35: Формула розрахунку - [(Показник 1.1+Показник 1.2+Показник 1.3)/(Показник 1.4+Показник 1.5+Показник 1.6)*100%], де Показник 1.1 - Випускники вищих навчальних закладів за спеціальностями в ІТ-галузі очної форми навчання, осіб Показник 1.2 - Випускники вищих навчальних закладів за спеціальностями в ІТ-галузі заочної форми навчання, осіб Показник 1.3 - Випускники вищих навчальних закладів за спеціальностями в ІТ-галузі вечірньої форми навчання, осіб Показник 1.4 - Загальна кількість випускників вищих навчальних закладів очної форми навчання, осіб Показник 1.5 - Загальна кількість випускників вищих навчальних закладів заочної форми навчання, осіб Показник 1.6 - Загальна кількість випускників вищих навчальних закладів вечірньої форми навчання, осіб | T35: Випускники вищих навчальних закладів вечірньої форми навчання в ІТ-галузі – особи, що навчаються за спеціальностями згідно з визначеним переліком галузей знань і спеціальностей, за якими здійснюється підготовка здобувачів вищої освіти в нижченаведених напрямах: 111 Математика 113 Прикладна математика 12 Інформаційні технології 151 Автоматизація та комп’ютерно-інтегровані технології | U35: станом на 01.01.2022 | V35: Постанова КМУ від 29 квітня 2015 р. № 266 "Про затвердження переліку галузей знань і спеціальностей, за якими здійснюється підготовка здобувачів вищої освіти" | W35: Дані підрозділу Міністерства освіти і науки
B36: Цифрова економіка в ТГ | C36: Привабливість для інвестицій в галузь ІТ | D36: A.2.4 | E36: % випускників вищих навчальних закладів (крім коледжів) за спеціальностями в ІТ-галузі від загальної кількості випускників | G36: % | H36: Розширений | I36: Обов'язковий для вимірювання | J36: Кількісні дані | K36: 0.2 | L36: =VLOOKUP(D36,'Перелік Iндикаторiв'!$D$4:$M$99,8,FALSE) -> 0.1 | M36: =VLOOKUP(D36,'Перелік Iндикаторiв'!$D$4:$M$99,9,FALSE) -> 0.33333333 | O36: A.2.4.4 | P36: Загальна кількість випускників вищих навчальних закладів очної форми навчання (ОВ: осіб) | Q36: Бал індикатора присвоюється пропорційно до розрахованого значення у відношенні до цільового з кроком 1 бал, де 100 - максимальний бал, коли розраховане значення дорівнює цільовому, 0 - мінімальний бал | R36: Формула розрахунку - [(Показник 1.1+Показник 1.2+Показник 1.3)/(Показник 1.4+Показник 1.5+Показник 1.6)*100%], де Показник 1.1 - Випускники вищих навчальних закладів за спеціальностями в ІТ-галузі очної форми навчання, осіб Показник 1.2 - Випускники вищих навчальних закладів за спеціальностями в ІТ-галузі заочної форми навчання, осіб Показник 1.3 - Випускники вищих навчальних закладів за спеціальностями в ІТ-галузі вечірньої форми навчання, осіб Показник 1.4 - Загальна кількість випускників вищих навчальних закладів очної форми навчання, осіб Показник 1.5 - Загальна кількість випускників вищих навчальних закладів заочної форми навчання, осіб Показник 1.6 - Загальна кількість випускників вищих навчальних закладів вечірньої форми навчання, осіб | T36: Усі випускники вищих навчальних закладів освіти очної форми навчання | U36: станом на 01.01.2022 | V36: Постанова КМУ від 29 квітня 2015 р. № 266 "Про затвердження переліку галузей знань і спеціальностей, за якими здійснюється підготовка здобувачів вищої освіти" | W36: Дані підрозділу Міністерства освіти і науки
B37: Цифрова економіка в ТГ | C37: Привабливість для інвестицій в галузь ІТ | D37: A.2.4 | E37: % випускників вищих навчальних закладів (крім коледжів) за спеціальностями в ІТ-галузі від загальної кількості випускників | G37: % | H37: Розширений | I37: Обов'язковий для вимірювання | J37: Кількісні дані | K37: 0.2 | L37: =VLOOKUP(D37,'Перелік Iндикаторiв'!$D$4:$M$99,8,FALSE) -> 0.1 | M37: =VLOOKUP(D37,'Перелік Iндикаторiв'!$D$4:$M$99,9,FALSE) -> 0.33333333 | O37: A.2.4.5 | P37: Загальна кількість випускників вищих навчальних закладів заочної форми навчання (ОВ: осіб) | Q37: Бал індикатора присвоюється пропорційно до розрахованого значення у відношенні до цільового з кроком 1 бал, де 100 - максимальний бал, коли розраховане значення дорівнює цільовому, 0 - мінімальний бал | R37: Формула розрахунку - [(Показник 1.1+Показник 1.2+Показник 1.3)/(Показник 1.4+Показник 1.5+Показник 1.6)*100%], де Показник 1.1 - Випускники вищих навчальних закладів за спеціальностями в ІТ-галузі очної форми навчання, осіб Показник 1.2 - Випускники вищих навчальних закладів за спеціальностями в ІТ-галузі заочної форми навчання, осіб Показник 1.3 - Випускники вищих навчальних закладів за спеціальностями в ІТ-галузі вечірньої форми навчання, осіб Показник 1.4 - Загальна кількість випускників вищих навчальних закладів очної форми навчання, осіб Показник 1.5 - Загальна кількість випускників вищих навчальних закладів заочної форми навчання, осіб Показник 1.6 - Загальна кількість випускників вищих навчальних закладів вечірньої форми навчання, осіб | T37: Усі випускники вищих навчальних закладів освіти заочної форми навчання | U37: станом на 01.01.2022 | V37: Постанова КМУ від 29 квітня 2015 р. № 266 "Про затвердження переліку галузей знань і спеціальностей, за якими здійснюється підготовка здобувачів вищої освіти" | W37: Дані підрозділу Міністерства освіти і науки
B38: Цифрова економіка в ТГ | C38: Привабливість для інвестицій в галузь ІТ | D38: A.2.4 | E38: % випускників вищих навчальних закладів (крім коледжів) за спеціальностями в ІТ-галузі від загальної кількості випускників | G38: % | H38: Розширений | I38: Обов'язковий для вимірювання | J38: Кількісні дані | K38: 0.2 | L38: =VLOOKUP(D38,'Перелік Iндикаторiв'!$D$4:$M$99,8,FALSE) -> 0.1 | M38: =VLOOKUP(D38,'Перелік Iндикаторiв'!$D$4:$M$99,9,FALSE) -> 0.33333333 | O38: A.2.4.6 | P38: Загальна кількість випускників вищих навчальних закладів вечірньої форми навчання (ОВ: осіб) | Q38: Бал індикатора присвоюється пропорційно до розрахованого значення у відношенні до цільового з кроком 1 бал, де 100 - максимальний бал, коли розраховане значення дорівнює цільовому, 0 - мінімальний бал | R38: Формула розрахунку - [(Показник 1.1+Показник 1.2+Показник 1.3)/(Показник 1.4+Показник 1.5+Показник 1.6)*100%], де Показник 1.1 - Випускники вищих навчальних закладів за спеціальностями в ІТ-галузі очної форми навчання, осіб Показник 1.2 - Випускники вищих навчальних закладів за спеціальностями в ІТ-галузі заочної форми навчання, осіб Показник 1.3 - Випускники вищих навчальних закладів за спеціальностями в ІТ-галузі вечірньої форми навчання, осіб Показник 1.4 - Загальна кількість випускників вищих навчальних закладів очної форми навчання, осіб Показник 1.5 - Загальна кількість випускників вищих навчальних закладів заочної форми навчання, осіб Показник 1.6 - Загальна кількість випускників вищих навчальних закладів вечірньої форми навчання, осіб | T38: Усі випускники вищих навчальних закладів освіти вечірньої форми навчання | U38: станом на 01.01.2022 | V38: Постанова КМУ від 29 квітня 2015 р. № 266 "Про затвердження переліку галузей знань і спеціальностей, за якими здійснюється підготовка здобувачів вищої освіти" | W38: Дані підрозділу Міністерства освіти і науки
B39: Цифрова економіка в ТГ | C39: Привабливість для інвестицій в галузь ІТ | D39: A.2.5 | E39: % випускників коледжів за спеціальностями в ІТ-галузі від загальної кількості випускників | F39: Частка випускників коледжів за спеціальностями в ІТ-галузі від загальної кількості випускників | G39: % | H39: Розширений | I39: Обов'язковий для вимірювання | J39: Кількісні дані | K39: 0.2 | L39: =VLOOKUP(D39,'Перелік Iндикаторiв'!$D$4:$M$99,8,FALSE) -> 0.1 | M39: =VLOOKUP(D39,'Перелік Iндикаторiв'!$D$4:$M$99,9,FALSE) -> 0.27083333 | O39: A.2.5.1 | P39: Випускники коледжів за спеціальностями в ІТ-галузі очної форми навчання (ОВ: осіб) | Q39: Бал індикатора присвоюється пропорційно до розрахованого значення у відношенні до цільового з кроком 1 бал, де 100 - максимальний бал, коли розраховане значення дорівнює цільовому, 0 - мінімальний бал | R39: Формула розрахунку - [(Показник 1.1+Показник 1.2+Показник 1.3)/(Показник 1.4+Показник 1.5+Показник 1.6)*100%], де Показник 1.1 - Випускники коледжів за спеціальностями в ІТ-галузі очної форми навчання, осіб Показник 1.2 - Випускники коледжів за спеціальностями в ІТ-галузі заочної форми навчання, осіб Показник 1.3 - Випускники коледжів за спеціальностями в ІТ-галузі вечірньої форми навчання, осіб Показник 1.4 - Загальна кількість випускників коледжів очної форми навчання, осіб Показник 1.5 - Загальна кількість випускників Коледжів заочної форми навчання, осіб Показник 1.6 - Загальна кількість випускників коледжів вечірньої форми навчання, осіб | T39: Випускники коледжів очної форми навчання в ІТ-галузі – особи, що навчаються за спеціальностями згідно з визначеним переліком галузей знань і спеціальностей, за якими здійснюється підготовка здобувачів вищої освіти в нижченаведених напрямах: 111 Математика 113 Прикладна математика 12 Інформаційні технології 151 Автоматизація та комп’ютерно-інтегровані технології, | U39: станом на 01.01.2022 | V39: Постанова КМУ від 29 квітня 2015 р. № 266 "Про затвердження переліку галузей знань і спеціальностей, за якими здійснюється підготовка здобувачів вищої освіти" | W39: Дані підрозділу Міністерства освіти і науки
B40: Цифрова економіка в ТГ | C40: Привабливість для інвестицій в галузь ІТ | D40: A.2.5 | E40: % випускників коледжів за спеціальностями в ІТ-галузі від загальної кількості випускників | G40: % | H40: Розширений | I40: Обов'язковий для вимірювання | J40: Кількісні дані | K40: 0.2 | L40: =VLOOKUP(D40,'Перелік Iндикаторiв'!$D$4:$M$99,8,FALSE) -> 0.1 | M40: =VLOOKUP(D40,'Перелік Iндикаторiв'!$D$4:$M$99,9,FALSE) -> 0.27083333 | O40: A.2.5.2 | P40: Випускники коледжів за спеціальностями в ІТ-галузі заочної форми навчання (ОВ: осіб) | Q40: Бал індикатора присвоюється пропорційно до розрахованого значення у відношенні до цільового з кроком 1 бал, де 100 - максимальний бал, коли розраховане значення дорівнює цільовому, 0 - мінімальний бал | R40: Формула розрахунку - [(Показник 1.1+Показник 1.2+Показник 1.3)/(Показник 1.4+Показник 1.5+Показник 1.6)*100%], де Показник 1.1 - Випускники коледжів за спеціальностями в ІТ-галузі очної форми навчання, осіб Показник 1.2 - Випускники коледжів за спеціальностями в ІТ-галузі заочної форми навчання, осіб Показник 1.3 - Випускники коледжів за спеціальностями в ІТ-галузі вечірньої форми навчання, осіб Показник 1.4 - Загальна кількість випускників коледжів очної форми навчання, осіб Показник 1.5 - Загальна кількість випускників Коледжів заочної форми навчання, осіб Показник 1.6 - Загальна кількість випускників коледжів вечірньої форми навчання, осіб | T40: Випускники коледжів заочної форми навчання в ІТ-галузі – особи, що навчаються за спеціальностями згідно з визначеним переліком галузей знань і спеціальностей, за якими здійснюється підготовка здобувачів вищої освіти в нижченаведених напрямах: 111 Математика 113 Прикладна математика 12 Інформаційні технології 151 Автоматизація та комп’ютерно-інтегровані технології, | U40: станом на 01.01.2022 | V40: Постанова КМУ від 29 квітня 2015 р. № 266 "Про затвердження переліку галузей знань і спеціальностей, за якими здійснюється підготовка здобувачів вищої освіти" | W40: Дані підрозділу Міністерства освіти і науки
B41: Цифрова економіка в ТГ | C41: Привабливість для інвестицій в галузь ІТ | D41: A.2.5 | E41: % випускників коледжів за спеціальностями в ІТ-галузі від загальної кількості випускників | G41: % | H41: Розширений | I41: Обов'язковий для вимірювання | J41: Кількісні дані | K41: 0.2 | L41: =VLOOKUP(D41,'Перелік Iндикаторiв'!$D$4:$M$99,8,FALSE) -> 0.1 | M41: =VLOOKUP(D41,'Перелік Iндикаторiв'!$D$4:$M$99,9,FALSE) -> 0.27083333 | O41: A.2.5.3 | P41: Випускники коледжів за спеціальностями в ІТ-галузі вечірньої форми навчання (ОВ: осіб) | Q41: Бал індикатора присвоюється пропорційно до розрахованого значення у відношенні до цільового з кроком 1 бал, де 100 - максимальний бал, коли розраховане значення дорівнює цільовому, 0 - мінімальний бал | R41: Формула розрахунку - [(Показник 1.1+Показник 1.2+Показник 1.3)/(Показник 1.4+Показник 1.5+Показник 1.6)*100%], де Показник 1.1 - Випускники коледжів за спеціальностями в ІТ-галузі очної форми навчання, осіб Показник 1.2 - Випускники коледжів за спеціальностями в ІТ-галузі заочної форми навчання, осіб Показник 1.3 - Випускники коледжів за спеціальностями в ІТ-галузі вечірньої форми навчання, осіб Показник 1.4 - Загальна кількість випускників коледжів очної форми навчання, осіб Показник 1.5 - Загальна кількість випускників Коледжів заочної форми навчання, осіб Показник 1.6 - Загальна кількість випускників коледжів вечірньої форми навчання, осіб | T41: Випускники коледжів вечірньої форми навчання в ІТ-галузі – особи, що навчаються за спеціальностями згідно з визначеним переліком галузей знань і спеціальностей, за якими здійснюється підготовка здобувачів вищої освіти в нижченаведених напрямах: 111 Математика 113 Прикладна математика 12 Інформаційні технології 151 Автоматизація та комп’ютерно-інтегровані технології | U41: станом на 01.01.2022 | V41: Постанова КМУ від 29 квітня 2015 р. № 266 "Про затвердження переліку галузей знань і спеціальностей, за якими здійснюється підготовка здобувачів вищої освіти" | W41: Дані підрозділу Міністерства освіти і науки
B42: Цифрова економіка в ТГ | C42: Привабливість для інвестицій в галузь ІТ | D42: A.2.5 | E42: % випускників коледжів за спеціальностями в ІТ-галузі від загальної кількості випускників | G42: % | H42: Розширений | I42: Обов'язковий для вимірювання | J42: Кількісні дані | K42: 0.2 | L42: =VLOOKUP(D42,'Перелік Iндикаторiв'!$D$4:$M$99,8,FALSE) -> 0.1 | M42: =VLOOKUP(D42,'Перелік Iндикаторiв'!$D$4:$M$99,9,FALSE) -> 0.27083333 | O42: A.2.5.4 | P42: Загальна кількість випускників коледжів очної форми навчання (ОВ: осіб) | Q42: Бал індикатора присвоюється пропорційно до розрахованого значення у відношенні до цільового з кроком 1 бал, де 100 - максимальний бал, коли розраховане значення дорівнює цільовому, 0 - мінімальний бал | R42: Формула розрахунку - [(Показник 1.1+Показник 1.2+Показник 1.3)/(Показник 1.4+Показник 1.5+Показник 1.6)*100%], де Показник 1.1 - Випускники коледжів за спеціальностями в ІТ-галузі очної форми навчання, осіб Показник 1.2 - Випускники коледжів за спеціальностями в ІТ-галузі заочної форми навчання, осіб Показник 1.3 - Випускники коледжів за спеціальностями в ІТ-галузі вечірньої форми навчання, осіб Показник 1.4 - Загальна кількість випускників коледжів очної форми навчання, осіб Показник 1.5 - Загальна кількість випускників Коледжів заочної форми навчання, осіб Показник 1.6 - Загальна кількість випускників коледжів вечірньої форми навчання, осіб | T42: Усі випускники коледжів очної форми навчання | U42: станом на 01.01.2022 | V42: Постанова КМУ від 29 квітня 2015 р. № 266 "Про затвердження переліку галузей знань і спеціальностей, за якими здійснюється підготовка здобувачів вищої освіти" | W42: Дані підрозділу Міністерства освіти і науки
B43: Цифрова економіка в ТГ | C43: Привабливість для інвестицій в галузь ІТ | D43: A.2.5 | E43: % випускників коледжів за спеціальностями в ІТ-галузі від загальної кількості випускників | G43: % | H43: Розширений | I43: Обов'язковий для вимірювання | J43: Кількісні дані | K43: 0.2 | L43: =VLOOKUP(D43,'Перелік Iндикаторiв'!$D$4:$M$99,8,FALSE) -> 0.1 | M43: =VLOOKUP(D43,'Перелік Iндикаторiв'!$D$4:$M$99,9,FALSE) -> 0.27083333 | O43: A.2.5.5 | P43: Загальна кількість випускників коледжів заочної форми навчання (ОВ: осіб) | Q43: Бал індикатора присвоюється пропорційно до розрахованого значення у відношенні до цільового з кроком 1 бал, де 100 - максимальний бал, коли розраховане значення дорівнює цільовому, 0 - мінімальний бал | R43: Формула розрахунку - [(Показник 1.1+Показник 1.2+Показник 1.3)/(Показник 1.4+Показник 1.5+Показник 1.6)*100%], де Показник 1.1 - Випускники коледжів за спеціальностями в ІТ-галузі очної форми навчання, осіб Показник 1.2 - Випускники коледжів за спеціальностями в ІТ-галузі заочної форми навчання, осіб Показник 1.3 - Випускники коледжів за спеціальностями в ІТ-галузі вечірньої форми навчання, осіб Показник 1.4 - Загальна кількість випускників коледжів очної форми навчання, осіб Показник 1.5 - Загальна кількість випускників Коледжів заочної форми навчання, осіб Показник 1.6 - Загальна кількість випускників коледжів вечірньої форми навчання, осіб | T43: Усі випускники коледжів заочної форми навчання | U43: станом на 01.01.2022 | V43: Постанова КМУ від 29 квітня 2015 р. № 266 "Про затвердження переліку галузей знань і спеціальностей, за якими здійснюється підготовка здобувачів вищої освіти" | W43: Дані підрозділу Міністерства освіти і науки
B44: Цифрова економіка в ТГ | C44: Привабливість для інвестицій в галузь ІТ | D44: A.2.5 | E44: % випускників коледжів за спеціальностями в ІТ-галузі від загальної кількості випускників | G44: % | H44: Розширений | I44: Обов'язковий для вимірювання | J44: Кількісні дані | K44: 0.2 | L44: =VLOOKUP(D44,'Перелік Iндикаторiв'!$D$4:$M$99,8,FALSE) -> 0.1 | M44: =VLOOKUP(D44,'Перелік Iндикаторiв'!$D$4:$M$99,9,FALSE) -> 0.27083333 | O44: A.2.5.6 | P44: Загальна кількість випускників коледжів вечірньої форми навчання (ОВ: осіб) | Q44: Бал індикатора присвоюється пропорційно до розрахованого значення у відношенні до цільового з кроком 1 бал, де 100 - максимальний бал, коли розраховане значення дорівнює цільовому, 0 - мінімальний бал | R44: Формула розрахунку - [(Показник 1.1+Показник 1.2+Показник 1.3)/(Показник 1.4+Показник 1.5+Показник 1.6)*100%], де Показник 1.1 - Випускники коледжів за спеціальностями в ІТ-галузі очної форми навчання, осіб Показник 1.2 - Випускники коледжів за спеціальностями в ІТ-галузі заочної форми навчання, осіб Показник 1.3 - Випускники коледжів за спеціальностями в ІТ-галузі вечірньої форми навчання, осіб Показник 1.4 - Загальна кількість випускників коледжів очної форми навчання, осіб Показник 1.5 - Загальна кількість випускників Коледжів заочної форми навчання, осіб Показник 1.6 - Загальна кількість випускників коледжів вечірньої форми навчання, осіб | T44: Усі випускники коледжів вечірньої форми навчання | U44: станом на 01.01.2022 | V44: Постанова КМУ від 29 квітня 2015 р. № 266 "Про затвердження переліку галузей знань і спеціальностей, за якими здійснюється підготовка здобувачів вищої освіти" | W44: Дані підрозділу Міністерства освіти і науки
B45: Цифрова економіка в ТГ | C45: Цифрові технології для бізнесу | D45: A.3.1 | E45: % заявок на реєстрацію СПД, поданих онлайн | G45: % | H45: Базовий | I45: На майбутнє вимірювання | J45: Кількісні дані | K45: 1 | L45: =VLOOKUP(D45,'Перелік Iндикаторiв'!$D$4:$M$99,8,FALSE) -> 1 | M45: =VLOOKUP(D45,'Перелік Iндикаторiв'!$D$4:$M$99,9,FALSE) -> 0 | O45: A.3.1.1 | P45: Кількість заявок на первинну реєстрацію СПД, поданих онлайн (ОВ: кількість заявок) | Q45: Бал індикатора присвоюється пропорційно до розрахованого значення у відношенні до цільового з кроком 1 бал, де 100 - максимальний бал, коли розраховане значення дорівнює цільовому, 0 - мінімальний бал | R45: Формула розрахунку - [(Показник 1.1/Показник 1.2)*100%], де Показник 1.1 - Кількість заявок на первинну реєстрацію СПД, поданих онлайн, кількість заявок Показник 1.2 - Загальна кількість заявок на реєстрацію СПД, кількість заявок | T45: Суб'єкти підприємницької діяльності (СПД) – громадяни України, інших держав, не обмежені законом у правоздатності або дієздатності, які провадять діяльність, метою якої є отримання прибутку; юридичні особи всіх форм власності. | U45: за рік | V45: Закон України від 06.09.2012 № 5203-VI "Про адміністративні послуги". | W45: Дані структурного підрозділу ОМС
B46: Цифрова економіка в ТГ | C46: Цифрові технології для бізнесу | D46: A.3.1 | E46: % заявок на реєстрацію СПД, поданих онлайн | G46: % | H46: Базовий | I46: На майбутнє вимірювання | J46: Кількісні дані | K46: 1 | L46: =VLOOKUP(D46,'Перелік Iндикаторiв'!$D$4:$M$99,8,FALSE) -> 1 | M46: =VLOOKUP(D46,'Перелік Iндикаторiв'!$D$4:$M$99,9,FALSE) -> 0 | O46: A.3.1.2 | P46: Загальна кількість заявок на первинну реєстрацію СПД (ОВ: кількість заявок) | Q46: Бал індикатора присвоюється пропорційно до розрахованого значення у відношенні до цільового з кроком 1 бал, де 100 - максимальний бал, коли розраховане значення дорівнює цільовому, 0 - мінімальний бал | R46: Формула розрахунку - [(Показник 1.1/Показник 1.2)*100%], де Показник 1.1 - Кількість заявок на первинну реєстрацію СПД (суб'єкта підприємницької діяльності) поданих онлайн, кількість заявок Показник 1.2 - Загальна кількість заявок на реєстрацію СПД (суб'єкта підприємницької діяльності), кількість заявок | T46: Суб'єкти підприємницької діяльності (СПД) – громадяни України, інших держав, не обмежені законом у правоздатності або дієздатності, які провадять діяльність, метою якої є отримання прибутку; юридичні особи всіх форм власності. | U46: за рік | V46: Закон України від 06.09.2012 № 5203-VI "Про адміністративні послуги". | W46: Дані структурного підрозділу ОМС
B47: Цифрова економіка в ТГ | C47: Цифрові технології для бізнесу | D47: A.3.2 | E47: % СПД, які подають звіти онлайн | G47: % | H47: Базовий | I47: На майбутнє вимірювання | J47: Кількісні дані | K47: 1 | L47: =VLOOKUP(D47,'Перелік Iндикаторiв'!$D$4:$M$99,8,FALSE) -> 1 | M47: =VLOOKUP(D47,'Перелік Iндикаторiв'!$D$4:$M$99,9,FALSE) -> 0 | O47: A.3.2.1 | P47: Кількість СПД, які подають звіти до податкового органу онлайн (ОВ: кількість СПД) | Q47: Бал індикатора присвоюється пропорційно до розрахованого значення у відношенні до цільового з кроком 1 бал, де 100 - максимальний бал, коли розраховане значення дорівнює цільовому, 0 - мінімальний бал | R47: Формула розрахунку - [(Показник 1.1/Показник 1.2)*100%], де Показник 1.1 - Кількість СПД, які подають звіти до податкового органу онлайн, кількість СПД Показник 1.2 - Загальна кількість СПД у ТГ, кількість СПД | T47: Суб'єкти підприємницької діяльності (СПД) – громадяни України, інших держав, не обмежені законом у правоздатності або дієздатності, які провадять діяльність, метою якої є отримання прибутку; юридичні особи всіх форм власності. | U47: станом на 01.01.2022 | V47: Закон України "Про внесення змін до Податкового кодексу України та інших законодавчих актів України щодо забезпечення збалансованості бюджетних надходжень" №1914 від 30.11.2021 | W47: Дані Державної податкової служби
B48: Цифрова економіка в ТГ | C48: Цифрові технології для бізнесу | D48: A.3.2 | E48: % СПД, які подають звіти онлайн | G48: % | H48: Базовий | I48: На майбутнє вимірювання | J48: Кількісні дані | K48: 1 | L48: =VLOOKUP(D48,'Перелік Iндикаторiв'!$D$4:$M$99,8,FALSE) -> 1 | M48: =VLOOKUP(D48,'Перелік Iндикаторiв'!$D$4:$M$99,9,FALSE) -> 0 | O48: A.3.2.2 | P48: Загальна кількість СПД у ТГ (ОВ: кількість СПД) | Q48: Бал індикатора присвоюється пропорційно до розрахованого значення у відношенні до цільового з кроком 1 бал, де 100 - максимальний бал, коли розраховане значення дорівнює цільовому, 0 - мінімальний бал | R48: Формула розрахунку - [(Показник 1.1/Показник 1.2)*100%], де Показник 1.1 - Кількість СПД, які подають звіти до податкового органу онлайн, кількість СПД Показник 1.2 - Загальна кількість СПД у ТГ, кількість СПД | T48: Суб'єкти підприємницької діяльності (СПД) – громадяни України, інших держав, не обмежені законом у правоздатності або дієздатності, які провадять діяльність, метою якої є отримання прибутку; юридичні особи всіх форм власності. | U48: станом на 01.01.2022 | V48: Закон України "Про внесення змін до Податкового кодексу України та інших законодавчих актів України щодо забезпечення збалансованості бюджетних надходжень" №1914 від 30.11.2021 | W48: Дані Державної податкової служби
B49: Цифрова економіка в ТГ | C49: Цифрові технології для бізнесу | D49: A.3.3 | E49: % онлайн-послуг ОМС для бізнесу від загальної кількості послуг (послуги, суб'єктом надання яких є ОМС, комунальні підприємства, заклади) | F49: Частка онлайн-послуг ОМС для бізнесу від загальної кількості послуг | G49: % | H49: Базовий | I49: Обов'язковий для вимірювання | J49: Кількісні дані | K49: 1 | L49: =VLOOKUP(D49,'Перелік Iндикаторiв'!$D$4:$M$99,8,FALSE) -> 1 | M49: =VLOOKUP(D49,'Перелік Iндикаторiв'!$D$4:$M$99,9,FALSE) -> 0.5 | O49: A.3.3.1 | P49: Кількість адміністративних онлайн-послуг, суб'єктом надання яких є ОМС (ОВ: кількість послуг) | Q49: Бал індикатора присвоюється пропорційно до розрахованого значення у відношенні до цільового з кроком 1 бал, де 100 - максимальний бал, коли розраховане значення дорівнює цільовому, 0 - мінімальний бал | R49: Формула розрахунку - [(Показник 1.1/Показник 1.2)*100%], де Показник 1.1 - Кількість адміністративних послуг, суб'єктом надання яких є ОМС і які надаються в режимі онлайн, кількість послуг Показник 1.2 - Загальна кількість адміністративних послуг, суб'єктом надання яких є ОМС, кількість послуг | T49: Адміністративна послуга – реЗакон України льтат здійснення владних повноважень суб’єктом надання адміністративних послуг за заявою фізичної або юридичної особи, спрямований на набуття, зміну або припинення прав та/або здійснення обов’язків такої особи відповідно до закону. Суб’єкт надання адміністративної послуги – орган виконавчої влади, інший державний орган, орган влади Автономної Республіки Крим, орган місцевого самоврядування, їхні посадові особи, державний реєстратор, суб’єкт державної реєстрації, уповноважені відповідно до закону надавати адміністративні послуги. | U49: станом на 01.01.2022 | V49: Закон України від 06.09.2012 № 5203-VI "Про адміністративні послуги". | W49: Дані структурного підрозділу ОМС
B50: Цифрова економіка в ТГ | C50: Цифрові технології для бізнесу | D50: A.3.3 | E50: % онлайн-послуг ОМС для бізнесу від загальної кількості послуг (послуги, суб'єктом надання яких є ОМС, комунальні підприємства, заклади) | G50: % | H50: Базовий | I50: Обов'язковий для вимірювання | J50: Кількісні дані | K50: 1 | L50: =VLOOKUP(D50,'Перелік Iндикаторiв'!$D$4:$M$99,8,FALSE) -> 1 | M50: =VLOOKUP(D50,'Перелік Iндикаторiв'!$D$4:$M$99,9,FALSE) -> 0.5 | O50: A.3.3.2 | P50: Загальна кількість адміністративних послуг, суб'єктом надання яких є ОМС (ОВ: кількість послуг) | Q50: Бал індикатора присвоюється пропорційно до розрахованого значення у відношенні до цільового з кроком 1 бал, де 100 - максимальний бал, коли розраховане значення дорівнює цільовому, 0 - мінімальний бал | R50: Формула розрахунку - [(Показник 1.1/Показник 1.2)*100%], де Показник 1.1 - Кількість адміністративних послуг, суб'єктом надання яких є ОМС і які надаються в режимі онлайн, кількість послуг Показник 1.2 - Загальна кількість адміністративних послуг, суб'єктом надання яких є ОМС, кількість послуг | T50: Адміністративна послуга – реЗакон України льтат здійснення владних повноважень суб’єктом надання адміністративних послуг за заявою фізичної або юридичної особи, спрямований на набуття, зміну або припинення прав та/або здійснення обов’язків такої особи відповідно до закону. Суб’єкт надання адміністративної послуги – орган виконавчої влади, інший державний орган, орган влади Автономної Республіки Крим, орган місцевого самоврядування, їхні посадові особи, державний реєстратор, суб’єкт державної реєстрації, уповноважені відповідно до закону надавати адміністративні послуги. | U50: станом на 01.01.2022 | V50: Закон України від 06.09.2012 № 5203-VI "Про адміністративні послуги". | W50: Дані структурного підрозділу ОМС
B51: Цифрова економіка в ТГ | C51: Цифрові технології для бізнесу | D51: A.3.4 | E51: Створено центр підтримки підприємців Дія.Бізнес | F51: Створено центр Дія.Бізнес | G51: Балів | H51: Базовий | I51: Обов'язковий для вимірювання | J51: Якісні дані | K51: 1 | L51: =VLOOKUP(D51,'Перелік Iндикаторiв'!$D$4:$M$99,8,FALSE) -> 1 | M51: =VLOOKUP(D51,'Перелік Iндикаторiв'!$D$4:$M$99,9,FALSE) -> 0.5 | O51: A.3.4.1 | P51: Створено центр підтримки підприємців Дія.Бізнес (ОВ: Так/Ні) | Q51: 1 бал - якщо створено центр підтримки підприємців Дія.Бізнес, 0 балів - якщо не створено центр підтримки підприємців Дія.Бізнес | R51: Формула розрахунку - [Показник 1.1] де, Показник 1.1 - Створено центр підтримки підприємців Дія.Бізнес , Так -1 бал, Ні -0 балів | T51: Центр підтримки підприємців Дія.Бізнес – це центр підтримки підприємців разом із консалтинговою зоною для представників мікро-, малого та середнього бізнесу | U51: станом на 01.01.2022 | V51: Потребує визначення в законодавстві | W51: Дані структурного підрозділу ОМС
B52: Розвиток цифрових навичок населення | C52: Розвиток цифрової грамотності населення | D52: В.1.2 | E52: % населення, що має застосунок Дія | G52: % | I52: На майбутнє вимірювання | J52: Кількісні дані | K52: 0.8 | L52: =VLOOKUP(D52,'Перелік Iндикаторiв'!$D$4:$M$99,8,FALSE) -> 0.8 | M52: =VLOOKUP(D52,'Перелік Iндикаторiв'!$D$4:$M$99,9,FALSE) -> 0 | O52: В.1.2.1 | P52: Чисельність жителів ТГ, які мають застосунок Дія (ОВ: осіб) | Q52: Бал індикатора присвоюється пропорційно до розрахованого значення у відношенні до цільового з кроком 1 бал, де 100 - максимальний бал, коли розраховане значення дорівнює цільовому, 0 - мінімальний бал | R52: Формула розрахунку - [(Показник 1.1/Показник 1.2)*100%], де Показник 1.1 - Чисельність жителів ТГ, які мають застосунок Дія, осіб Показник 1.2 - Загальна чисельність наявного населення ТГ віком від 14 років, осіб | T52: Доросле населення – населення у віці від 15 до 64 років. | U52: станом на 01.01.2022 | V52: Потребує визначення в законодавстві | W52: Дані підрозділу Міністерства цифрової трансформації
B53: Розвиток цифрових навичок населення | C53: Розвиток цифрової грамотності населення | D53: В.1.2 | E53: % населення, що має застосунок Дія | G53: % | I53: На майбутнє вимірювання | J53: Кількісні дані | K53: 0.8 | L53: =VLOOKUP(D53,'Перелік Iндикаторiв'!$D$4:$M$99,8,FALSE) -> 0.8 | M53: =VLOOKUP(D53,'Перелік Iндикаторiв'!$D$4:$M$99,9,FALSE) -> 0 | O53: В.1.2.2 | P53: Загальна чисельність наявного населення ТГ віком від 14 років (ОВ: осіб) | Q53: Бал індикатора присвоюється пропорційно до розрахованого значення у відношенні до цільового з кроком 1 бал, де 100 - максимальний бал, коли розраховане значення дорівнює цільовому, 0 - мінімальний бал | R53: Формула розрахунку - [(Показник 1.1/Показник 1.2)*100%], де Показник 1.1 - Чисельність жителів ТГ, які мають застосунок Дія, осіб Показник 1.2 - Загальна чисельність наявного населення ТГ віком від 14 років, осіб | T53: Наявне населення віком від 14 років – населення (особи, яким виповнилось 14 і більше років), яке на момент перепису перебуває на території ОТГ, разом із тими, хто проживає тимчасово (за умови їхньої відсутності в постійному місці проживання не більше ніж 12 місяців). | U53: станом на 01.01.2022 | V53: Потребує визначення в законодавстві | W53: Дані підрозділу Міграційної служби
B54: Розвиток цифрових навичок населення | C54: Розвиток цифрової грамотності населення | D54: В.1.3 | E54: % населення у громаді, що використовує смартфони та/або планшети | G54: % | I54: На майбутнє вимірювання | J54: Кількісні дані | L54: =VLOOKUP(D54,'Перелік Iндикаторiв'!$D$4:$M$99,8,FALSE) -> 0 | M54: =VLOOKUP(D54,'Перелік Iндикаторiв'!$D$4:$M$99,9,FALSE) -> 0 | O54: В.1.3.1 | P54: Чисельність дорослого населення у громаді, що використовує смартфони та/або планшети (ОВ: осіб) | Q54: Бал індикатора присвоюється пропорційно до розрахованого значення у відношенні до цільового з кроком 1 бал, де 100 - максимальний бал, коли розраховане значення дорівнює цільовому, 0 - мінімальний бал | R54: Формула розрахунку - [(Показник 1.1/Показник 1.2)*100%], де Показник 1.1 - Кількість дорослого населення у громаді, що використовує смартфони та/або планшети, осіб Показник 1.2 - Чисельність дорослого населення ТГ, осіб | T54: Доросле населення – населення у віці від 15 до 64 років. | U54: станом на 01.01.2022 | V54: Потребує визначення в законодавстві | W54: Дані мобільних операторів / підрозділу Державної служби статистики
B55: Розвиток цифрових навичок населення | C55: Розвиток цифрової грамотності населення | D55: В.1.3 | E55: % населення у громаді, що використовує смартфони та/або планшети | G55: % | I55: На майбутнє вимірювання | J55: Кількісні дані | L55: =VLOOKUP(D55,'Перелік Iндикаторiв'!$D$4:$M$99,8,FALSE) -> 0 | M55: =VLOOKUP(D55,'Перелік Iндикаторiв'!$D$4:$M$99,9,FALSE) -> 0 | O55: В.1.3.2 | P55: Чисельність дорослого населення у ТГ (ОВ: осіб) | Q55: Бал індикатора присвоюється пропорційно до розрахованого значення у відношенні до цільового з кроком 1 бал, де 100 - максимальний бал, коли розраховане значення дорівнює цільовому, 0 - мінімальний бал | R55: Формула розрахунку - [(Показник 1.1/Показник 1.2)*100%], де Показник 1.1 - Кількість дорослого населення у громаді, що використовує смартфони та/або планшети, осіб Показник 1.2 - Чисельність дорослого населення ТГ, осіб | T55: Доросле населення – населення у віці від 15 до 64 років. | U55: станом на 01.01.2022 | V55: Потребує визначення в законодавстві | W55: Дані структурного підрозділу ОМС
B56: Розвиток цифрових навичок населення | C56: Розвиток цифрової грамотності населення | D56: В.1.4 | E56: % жителів поважного віку (60+ років), які пройшли навчання з цифрової грамотності / гігієни від загальної чисельності наявного населення поважного віку | G56: % | H56: Базовий | I56: На майбутнє вимірювання | J56: Кількісні дані | K56: 0.2 | L56: =VLOOKUP(D56,'Перелік Iндикаторiв'!$D$4:$M$99,8,FALSE) -> 0.05 | M56: =VLOOKUP(D56,'Перелік Iндикаторiв'!$D$4:$M$99,9,FALSE) -> 0.070588235 | O56: В.1.4.1 | P56: Кількість жителів поважного віку (60+ років), які пройшли навчання з цифрової грамотності / гігієни (ОВ: осіб) | Q56: Бал індикатора присвоюється пропорційно до розрахованого значення у відношенні до цільового з кроком 1 бал, де 100 - максимальний бал, коли розраховане значення дорівнює цільовому, 0 - мінімальний бал | R56: Формула розрахунку - [(Показник 1.1/Показник 1.2)*100%], де Показник 1.1 - Кількість жителів поважного віку (60+ років), які пройшли навчання з цифрової грамотності / гігієни, осіб Показник 1.2 - Загальна чисельність наявного населення ТГ віком від 60 років, осіб | T56: Кількість жителів поважного віку (60+ років), які пройшли навчання з цифрової грамотності / гігієни – населення віком більше 60 років, яке на момент перепису перебуває на території ТГ, разом із тими, хто проживає тимчасово (за умови їхньої відсутності в постійному місці проживання не більше ніж 12 місяців) та пройшли навчання з цифрової грамотності / гігієни | U56: за рік | V56: Потребує визначення в законодавстві | W56: Дані структурного підрозділу ОМС
B57: Розвиток цифрових навичок населення | C57: Розвиток цифрової грамотності населення | D57: В.1.4 | E57: % жителів поважного віку (60+ років), які пройшли навчання з цифрової грамотності / гігієни від загальної чисельності наявного населення поважного віку | G57: % | H57: Базовий | I57: На майбутнє вимірювання | J57: Кількісні дані | K57: 0.2 | L57: =VLOOKUP(D57,'Перелік Iндикаторiв'!$D$4:$M$99,8,FALSE) -> 0.05 | M57: =VLOOKUP(D57,'Перелік Iндикаторiв'!$D$4:$M$99,9,FALSE) -> 0.070588235 | O57: В.1.4.2 | P57: Загальна чисельність наявного населення ТГ віком від 60 років (ОВ: осіб) | Q57: Бал індикатора присвоюється пропорційно до розрахованого значення у відношенні до цільового з кроком 1 бал, де 100 - максимальний бал, коли розраховане значення дорівнює цільовому, 0 - мінімальний бал | R57: Формула розрахунку - [(Показник 1.1/Показник 1.2)*100%], де Показник 1.1 - Кількість жителів поважного віку (60+ років), які пройшли навчання з цифрової грамотності / гігієни, осіб Показник 1.2 - Загальна чисельність наявного населення ТГ віком від 60 років, осіб | T57: Наявне населення – населення (особи, яким виповнилось 60 і більше років), яке на момент перепису перебуває на території ТГ, разом із тими, хто проживає тимчасово (за умови їхньої відсутності у постійному місці проживання не більше ніж 12 місяців). | U57: станом на 01.01.2022 | V57: Наказ Державної служби статистики України від 25.12.2014 № 402 http://db.ukrcensus.gov.ua/PXWEB2007/ukr/method/index.asp | W57: Дані підрозділу Міграційної служби
B58: Розвиток цифрових навичок населення | C58: Розвиток цифрової грамотності населення | D58: В.1.5 | E58: % середньозваженого значення балів Цифрограм (1.0 та 2.0) осіб, які пройшли тестування в застосунку Цифрограм 1.0 та 2.0 протягом звітного періоду /до максимальної кількості балів Цифрограм (1.0 та 2.0) | G58: % | I58: На майбутнє вимірювання | J58: Кількісні дані | K58: 0.75 | L58: =VLOOKUP(D58,'Перелік Iндикаторiв'!$D$4:$M$99,8,FALSE) -> 0.75 | M58: =VLOOKUP(D58,'Перелік Iндикаторiв'!$D$4:$M$99,9,FALSE) -> 0 | O58: В.1.5.1 | P58: Сума балів, отриманих жителями ТГ, які пройшли тестування в застосунку Цифрограм 1.0 протягом звітного періоду (ОВ: бали) | Q58: Бал індикатора присвоюється пропорційно до розрахованого значення у відношенні до цільового з кроком 1 бал, де 100 - максимальний бал, коли розраховане значення дорівнює цільовому, 0 - мінімальний бал | R58: Формула розрахунку - [(Показник 1.1/(Показник 1.2*90)*Показник 1.2/(Показник 1.2+Показник 1.4))+ (Показник 1.3/(Показник 1.4*111)*Показник 1.4/(Показник 1.2+Показник 1.4))*100%), де Показник 1.1 - Сума балів, отриманих жителями ТГ, які пройшли тестування в застосунку Цифрограм 1.0 протягом звітного періоду, балів Показник 1.2 - Кількість жителів ТГ, які пройшли тестування в Цифрограм 1.0 протягом звітного періоду, жителів Показник 1.3 - Сума балів, отриманих жителями ТГ, які пройшли тестування в застосунку Цифрограм 2.0 протягом звітного періоду, балів Показник 1.4 - Кількість жителів ТГ, які пройшли тестування в Цифрограм 2.0 протягом звітного періоду, жителів | T58: Цифрограм 1.0 та 2.0 для громадян – онлайн-тест від Міністерства цифрової трансформації, який висвітлює знання за такими напрямами: Розв'язання проблем у цифровому середовищі та навчання впродовж життя Безпека в цифровому середовищі Створення цифрового контенту Комунікація та взаємодія в цифровому суспільстві Інформаційна грамотність, уміння працювати з даними Основи комп'ютерної грамотності | U58: станом на 01.01.2022 | V58: Постанова КМУ Питання Єдиного державного вебпорталу цифрової освіти “Дія. Цифрова освіта” від 10 березня 2021 р. № 184 https://zakon.rada.gov.ua/laws/show/184-2021-%D0%BF/ed20210310#n21 | W58: Дані підрозділу Міністерства цифрової трансформації
B59: Розвиток цифрових навичок населення | C59: Розвиток цифрової грамотності населення | D59: В.1.5 | E59: % середньозваженого значення балів Цифрограм (1.0 та 2.0) осіб, які пройшли тестування в застосунку Цифрограм 1.0 та 2.0 протягом звітного періоду /до максимальної кількості балів Цифрограм (1.0 та 2.0) | G59: % | I59: На майбутнє вимірювання | J59: Кількісні дані | K59: 0.75 | L59: =VLOOKUP(D59,'Перелік Iндикаторiв'!$D$4:$M$99,8,FALSE) -> 0.75 | M59: =VLOOKUP(D59,'Перелік Iндикаторiв'!$D$4:$M$99,9,FALSE) -> 0 | O59: В.1.5.2 | P59: Кількість жителів ТГ, які пройшли тестування в Цифрограм 1.0 протягом звітного періоду (ОВ: жителів) | Q59: Бал індикатора присвоюється пропорційно до розрахованого значення у відношенні до цільового з кроком 1 бал, де 100 - максимальний бал, коли розраховане значення дорівнює цільовому, 0 - мінімальний бал | R59: Формула розрахунку - [(Показник 1.1/(Показник 1.2*90)*Показник 1.2/(Показник 1.2+Показник 1.4))+ (Показник 1.3/(Показник 1.4*111)*Показник 1.4/(Показник 1.2+Показник 1.4))*100%), де Показник 1.1 - Сума балів, отриманих жителями ТГ, які пройшли тестування в застосунку Цифрограм 1.0 протягом звітного періоду, балів Показник 1.2 - Кількість жителів ТГ, які пройшли тестування в Цифрограм 1.0 протягом звітного періоду, жителів Показник 1.3 - Сума балів, отриманих жителями ТГ, які пройшли тестування в застосунку Цифрограм 2.0 протягом звітного періоду, балів Показник 1.4 - Кількість жителів ТГ, які пройшли тестування в Цифрограм 2.0 протягом звітного періоду, жителів | T59: Цифрограм 1.0 та 2.0 для громадян – онлайн-тест від Міністерства цифрової трансформації, який висвітлює знання за такими напрямами: Розв'язання проблем у цифровому середовищі та навчання впродовж життя Безпека в цифровому середовищі Створення цифрового контенту Комунікація та взаємодія в цифровому суспільстві Інформаційна грамотність, уміння працювати з даними Основи комп'ютерної грамотності | U59: станом на 01.01.2022 | V59: Постанова КМУ Питання Єдиного державного вебпорталу цифрової освіти “Дія. Цифрова освіта” від 10 березня 2021 р. № 184 https://zakon.rada.gov.ua/laws/show/184-2021-%D0%BF/ed20210310#n21 | W59: Дані підрозділу Міністерства цифрової трансформації
B60: Розвиток цифрових навичок населення | C60: Розвиток цифрової грамотності населення | D60: В.1.5 | E60: % середньозваженого значення балів Цифрограм (1.0 та 2.0) осіб, які пройшли тестування в застосунку Цифрограм 1.0 та 2.0 протягом звітного періоду, від максимальної кількості балів Цифрограм (1.0 та 2.0) | G60: % | I60: На майбутнє вимірювання | J60: Кількісні дані | K60: 0.75 | L60: =VLOOKUP(D60,'Перелік Iндикаторiв'!$D$4:$M$99,8,FALSE) -> 0.75 | M60: =VLOOKUP(D60,'Перелік Iндикаторiв'!$D$4:$M$99,9,FALSE) -> 0 | O60: В.1.5.3 | P60: Сума балів, отриманих жителями ТГ, які пройшли тестування в застосунку Цифрограм 2.0 протягом звітного періоду (ОВ: бали) | Q60: Бал індикатора присвоюється пропорційно до розрахованого значення у відношенні до цільового з кроком 1 бал, де 100 - максимальний бал, коли розраховане значення дорівнює цільовому, 0 - мінімальний бал | R60: Формула розрахунку - [(Показник 1.1/(Показник 1.2*90)*Показник 1.2/(Показник 1.2+Показник 1.4))+ (Показник 1.3/(Показник 1.4*111)*Показник 1.4/(Показник 1.2+Показник 1.4))*100%), де Показник 1.1 - Сума балів, отриманих жителями ТГ, які пройшли тестування в застосунку Цифрограм 1.0 протягом звітного періоду, балів Показник 1.2 - Кількість жителів ТГ, які пройшли тестування в Цифрограм 1.0 протягом звітного періоду, жителів Показник 1.3 - Сума балів, отриманих жителями ТГ, які пройшли тестування в застосунку Цифрограм 2.0 протягом звітного періоду, балів Показник 1.4 - Кількість жителів ТГ, які пройшли тестування в Цифрограм 2.0 протягом звітного періоду, жителів | T60: Цифрограм 1.0 та 2.0 для громадян – онлайн-тест від Міністерства цифрової трансформації, який висвітлює знання за такими напрямами: Розв'язання проблем у цифровому середовищі та навчання впродовж життя Безпека в цифровому середовищі Створення цифрового контенту Комунікація та взаємодія в цифровому суспільстві Інформаційна грамотність, уміння працювати з даними Основи комп'ютерної грамотності | U60: станом на 01.01.2022 | V60: Постанова КМУ Питання Єдиного державного вебпорталу цифрової освіти “Дія. Цифрова освіта” від 10 березня 2021 р. № 184 https://zakon.rada.gov.ua/laws/show/184-2021-%D0%BF/ed20210310#n21 | W60: Дані підрозділу Міністерства цифрової трансформації
B61: Розвиток цифрових навичок населення | C61: Розвиток цифрової грамотності населення | D61: В.1.5 | E61: % середньозваженого значення балів Цифрограм (1.0 та 2.0) осіб, які пройшли тестування в застосунку Цифрограм 1.0 та 2.0 протягом звітного періоду, від максимальної кількості балів Цифрограм (1.0 та 2.0) | G61: % | I61: На майбутнє вимірювання | J61: Кількісні дані | K61: 0.75 | L61: =VLOOKUP(D61,'Перелік Iндикаторiв'!$D$4:$M$99,8,FALSE) -> 0.75 | M61: =VLOOKUP(D61,'Перелік Iндикаторiв'!$D$4:$M$99,9,FALSE) -> 0 | O61: В.1.5.4 | P61: Кількість жителів ТГ, які пройшли тестування в Цифрограм 2.0 протягом звітного періоду (ОВ: жителів) | Q61: Бал індикатора присвоюється пропорційно до розрахованого значення у відношенні до цільового з кроком 1 бал, де 100 - максимальний бал, коли розраховане значення дорівнює цільовому, 0 - мінімальний бал | R61: Формула розрахунку - [(Показник 1.1/(Показник 1.2*90)*Показник 1.2/(Показник 1.2+Показник 1.4))+ (Показник 1.3/(Показник 1.4*111)*Показник 1.4/(Показник 1.2+Показник 1.4))*100%), де Показник 1.1 - Сума балів, отриманих жителями ТГ, які пройшли тестування в застосунку Цифрограм 1.0 протягом звітного періоду, балів Показник 1.2 - Кількість жителів ТГ, які пройшли тестування в Цифрограм 1.0 протягом звітного періоду, жителів Показник 1.3 - Сума балів, отриманих жителями ТГ, які пройшли тестування в застосунку Цифрограм 2.0 протягом звітного періоду, балів Показник 1.4 - Кількість жителів ТГ, які пройшли тестування в Цифрограм 2.0 протягом звітного періоду, жителів | T61: Цифрограм 1.0 та 2.0 для громадян – онлайн-тест від Міністерства цифрової трансформації, який висвітлює знання за такими напрямами: Розв'язання проблем у цифровому середовищі та навчання впродовж життя Безпека в цифровому середовищі Створення цифрового контенту Комунікація та взаємодія в цифровому суспільстві Інформаційна грамотність, уміння працювати з даними Основи комп'ютерної грамотності | U61: станом на 01.01.2022 | V61: Постанова КМУ Питання Єдиного державного вебпорталу цифрової освіти “Дія. Цифрова освіта” від 10 березня 2021 р. № 184 https://zakon.rada.gov.ua/laws/show/184-2021-%D0%BF/ed20210310#n21 | W61: Дані підрозділу Міністерства цифрової трансформації
B62: Розвиток цифрових навичок населення | C62: Розвиток цифрової грамотності населення | D62: В.1.6 | E62: Кількість осіб у ТГ, які пройшли тестування в застосунку Цифрограм 1.0 та 2.0/на 1000 населення в ТГ | F62: Кількість осіб у ТГ, які пройшли тестування Цифрограм 1.0 та 2.0 на 1 тис. населення в ТГ | G62: Осіб/1000 осіб | H62: Базовий | I62: Обов'язковий для вимірювання | J62: Кількісні дані | K62: 400 | L62: =VLOOKUP(D62,'Перелік Iндикаторiв'!$D$4:$M$99,8,FALSE) -> 50 | M62: =VLOOKUP(D62,'Перелік Iндикаторiв'!$D$4:$M$99,9,FALSE) -> 0.16470588 | O62: В.1.6.1 | P62: Кількість осіб ТГ, які пройшли тестування в застосунку Цифрограм 1.0 та 2.0 (ОВ: осіб) | Q62: Бал індикатора присвоюється пропорційно до розрахованого значення у відношенні до цільового з кроком 1 бал, де 100 - максимальний бал, коли розраховане значення дорівнює цільовому, 0 - мінімальний бал | R62: Формула розрахунку - [Показник 1.1/Показник 1.2], де Показник 1.1 - Кількість осіб ТГ, які пройшли тестування в застосунку Цифрограм 1.0 та 2.0, осіб Показник 1.2 - Загальна чисельність наявного населення ТГ віком від 14 років, осіб | T62: Цифрограм 1.0 та 2.0 для громадян – онлайн-тест від Міністерства цифрової трансформації, для визначення рівня цифрових навичок громадян за такими напрямами: Розв'язання проблем у цифровому середовищі та навчання впродовж життя Безпека в цифровому середовищі Створення цифрового контенту Комунікація та взаємодія в цифровому суспільстві Інформаційна грамотність, уміння працювати з даними Основи комп'ютерної грамотності | U62: станом на 01.01.2022 | V62: Постанова КМУ Питання Єдиного державного вебпорталу цифрової освіти “Дія. Цифрова освіта” від 10 березня 2021 р. № 184 https://zakon.rada.gov.ua/laws/show/184-2021-%D0%BF/ed20210310#n21 | W62: Дані підрозділу Міністерства цифрової трансформації
B63: Розвиток цифрових навичок населення | C63: Розвиток цифрової грамотності населення | D63: В.1.6 | E63: Кількість осіб у ТГ, які пройшли тестування в застосунку Цифрограм 1.0 та 2.0/на 1000 населення в ТГ | G63: Осіб/1000 осіб | H63: Базовий | I63: Обов'язковий для вимірювання | J63: Кількісні дані | K63: 400 | L63: =VLOOKUP(D63,'Перелік Iндикаторiв'!$D$4:$M$99,8,FALSE) -> 50 | M63: =VLOOKUP(D63,'Перелік Iндикаторiв'!$D$4:$M$99,9,FALSE) -> 0.16470588 | O63: В.1.6.2 | P63: Загальна чисельність наявного населення ТГ віком від 14 років (ОВ: осіб) | Q63: Бал індикатора присвоюється пропорційно до розрахованого значення у відношенні до цільового з кроком 1 бал, де 100 - максимальний бал, коли розраховане значення дорівнює цільовому, 0 - мінімальний бал | R63: Формула розрахунку - [Показник 1.1/Показник 1.2], де Показник 1.1 - Кількість осіб ТГ, які пройшли тестування в застосунку Цифрограм 1.0 та 2.0, осіб Показник 1.2 - Загальна чисельність наявного населення ТГ віком від 14 років, осіб | T63: Наявне населення віком від 14 років – населення (особи, яким виповнилось 14 і більше років), яке на момент перепису перебуває на території ОТГ, разом із тими, хто проживає тимчасово (за умови їхньої відсутності в постійному місці проживання не більше ніж 12 місяців). | U63: станом на 01.01.2022 | V63: Постанова КМУ Питання Єдиного державного вебпорталу цифрової освіти “Дія. Цифрова освіта” від 10 березня 2021 р. № 184 https://zakon.rada.gov.ua/laws/show/184-2021-%D0%BF/ed20210310#n21 | W63: Дані підрозділу Міграційної служби
B64: Розвиток цифрових навичок населення | C64: Розвиток цифрової грамотності населення | D64: В.1.7 | E64: % жителів громади, які отримали ID-картки, від загальної кількості жителів ТГ відповідного віку | G64: % | H64: Базовий | I64: На майбутнє вимірювання | J64: Кількісні дані | K64: 1 | L64: =VLOOKUP(D64,'Перелік Iндикаторiв'!$D$4:$M$99,8,FALSE) -> 1 | M64: =VLOOKUP(D64,'Перелік Iндикаторiв'!$D$4:$M$99,9,FALSE) -> 0.43529412 | O64: В.1.7.1 | P64: Кількість жителів громади, які отримали ID-картки (ОВ: осіб) | Q64: Бал індикатора присвоюється пропорційно до розрахованого значення у відношенні до цільового з кроком 1 бал, де 100 - максимальний бал, коли розраховане значення дорівнює цільовому, 0 - мінімальний бал | R64: Формула розрахунку: [(Показник 1.1/Показник 1.2)*100], де Показник 1.1 - Кількість жителів громади, які отримали ID-картки, осіб Показник 1.2 - Загальна чисельність наявного населення ТГ віком від 14 років, осіб | T64: Кількість жителів громади, які отримали ID-картки – кількість жителів громади, які оформили ID-картки за весь час до звітного періоду | U64: станом на 01.01.2022 | V64: Постанова ВРУ Про затвердження положень про паспорт громадянина України та про паспорт громадянина України для виїзду за кордон https://zakon.rada.gov.ua/laws/show/2503-12#Text | W64: Дані підрозділу Міграційної служби
B65: Розвиток цифрових навичок населення | C65: Розвиток цифрової грамотності населення | D65: В.1.7 | E65: % жителів громади, які отримали ID-картки, від загальної кількості жителів ТГ відповідного віку | G65: % | H65: Базовий | I65: На майбутнє вимірювання | J65: Кількісні дані | K65: 1 | L65: =VLOOKUP(D65,'Перелік Iндикаторiв'!$D$4:$M$99,8,FALSE) -> 1 | M65: =VLOOKUP(D65,'Перелік Iндикаторiв'!$D$4:$M$99,9,FALSE) -> 0.43529412 | O65: В.1.7.2 | P65: Загальна чисельність наявного населення ТГ віком від 14 років (ОВ: осіб) | Q65: Бал індикатора присвоюється пропорційно до розрахованого значення у відношенні до цільового з кроком 1 бал, де 100 - максимальний бал, коли розраховане значення дорівнює цільовому, 0 - мінімальний бал | R65: Формула розрахунку: [(Показник 1.1/Показник 1.2)*100], де Показник 1.1 - Кількість жителів громади, які отримали ID-картки, осіб Показник 1.2 - Загальна чисельність наявного населення ТГ віком від 14 років, осіб | T65: Наявне населення віком від 14 років – населення (особи, яким виповнилось 14 і більше років), яке на момент перепису перебуває на території ОТГ, разом із тими, хто проживає тимчасово (за умови їхньої відсутності в постійному місці проживання не більше ніж 12 місяців). | U65: станом на 01.01.2022 | V65: Постанова КМУ Питання Єдиного державного вебпорталу цифрової освіти “Дія. Цифрова освіта” від 10 березня 2021 р. № 184 https://zakon.rada.gov.ua/laws/show/184-2021-%D0%BF/ed20210310#n21 | W65: Дані підрозділу Міграційної служби
B66: Розвиток цифрових навичок населення | C66: Розвиток цифрової грамотності населення | D66: В.1.8 | E66: % жителів ТГ, які зареєстрували своє місце проживання через портал Дія, від загальної кількості реєстрацій місць проживання за звітний період | G66: % | I66: На майбутнє вимірювання | J66: Кількісні дані | K66: 0.5 | L66: =VLOOKUP(D66,'Перелік Iндикаторiв'!$D$4:$M$99,8,FALSE) -> 0.5 | M66: =VLOOKUP(D66,'Перелік Iндикаторiв'!$D$4:$M$99,9,FALSE) -> 0 | O66: В.1.8.1 | P66: Кількість жителів ТГ, які зареєстрували своє місце проживання через портал Дія (ОВ: осіб) | Q66: Бал індикатора присвоюється пропорційно до розрахованого значення у відношенні до цільового з кроком 1 бал, де 100 - максимальний бал, коли розраховане значення дорівнює цільовому, 0 - мінімальний бал | R66: Формула розрахунку: [(Показник 1.1/Показник 1.2)*100], де Показник 1.1 - Кількість жителів ТГ, які зареєстрували своє місце проживання через портал Дія, осіб Показник 1.2 - Загальна кількість реєстрацій місць проживання за звітний період, осіб | T66: Кількість жителів ТГ, які зареєстрували своє місце проживання через портал Дія – це кількість жителів ТГ, які звернулися через портал Дія за зміною місця проживання на території ТГ та які успішно отримали цю послугу | U66: за рік | V66: Постанова КМУ "Деякі питання декларування і реєстрації місця проживання та ведення реєстрів територіальних громад" | W66: Дані підрозділу Міністерства цифрової трансформації
B67: Розвиток цифрових навичок населення | C67: Розвиток цифрової грамотності населення | D67: В.1.8 | E67: % жителів ТГ, які зареєстрували своє місце проживання через портал Дія, від загальної кількості реєстрацій місць проживання за звітний період | G67: % | I67: На майбутнє вимірювання | J67: Кількісні дані | K67: 0.5 | L67: =VLOOKUP(D67,'Перелік Iндикаторiв'!$D$4:$M$99,8,FALSE) -> 0.5 | M67: =VLOOKUP(D67,'Перелік Iндикаторiв'!$D$4:$M$99,9,FALSE) -> 0 | O67: В.1.8.2 | P67: Загальна кількість реєстрацій місць проживання за звітний період (ОВ: осіб) | Q67: Бал індикатора присвоюється пропорційно до розрахованого значення у відношенні до цільового з кроком 1 бал, де 100 - максимальний бал, коли розраховане значення дорівнює цільовому, 0 - мінімальний бал | R67: Формула розрахунку: [(Показник 1.1/Показник 1.2)*100], де Показник 1.1 - Кількість жителів ТГ, які зареєстрували своє місце проживання через портал Дія, осіб Показник 1.2 - Загальна кількість реєстрацій місць проживання за звітний період, осіб | T67: Загальна кількість реєстрацій місць проживання за звітний період – кількість наданих послуг із реєстрації місця проживання через усі можливі канали надання такої послуги | U67: за рік | V67: Постанова КМУ "Деякі питання декларування і реєстрації місця проживання та ведення реєстрів територіальних громад" | W67: Дані структурного підрозділу ОМС
B68: Розвиток цифрових навичок населення | C68: Розвиток цифрової грамотності населення | D68: В.1.9 | E68: % дітей, зареєстрованих через єМалятко, від загальної кількості новонароджених | G68: % | H68: Базовий | I68: На майбутнє вимірювання | J68: Кількісні дані | K68: 1 | L68: =VLOOKUP(D68,'Перелік Iндикаторiв'!$D$4:$M$99,8,FALSE) -> 1 | M68: =VLOOKUP(D68,'Перелік Iндикаторiв'!$D$4:$M$99,9,FALSE) -> 0.32941176 | O68: В.1.9.1 | P68: Кількість дітей, зареєстрованих через єМалятко (ОВ: Дітей) | Q68: Бал індикатора присвоюється пропорційно до розрахованого значення у відношенні до цільового з кроком 1 бал, де 100 - максимальний бал, коли розраховане значення дорівнює цільовому, 0 - мінімальний бал | R68: Формула розрахунку: [(Показник 1.1/Показник 1.2)*100], де Показник 1.1 - Кількість дітей, зареєстрованих через єМалятко, дітей Показник 1.2 - Загальна кількість новонароджених на території ТГ, дітей | T68: Кількість дітей, зареєстрованих через єМалятко – кількість батьків, які скористалися комплексною послугою єМалятко | U68: за рік | V68: Постанова КМУ від 10 липня 2019 р. № 691 Про реалізацію експериментального проєкту щодо створення сприятливих умов для реалізації прав дитини https://zakon.rada.gov.ua/laws/show/691-2019-%D0%BF#Text | W68: Дані підрозділу Міністерства цифрової трансформації
B69: Розвиток цифрових навичок населення | C69: Розвиток цифрової грамотності населення | D69: В.1.9 | E69: % дітей, зареєстрованих через єМалятко, від загальної кількості новонароджених | G69: % | H69: Базовий | I69: На майбутнє вимірювання | J69: Кількісні дані | K69: 1 | L69: =VLOOKUP(D69,'Перелік Iндикаторiв'!$D$4:$M$99,8,FALSE) -> 1 | M69: =VLOOKUP(D69,'Перелік Iндикаторiв'!$D$4:$M$99,9,FALSE) -> 0.32941176 | O69: В.1.9.2 | P69: Загальна кількість новонароджених на території ТГ (ОВ: Дітей) | Q69: Бал індикатора присвоюється пропорційно до розрахованого значення у відношенні до цільового з кроком 1 бал, де 100 - максимальний бал, коли розраховане значення дорівнює цільовому, 0 - мінімальний бал | R69: Формула розрахунку: [(Показник 1.1/Показник 1.2)*100], де Показник 1.1 - Кількість дітей, зареєстрованих через єМалятко, дітей Показник 1.2 - Загальна кількість новонароджених на території ТГ, дітей | T69: Загальна кількість новонароджених на території ТГ – кількість новонароджених дітей на території ТГ | U69: за рік | V69: Закон України Про державну реєстрацію актів цивільного стану | W69: Дані структурного підрозділу ОМС
B70: Розвиток цифрових навичок населення | C70: Розвиток талантів в галузі ІКТ | D70: В.2.1 | E70: Наявність школярів (6-11 класів), які стали призерами (1-3 місце) всеукраїнських олімпіад (4 етапу) з Математики та Інформатики | F70: Наявність школярів (6-11 класів), які стали призерами (1-3 місце) всеукраїнських олімпіад (4 етапу) з математики та інформатики | G70: Балів | H70: Базовий | I70: Обов'язковий для вимірювання | J70: Якісні дані | K70: 1 | L70: =VLOOKUP(D70,'Перелік Iндикаторiв'!$D$4:$M$99,8,FALSE) -> 1 | M70: =VLOOKUP(D70,'Перелік Iндикаторiв'!$D$4:$M$99,9,FALSE) -> 0.33333333 | O70: В.2.1.1 | P70: Наявність школярів (6-11 класів), які стали призерами (1-3 місце) всеукраїнських олімпіад (4 етапу) з Математики та Інформатики, (ОВ: немає), відповідь так/ні | Q70: Бал індикатора присвоюється пропорційно до розрахованого значення у відношенні до цільового з кроком 1 бал, де 100 - максимальний бал, коли розраховане значення дорівнює цільовому, 0 - мінімальний бал | R70: Формула розрахунку - [Показник 1.1], де 1 бал - якщо у звітному році є школярі (6-11 класів), які стали призерами олімпіад (4 етапи) з Математики та Інформатики, осіб | T70: Кількість школярів (6-11 класів), які стали переможцями олімпіад (3 та 4 етапи) з математики й інформатики – школярі, які отримують середню освіту в навчальних закладах на території територіальної громади в 6-11 класах і які здобули призові місця у всеукраїнській учнівській олімпіаді (на етапі 4 (всеукраїнському)) з математики та інформатики. | U70: за рік | V70: Наказ Міністерства освіти і науки, молоді та спорту від 22.09.2011 № 1099 Про затвердження Положення про Всеукраїнські учнівські олімпіади, турніри, конкурси з навчальних предметів, конкурси-захисти науково-дослідницьких робіт, олімпіади зі спеціальних дисциплін та конкурси фахової майстерності https://zakon.rada.gov.ua/laws/show/z1318-11#Text | W70: Дані структурного підрозділу ОМС
B71: Розвиток цифрових навичок населення | C71: Розвиток талантів в галузі ІКТ | D71: В.2.2 | E71: Кількість школярів (6-11 класів), які стали призерами (1-3 місце) олімпіад (2 та 3 етапів) з Математики та Інформатики, на 1000 тисячу школярів (6-11 класів) в ТГ | F71: Кількість школярів (6-11 класів), які стали призерами (1-3 місце) олімпіад (2 та 3 етапів) з математики та інформатики, на 1 тис тисячу школярів (6-11 класів) в ТГ | G71: Осіб/1000 осіб | H71: Базовий | I71: Обов'язковий для вимірювання | J71: Кількісні дані | K71: 5 | L71: =VLOOKUP(D71,'Перелік Iндикаторiв'!$D$4:$M$99,8,FALSE) -> 5 | M71: =VLOOKUP(D71,'Перелік Iндикаторiв'!$D$4:$M$99,9,FALSE) -> 0.33333333 | O71: В.2.2.1 | P71: Кількість школярів (6-11 класів), які стали призерами олімпіад (2 та 3 етапи) з Математики та Інформатики (ОВ: осіб) | Q71: Бал індикатора присвоюється пропорційно до розрахованого значення у відношенні до цільового з кроком 1 бал, де 100 - максимальний бал, коли розраховане значення дорівнює цільовому, 0 - мінімальний бал | R71: Формула розрахунку - [(Показник 1.1/Показник 1.2)*1000], де Показник 1.1 - Кількість школярів (6-11 класів), які стали призерами олімпіад (2 та 3 етапи) з Математики та Інформатики, осіб Показник 1.2 - Кількість школярів (6-11 класів), осіб | T71: Кількість школярів (6-11 класів), які стали переможцями олімпіад (3 та 4 етапи) з математики й інформатики – школярі, які отримують середню освіту в навчальних закладах на території територіальної громади в 6-11 класах і які здобули призові місця у всеукраїнській учнівській олімпіаді (на етапі 3 (обласному або у м. Києві - міському) та етапі 4 (всеукраїнському)) з математики та інформатики. | U71: за рік | V71: Наказ Міністерства освіти і науки, молоді та спорту від 22.09.2011 № 1099 Про затвердження Положення про Всеукраїнські учнівські олімпіади, турніри, конкурси з навчальних предметів, конкурси-захисти науково-дослідницьких робіт, олімпіади зі спеціальних дисциплін та конкурси фахової майстерності https://zakon.rada.gov.ua/laws/show/z1318-11#Text | W71: Дані структурного підрозділу ОМС
B72: Розвиток цифрових навичок населення | C72: Розвиток талантів в галузі ІКТ | D72: В.2.2 | E72: Кількість школярів (6-11 класів), які стали призерами (1-3 місце) олімпіад (2 та 3 етапів) з Математики та Інформатики, на 1000 тисячу школярів (6-11 класів) в ТГ | G72: Осіб/1000 осіб | H72: Базовий | I72: Обов'язковий для вимірювання | J72: Кількісні дані | K72: 5 | L72: =VLOOKUP(D72,'Перелік Iндикаторiв'!$D$4:$M$99,8,FALSE) -> 5 | M72: =VLOOKUP(D72,'Перелік Iндикаторiв'!$D$4:$M$99,9,FALSE) -> 0.33333333 | O72: В.2.2.2 | P72: Кількість школярів (6-11 класів) (ОВ: осіб) | Q72: Бал індикатора присвоюється пропорційно до розрахованого значення у відношенні до цільового з кроком 1 бал, де 100 - максимальний бал, коли розраховане значення дорівнює цільовому, 0 - мінімальний бал | R72: Формула розрахунку - [(Показник 1.1/Показник 1.2)*1000], де Показник 1.1 - Кількість школярів (6-11 класів), які стали призерами олімпіад (2 та 3 етапи) з Математики та Інформатики, осіб Показник 1.2 - Кількість школярів (6-11 класів), осіб | T72: Кількість школярів (6-11 класів) – школярі, які здобувають середню освіту в навчальних закладах на території територіальної громади й навчаються в 6-11 класах | U72: за рік | V72: Наказ Міністерства освіти і науки, молоді та спорту від 22.09.2011 № 1099 Про затвердження Положення про Всеукраїнські учнівські олімпіади, турніри, конкурси з навчальних предметів, конкурси-захисти науково-дослідницьких робіт, олімпіади зі спеціальних дисциплін та конкурси фахової майстерності https://zakon.rada.gov.ua/laws/show/z1318-11#Text | W72: Дані структурного підрозділу ОМС
B73: Розвиток цифрових навичок населення | C73: Розвиток талантів в галузі ІКТ | D73: В.2.3 | E73: Хабів цифрової освіти на 10 000 осіб | G73: Хабів/10 000 осіб | H73: Базовий | I73: На майбутнє вимірювання | J73: Кількісні дані | K73: 1 | L73: =VLOOKUP(D73,'Перелік Iндикаторiв'!$D$4:$M$99,8,FALSE) -> 1 | M73: =VLOOKUP(D73,'Перелік Iндикаторiв'!$D$4:$M$99,9,FALSE) -> 0.33333333 | O73: В.2.3.1 | P73: Кількість хабів цифрової освіти (ОВ: хабів) | Q73: Бал індикатора присвоюється пропорційно до розрахованого значення у відношенні до цільового з кроком 1 бал, де 100 - максимальний бал, коли розраховане значення дорівнює цільовому, 0 - мінімальний бал | R73: Формула розрахунку - [(Показник 1.1/Показник 1.2/10 000] де, Показник 1.1 - Кількість хабів цифрової освіти у ТГ, хабів Показник 1.2 - Загальна кількість осіб місце проживання яких зареєстровано у ТГ, осіб | T73: Хаби цифрової освіти – це місця, куди може завітати кожен громадянин, щоб безкоштовно отримати доступ до сайту Дія.Цифрова освіта й пройти навчання з цифрової грамотності. Це - бібліотеки, школи, університети, компанії і приватний сектор, IT-організації, ЦНАПи, громадські організації. | U73: станом на 01.01.2022 | V73: Постанова КМУ від 10 березня 2021 р. № 184 Питання Єдиного державного вебпорталу цифрової освіти “Дія. Цифрова освіта” https://zakon.rada.gov.ua/laws/show/184-2021-%D0%BF#Text | W73: Дані підрозділу Міністерства цифрової трансформації
B74: Розвиток цифрових навичок населення | C74: Розвиток талантів в галузі ІКТ | D74: В.2.3 | E74: Кількість хабів цифрової освіти на 10 000 осіб | G74: Хабів/10 000 осіб | H74: Базовий | I74: На майбутнє вимірювання | J74: Кількісні дані | K74: 1 | L74: =VLOOKUP(D74,'Перелік Iндикаторiв'!$D$4:$M$99,8,FALSE) -> 1 | M74: =VLOOKUP(D74,'Перелік Iндикаторiв'!$D$4:$M$99,9,FALSE) -> 0.33333333 | O74: В.2.3.2 | P74: Загальна кількість осіб, місце проживання яких зареєстровано у ТГ (ОВ: осіб) | Q74: Бал індикатора присвоюється пропорційно до розрахованого значення у відношенні до цільового з кроком 1 бал, де 100 - максимальний бал, коли розраховане значення дорівнює цільовому, 0 - мінімальний бал | R74: Формула розрахунку - [(Показник 1.1/Показник 1.2/10 000] де, Показник 1.1 - кількість хабів цифрової освіти в ТГ, хабів Показник 1.2 - Загальна кількість осіб місце проживання яких зареєстровано в ТГ, осіб | T74: Реєстрація місця проживання (перебування) особи – це внесення за заявою про реєстрацію місця проживання (перебування), поданою особою в паперовій формі, до реєстру територіальної громади інформації про місце проживання (перебування) особи. | U74: станом на 01.01.2022 | V74: Постанова КМУ від 10 березня 2021 р. № 184 Питання Єдиного державного вебпорталу цифрової освіти “Дія. Цифрова освіта” https://zakon.rada.gov.ua/laws/show/184-2021-%D0%BF#Text | W74: Дані підрозділу Міграційної служби
B75: Цифрова інфраструктура в ТГ | C75: Якість та доступність цифрової інфраструктури | D75: С.1.1 | E75: % соціальних об'єктів ТГ, підключених до волоконно-оптичних мереж | F75: Частка соціальних об'єктів ТГ, підключених до волоконно-оптичних мереж | G75: % | H75: Базовий | I75: Обов'язковий для вимірювання | J75: Кількісні дані | K75: 1 | L75: =VLOOKUP(D75,'Перелік Iндикаторiв'!$D$4:$M$99,8,FALSE) -> 1 | M75: =VLOOKUP(D75,'Перелік Iндикаторiв'!$D$4:$M$99,9,FALSE) -> 0.28776978 | O75: С.1.1.1 | P75: Кількість соціальних об'єктів ТГ, підключених до волоконно-оптичних мереж (ОВ: соціальні об'єкти) | Q75: Бал індикатора присвоюється пропорційно до розрахованого значення у відношенні до цільового з кроком 1 бал, де 100 - максимальний бал, коли розраховане значення дорівнює цільовому, 0 - мінімальний бал | R75: Формула розрахунку - [(Показник 1.1/Показник 1.2)*100], де Показник 1.1 - Кількість соціальних об'єктів ТГ, підключених до волоконно-оптичних мереж, соціальних об'єктів Показник 1.2 - Загальна кількість соціальних об'єктів ТГ, соціальних об'єктів | T75: Соціальні об'єкти ТГ, підключені до волоконно-оптичних мереж – до числа таких соціальних об`єктів входять заклади освіти (дошкільні, денні загальноосвітні, НВК, ПТНЗ, ВНЗ), охорони здоров`я (лікарні, амбулаторії-поліклініки, ФАП), культури (клубні заклади, бібліотеки, музеї), які мають підключення до мережі інтернет за допомогою волоконно-оптичних ліній передачі | U75: станом на 01.01.2022 | V75: Потребує визначення в законодавстві | W75: Дані структурного підрозділу ОМС
B76: Цифрова інфраструктура в ТГ | C76: Якість та доступність цифрової інфраструктури | D76: С.1.1 | E76: % соціальних об'єктів ТГ, підключених до волоконно-оптичних мереж | G76: % | H76: Базовий | I76: Обов'язковий для вимірювання | J76: Кількісні дані | K76: 1 | L76: =VLOOKUP(D76,'Перелік Iндикаторiв'!$D$4:$M$99,8,FALSE) -> 1 | M76: =VLOOKUP(D76,'Перелік Iндикаторiв'!$D$4:$M$99,9,FALSE) -> 0.28776978 | O76: С.1.1.2 | P76: Загальна кількість соціальних об'єктів ТГ (ОВ: соціальні об'єкти) | Q76: Бал індикатора присвоюється пропорційно до розрахованого значення у відношенні до цільового з кроком 1 бал, де 100 - максимальний бал, коли розраховане значення дорівнює цільовому, 0 - мінімальний бал | R76: Формула розрахунку - [(Показник 1.1/Показник 1.2)*100], де Показник 1.1 - Кількість соціальних об'єктів ТГ, підключених до волоконно-оптичних мереж, соціальних об'єктів Показник 1.2 - Загальна кількість соціальних об'єктів ТГ, соціальних об'єктів | T76: Загальна кількість соціальних об'єктів ТГ – до числа таких соціальних об`єктів входять заклади освіти (дошкільні, денні загальноосвітні, НВК, ПТНЗ, ВНЗ), охорони здоров`я (лікарні, амбулаторії-поліклініки, ФАП), культури (клубні заклади, бібліотеки, музеї) | U76: станом на 01.01.2022 | V76: Потребує визначення в законодавстві | W76: Дані структурного підрозділу ОМС
B77: Цифрова інфраструктура в ТГ | C77: Якість та доступність цифрової інфраструктури | D77: С.1.2 | E77: % підрозділів і віддалених робочих місць ЦНАП, підключених до системи онлайн-моніторингу й оцінювання якості послуг Порталу Дія | F77: Частка підрозділів та віддалених робочих місць ЦНАП, підключених до системи онлайн-моніторингу й оцінювання якості послуг Порталу Дія | G77: % | H77: Базовий | I77: Обов'язковий для вимірювання | J77: Кількісні дані | K77: 1 | L77: =VLOOKUP(D77,'Перелік Iндикаторiв'!$D$4:$M$99,8,FALSE) -> 1 | M77: =VLOOKUP(D77,'Перелік Iндикаторiв'!$D$4:$M$99,9,FALSE) -> 0.22302158 | O77: С.1.2.1 | P77: Кількість підрозділів і віддалених робочих місць ЦНАП, підключених до системи онлайн-моніторингу й оцінювання якості послуг Порталу Дія (ОВ: шт) | Q77: Бал індикатора присвоюється пропорційно до розрахованого значення у відношенні до цільового з кроком 1 бал, де 100 - максимальний бал, коли розраховане значення дорівнює цільовому, 0 - мінімальний бал | R77: Формула розрахунку - [(Показник 1.1/Показник 1.2)*100], де Показник 1.1 - Кількість підрозділів і віддалених робочих місць ЦНАП, підключених до системи онлайн-моніторингу й оцінювання якості послуг Порталу Дія, шт Показник 1.2 - Загальна кількість підрозділів і віддалених робочих місць ЦНАП, шт | T77: ЦНАП – це установи, у яких різні групи осіб можуть отримати широкий спектр адміністративних послуг у комфортних умовах. Створюються місцевими радами та місцевими державними адміністраціями і обслуговують як фізичних, так і юридичних осіб Підрозділ ЦНАПу – це територіально віддалений підрозділ, який надає адміністративні послуги Віддалене робоче місце ЦНАП – це територіально віддалені від основного центру робочі місця для надання адміністративних послуг | U77: станом на 01.01.2022 | V77: Закон України "Про адміністративні послуги" | W77: Дані підрозділу Міністерства цифрової трансформації
B78: Цифрова інфраструктура в ТГ | C78: Якість та доступність цифрової інфраструктури | D78: С.1.2 | E78: % підрозділів і віддалених робочих місць ЦНАП, підключених до системи онлайн-моніторингу й оцінювання якості послуг Порталу Дія | G78: % | H78: Базовий | I78: Обов'язковий для вимірювання | J78: Кількісні дані | K78: 1 | L78: =VLOOKUP(D78,'Перелік Iндикаторiв'!$D$4:$M$99,8,FALSE) -> 1 | M78: =VLOOKUP(D78,'Перелік Iндикаторiв'!$D$4:$M$99,9,FALSE) -> 0.22302158 | O78: С.1.2.2 | P78: Загальна кількість підрозділів і віддалених робочих місць ЦНАП (ОВ: підрозділи та робочі місця ЦНАП) | Q78: Бал індикатора присвоюється пропорційно до розрахованого значення у відношенні до цільового з кроком 1 бал, де 100 - максимальний бал, коли розраховане значення дорівнює цільовому, 0 - мінімальний бал | R78: Формула розрахунку - [(Показник 1.1/Показник 1.2)*100], де Показник 1.1 - Кількість підрозділів і віддалених робочих місць ЦНАП, підключених до системи онлайн-моніторингу й оцінювання якості послуг Порталу Дія, шт Показник 1.2 - Загальна кількість підрозділів і віддалених робочих місць ЦНАП, шт | T78: ЦНАП – це установи, у яких різні групи осіб можуть отримати широкий спектр адміністративних послуг у комфортних умовах. Створюються місцевими радами та місцевими державними адміністраціями і обслуговують як фізичних, так і юридичних осіб Підрозділ ЦНАПу – це територіально віддалений підрозділ, який надає адміністративні послуги Віддалене робоче місце ЦНАП – це територіально віддалені від основного центру робочі місця для надання адміністративних послуг | U78: станом на 01.01.2022 | V78: Закон України "Про адміністративні послуги" | W78: Дані структурного підрозділу ОМС
B79: Цифрова інфраструктура в ТГ | C79: Якість та доступність цифрової інфраструктури | D79: С.1.3 | E79: % посадових осіб, які мають службовий персональний комп'ютер, від загальної кількості посадових осіб ОМС | F79: Частка посадових осіб, які мають службовий персональний комп'ютер, від загальної кількості посадових осіб ОМС | G79: % | H79: Базовий | I79: Обов'язковий для вимірювання | J79: Кількісні дані | K79: 1 | L79: =VLOOKUP(D79,'Перелік Iндикаторiв'!$D$4:$M$99,8,FALSE) -> 1 | M79: =VLOOKUP(D79,'Перелік Iндикаторiв'!$D$4:$M$99,9,FALSE) -> 0.20143885 | O79: С.1.3.1 | P79: Кількість посадових осіб, які мають службовий персональний комп'ютер (ОВ: посадових осіб) | Q79: Бал індикатора присвоюється пропорційно до розрахованого значення у відношенні до цільового з кроком 1 бал, де 100 - максимальний бал, коли розраховане значення дорівнює цільовому, 0 - мінімальний бал | R79: Формула розрахунку - [(Показник 1.1/Показник 1.2)*100%], де Показник 1.1 - Кількість посадових осіб, які мають службовий персональний комп'ютер, посадових осіб Показник 1.2 - Загальна кількість посадових осіб у ОМС, посадових осіб | T79: Посадова особа місцевого самоврядування – особа, яка працює в органах місцевого самоврядування, має відповідні посадові повноваження щодо здійснення організаційно-розпорядчих та консультативно-дорадчих функцій і отримує заробітну плату коштом місцевого бюджету | U79: станом на 01.01.2022 | V79: Закон України Про службу в органах місцевого самоврядування https://zakon.rada.gov.ua/laws/show/2493-14#Text | W79: Дані структурного підрозділу ОМС
B80: Цифрова інфраструктура в ТГ | C80: Якість та доступність цифрової інфраструктури | D80: С.1.3 | E80: % посадових осіб, які мають службовий персональний комп'ютер, від загальної кількості посадових осіб ОМС | G80: % | H80: Базовий | I80: Обов'язковий для вимірювання | J80: Кількісні дані | K80: 1 | L80: =VLOOKUP(D80,'Перелік Iндикаторiв'!$D$4:$M$99,8,FALSE) -> 1 | M80: =VLOOKUP(D80,'Перелік Iндикаторiв'!$D$4:$M$99,9,FALSE) -> 0.20143885 | O80: С.1.3.2 | P80: Загальна кількість посадових осіб в ОМС (ОВ: посадових осіб) | Q80: Бал індикатора присвоюється пропорційно до розрахованого значення у відношенні до цільового з кроком 1 бал, де 100 - максимальний бал, коли розраховане значення дорівнює цільовому, 0 - мінімальний бал | R80: Формула розрахунку - [(Показник 1.1/Показник 1.2)*100%], де Показник 1.1 - Кількість посадових осіб, які мають службовий персональний комп'ютер, посадових осіб Показник 1.2 - Загальна кількість посадових осіб у ОМС, посадових осіб | T80: Посадова особа місцевого самоврядування – особа, яка працює в органах місцевого самоврядування, має відповідні посадові повноваження щодо здійснення організаційно-розпорядчих та консультативно-дорадчих функцій і отримує заробітну плату коштом місцевого бюджету | U80: станом на 01.01.2022 | V80: Закон України Про службу в органах місцевого самоврядування https://zakon.rada.gov.ua/laws/show/2493-14#Text | W80: Дані структурного підрозділу ОМС
B81: Цифрова інфраструктура в ТГ | C81: Якість та доступність цифрової інфраструктури | D81: С.1.4 | E81: % комп'ютерної техніки в закладах освіти, вік якої менше 7 років | F81: Частка комп'ютерної техніки в закладах освіти віком до 7 років | G81: % | H81: Базовий | I81: Обов'язковий для вимірювання | J81: Кількісні дані | K81: 1 | L81: =VLOOKUP(D81,'Перелік Iндикаторiв'!$D$4:$M$99,8,FALSE) -> 1 | M81: =VLOOKUP(D81,'Перелік Iндикаторiв'!$D$4:$M$99,9,FALSE) -> 0.086330935 | O81: С.1.4.1 | P81: Кількість комп'ютерної техніки в закладах освіти, вік якої менше 7 років (ОВ: одиниць) | Q81: Бал індикатора присвоюється пропорційно до розрахованого значення у відношенні до цільового з кроком 1 бал, де 100 - максимальний бал, коли розраховане значення дорівнює цільовому, 0 - мінімальний бал | R81: Формула розрахунку: [(Показник 1.1/Показник 1.2)*100], де Показник 1.1 - Кількість комп'ютерної техніки в закладах освіти, вік якої менше 7 років, одиниць Показник 1.2 - Загальна кількість комп'ютерної техніки в закладах освіти, одиниць | T81: Кількість комп'ютерної техніки в закладах освіти, вік якої менше 7 років – пристрої та системи пристроїв, що є компонентами комп'ютера, а також самі комп'ютери та обладнання, яке працює спільно з комп'ютерами, вік яких менший за 7 років | U81: станом на 01.01.2022 | V81: Потребує визначення в законодавстві | W81: Дані структурного підрозділу ОМС
B82: Цифрова інфраструктура в ТГ | C82: Якість та доступність цифрової інфраструктури | D82: С.1.4 | E82: % комп'ютерної техніки в закладах освіти, вік якої менше 7 років | G82: % | H82: Базовий | I82: Обов'язковий для вимірювання | J82: Кількісні дані | K82: 1 | L82: =VLOOKUP(D82,'Перелік Iндикаторiв'!$D$4:$M$99,8,FALSE) -> 1 | M82: =VLOOKUP(D82,'Перелік Iндикаторiв'!$D$4:$M$99,9,FALSE) -> 0.086330935 | O82: С.1.4.2 | P82: Загальна кількість комп'ютерної техніки в закладах освіти (ОВ: одиниць) | Q82: Бал індикатора присвоюється пропорційно до розрахованого значення у відношенні до цільового з кроком 1 бал, де 100 - максимальний бал, коли розраховане значення дорівнює цільовому, 0 - мінімальний бал | R82: Формула розрахунку: [(Показник 1.1/Показник 1.2)*100], де Показник 1.1 - Кількість комп'ютерної техніки в закладах освіти, вік якої менше 7 років, одиниць Показник 1.2 - Загальна кількість комп'ютерної техніки в закладах освіти, одиниць | T82: Загальна кількість комп'ютерної техніки в закладах освіти | U82: станом на 01.01.2022 | V82: Потребує визначення в законодавстві | W82: Дані структурного підрозділу ОМС
B83: Цифрова інфраструктура в ТГ | C83: Якість та доступність цифрової інфраструктури | D83: С.1.5 | E83: % персональних комп'ютерів та серверів у ОМС віком до 7 років | F83: Частка персональних комп'ютерів та серверів у ОМС віком до 7 років | G83: % | H83: Базовий | I83: Обов'язковий для вимірювання | J83: Кількісні дані | K83: 1 | L83: =VLOOKUP(D83,'Перелік Iндикаторiв'!$D$4:$M$99,8,FALSE) -> 1 | M83: =VLOOKUP(D83,'Перелік Iндикаторiв'!$D$4:$M$99,9,FALSE) -> 0.20143885 | O83: С.1.5.1 | P83: Кількість персональних комп'ютерів та серверів віком до 7 років в ОМС (ОВ: персональних комп'ютерів та серверів) | Q83: Бал індикатора присвоюється пропорційно до розрахованого значення у відношенні до цільового з кроком 1 бал, де 100 - максимальний бал, коли розраховане значення дорівнює цільовому, 0 - мінімальний бал | R83: Формула розрахунку - [(Показник 1.1/Показник 1.2)*100%], де Показник 1.1 - Кількість персональних комп'ютерів та серверів віком до 7 років в ОМС, персональних комп'ютерів та серверів Показник 1.2 - Загальна кількість персональних комп'ютерів та серверів у ОМС, персональних комп'ютерів та серверів | U83: станом на 01.01.2022 | V83: Потребує визначення в законодавстві | W83: Дані структурного підрозділу ОМС
B84: Цифрова інфраструктура в ТГ | C84: Якість та доступність цифрової інфраструктури | D84: С.1.5 | E84: % персональних комп'ютерів та серверів у ОМС віком до 7 років | G84: % | H84: Базовий | I84: Обов'язковий для вимірювання | J84: Кількісні дані | K84: 1 | L84: =VLOOKUP(D84,'Перелік Iндикаторiв'!$D$4:$M$99,8,FALSE) -> 1 | M84: =VLOOKUP(D84,'Перелік Iндикаторiв'!$D$4:$M$99,9,FALSE) -> 0.20143885 | O84: С.1.5.2 | P84: Загальна кількість персональних комп'ютерів та серверів в ОМС (ОВ: персональних комп'ютерів та серверів) | Q84: Бал індикатора присвоюється пропорційно до розрахованого значення у відношенні до цільового з кроком 1 бал, де 100 - максимальний бал, коли розраховане значення дорівнює цільовому, 0 - мінімальний бал | R84: Формула розрахунку - [(Показник 1.1/Показник 1.2)*100%], де Показник 1.1 - Кількість персональних комп'ютерів та серверів віком до 7 років в ОМС, персональних комп'ютерів та серверів Показник 1.2 - Загальна кількість персональних комп'ютерів та серверів у ОМС, персональних комп'ютерів та серверів | U84: станом на 01.01.2022 | V84: Потребує визначення в законодавстві | W84: Дані структурного підрозділу ОМС
B85: Цифрова інфраструктура в ТГ | C85: Кібербезпека | D85: С.2.1 | E85: Управління кіберінцидентами | G85: Балів | I85: На майбутнє вимірювання | J85: Якісні дані | L85: =VLOOKUP(D85,'Перелік Iндикаторiв'!$D$4:$M$99,8,FALSE) -> 0 | M85: =VLOOKUP(D85,'Перелік Iндикаторiв'!$D$4:$M$99,9,FALSE) -> 0 | O85: С.2.1.1 | P85: Наявність впровадженої системи управління кіберінцидентами (ОВ: Так/Нi) | Q85: 0,5 бала - якщо наявна впроваджена система управління кіберінцидентами, 0 балів - якщо не впроваджена система управління кіберінцидентами | R85: Формула розрахунку - [(Показник 1.1+Показник 1.2+ Показник 1.3) де, Показник 1.1 - Наявність впровадженої системи управління кіберінцидентами, Так - 0,5 бала, Ні - 0 балів Показник 1.2 - Час реагування системи на кіберінциденти до Х годин, Так - 0,25 бала, Ні - 0 балів Показник 1.3 - Період відновлення системи після кіберінциденту до Х годин, Так - 0,25 бала, Ні - 0 балів | T85: Система управління кіберінцидентами – комплекс заходів і програм, що гарантує достатній рівень захищеності і готовності муніципальних інформаційних ресурсів та критичної інформаційної інфраструктури до запобігання кіберінцидентам, оперативного реагування на кіберзагрози, попередження, виявлення та захисту від кібератак, ліквідації їхніх наслідків, відновлення функціонування цих об'єктів і систем. | U85: станом на 01.01.2022 | V85: Закон України "Про основні засади забезпечення кібербезпеки України" https://zakon.rada.gov.ua/laws/show/2163-19#Text | W85: Дані структурного підрозділу ОМС
B86: Цифрова інфраструктура в ТГ | C86: Кібербезпека | D86: С.2.1 | E86: Управління кіберінцидентами | G86: Балів | I86: На майбутнє вимірювання | J86: Якісні дані | L86: =VLOOKUP(D86,'Перелік Iндикаторiв'!$D$4:$M$99,8,FALSE) -> 0 | M86: =VLOOKUP(D86,'Перелік Iндикаторiв'!$D$4:$M$99,9,FALSE) -> 0 | O86: С.2.1.2 | P86: Час реагування системи на кіберінциденти до Х годин (ОВ: Так/Нi) | Q86: 0,25 бала - якщо час реагування системи на кіберінциденти до Х годин 0 балів - якщо час реагування системи на кіберінциденти більше Х годин | R86: Формула розрахунку - [(Показник 1.1+Показник 1.2+ Показник 1.3) де, Показник 1.1 - Наявність впровадженої системи управління кіберінцидентами, Так - 0,5 бала, Ні - 0 балів Показник 1.2 - Час реагування системи на кіберінциденти до Х годин, Так - 0,25 бала, Ні - 0 балів Показник 1.3 - Період відновлення системи після кіберінциденту до Х годин, Так - 0,25 бала, Ні - 0 балів | T86: Час реагування системи на кіберінцидент – це час, необхідний для підтвердження зазначеної події та визначення мережевої активності після події стосовно інфільтрації систем та ексфільтрації даних, а також для виявлення додаткових зламаних комп'ютерів та облікових записів користувачів. | U86: станом на 01.01.2022 | V86: Закон України "Про основні засади забезпечення кібербезпеки України" https://zakon.rada.gov.ua/laws/show/2163-19#Text | W86: Дані структурного підрозділу ОМС
B87: Цифрова інфраструктура в ТГ | C87: Кібербезпека | D87: С.2.1 | E87: Управління кіберінцидентами | G87: Балів | I87: На майбутнє вимірювання | J87: Якісні дані | L87: =VLOOKUP(D87,'Перелік Iндикаторiв'!$D$4:$M$99,8,FALSE) -> 0 | M87: =VLOOKUP(D87,'Перелік Iндикаторiв'!$D$4:$M$99,9,FALSE) -> 0 | O87: С.2.1.3 | P87: Період відновлення системи після кіберінциденту до Х годин (ОВ: Так/Нi) | Q87: 0,25 бала - якщо період відновлення систем після кіберінциденту до Х годин 0 балів - якщо період відновлення систем після кіберінциденту більше Х годин | R87: Формула розрахунку - [(Показник 1.1+Показник 1.2+ Показник 1.3) де, Показник 1.1 - Наявність впровадженої системи управління кіберінцидентами, Так - 0,5 бала, Ні - 0 балів Показник 1.2 - Час реагування системи на кіберінциденти до Х годин, Так - 0,25 бала, Ні - 0 балів Показник 1.3 - Період відновлення системи після кіберінциденту до Х годин, Так - 0,25 бала, Ні - 0 балів | T87: Час відновлення – це час, необхідний для визначення короткострокових потреб і дій для усунення кіберзагрози на основі показників інциденту та рівня захищеності інформаційних систем, а також для визначення довгострокових проєктів щодо подальшого зміцнення інформаційної безпеки. | U87: станом на 01.01.2022 | V87: Закон України "Про основні засади забезпечення кібербезпеки України" https://zakon.rada.gov.ua/laws/show/2163-19#Text | W87: Дані структурного підрозділу ОМС
B88: Цифрова інфраструктура в ТГ | C88: Кібербезпека | D88: С.2.2 | E88: % посадових осіб ОМС, які пройшли навчання (підвищення кваліфікації) за програмами з кібербезпеки й кібергігієни, від загальної кількості посадових осіб ОМС | F88: Частка посадових осіб ОМС, які пройшли навчання (підвищення кваліфікації) за програмами з кібербезпеки й кібергігієни, від загальної кількості посадових осіб ОМС | G88: % | H88: Базовий | I88: Обов'язковий для вимірювання | J88: Кількісні дані | K88: 0.5 | L88: =VLOOKUP(D88,'Перелік Iндикаторiв'!$D$4:$M$99,8,FALSE) -> 0.5 | M88: =VLOOKUP(D88,'Перелік Iндикаторiв'!$D$4:$M$99,9,FALSE) -> 0.22077922 | O88: С.2.2.1 | P88: Кількість посадових осіб ОМС, які пройшли навчання (підвищення кваліфікації) за програмами з кібербезпеки й кібергігієни (ОВ: посадових осіб) | Q88: Бал індикатора присвоюється пропорційно до розрахованого значення у відношенні до цільового з кроком 1 бал, де 100 - максимальний бал, коли розраховане значення дорівнює цільовому, 0 - мінімальний бал | R88: Формула розрахунку - [(Показник 1.1/Показник 1.2)*100%] де, Показник 1.1 - Кількість посадових осіб ОМС, які пройшли навчання (підвищення кваліфікації) за програмами із кібербезпеки й кібергігієни, посадових осіб Показник 1.2 - Загальна кількість посадових осіб ОМС, посадових осіб | T88: Посадова особа ОМС, яка пройшла навчання (підвищення кваліфікації) за програмами з кібербезпеки й кібергігієни – це особа, яка працює в органах місцевого самоврядування, має відповідні посадові повноваження щодо здійснення організаційно-розпорядчих та консультативно-дорадчих функцій, отримує заробітну плату коштом місцевого бюджету та має підтвердження щодо проходження освітніх продуктів із кібербезпеки й кібергігієни на порталі Дія.Цифрова освіта | U88: станом на 01.01.2022 | V88: Постанова КМУ від 10 березня 2021 р. № 184 Питання Єдиного державного вебпорталу цифрової освіти “Дія. Цифрова освіта” https://zakon.rada.gov.ua/laws/show/184-2021-%D0%BF#Text | W88: Дані структурного підрозділу ОМС
B89: Цифрова інфраструктура в ТГ | C89: Кібербезпека | D89: С.2.2 | E89: % посадових осіб ОМС, які пройшли навчання (підвищення кваліфікації) за програмами з кібербезпеки та кібергігієни, від загальної кількості посадових осіб ОМС | G89: % | H89: Базовий | I89: Обов'язковий для вимірювання | J89: Кількісні дані | K89: 0.5 | L89: =VLOOKUP(D89,'Перелік Iндикаторiв'!$D$4:$M$99,8,FALSE) -> 0.5 | M89: =VLOOKUP(D89,'Перелік Iндикаторiв'!$D$4:$M$99,9,FALSE) -> 0.22077922 | O89: С.2.2.2 | P89: Загальна кількість посадових осіб ОМС (ОВ: посадових осіб) | Q89: Бал індикатора присвоюється пропорційно до розрахованого значення у відношенні до цільового з кроком 1 бал, де 100 - максимальний бал, коли розраховане значення дорівнює цільовому, 0 - мінімальний бал | R89: Формула розрахунку - [(Показник 1.1/Показник 1.2)*100%] де, Показник 1.1 - Кількість посадових осіб ОМС, які пройшли навчання (підвищення кваліфікації) за програмами з кібербезпеки й кібергігієни, посадових осіб Показник 1.2 - Загальна кількість посадових осіб ОМС, посадових осіб | T89: Посадова особа ОМС – це особа, яка працює в органах місцевого самоврядування, має відповідні посадові повноваження щодо здійснення організаційно-розпорядчих та консультативно-дорадчих функцій, отримує заробітну плату коштом місцевого бюджету | U89: станом на 01.01.2022 | V89: Постанова КМУ від 10 березня 2021 р. № 184 Питання Єдиного державного вебпорталу цифрової освіти “Дія. Цифрова освіта” https://zakon.rada.gov.ua/laws/show/184-2021-%D0%BF#Text | W89: Дані структурного підрозділу ОМС
B90: Цифрова інфраструктура в ТГ | C90: Кібербезпека | D90: С.2.3 | E90: % комп'ютерної техніки в ОМС, на якій регулярно (1 раз на квартал) проводиться контроль оновлень ПЗ до останньої версії | F90: Частка комп'ютерної техніки в ОМС, на якій 1 раз на квартал проводиться контроль оновлень ПЗ до останньої версії | G90: % | H90: Базовий | I90: Обов'язковий для вимірювання | J90: Кількісні дані | K90: 1 | L90: =VLOOKUP(D90,'Перелік Iндикаторiв'!$D$4:$M$99,8,FALSE) -> 1 | M90: =VLOOKUP(D90,'Перелік Iндикаторiв'!$D$4:$M$99,9,FALSE) -> 0.22077922 | O90: С.2.3.1 | P90: Кількість одиниць комп'ютерної техніки в ОМС, на якій регулярно (1 раз на квартал) проводиться контроль оновлень ПЗ до останньої версії (ОВ: одиниць комп'ютерної техніки) | Q90: Бал індикатора присвоюється пропорційно до розрахованого значення у відношенні до цільового з кроком 1 бал, де 100 - максимальний бал, коли розраховане значення дорівнює цільовому, 0 - мінімальний бал | R90: Формула розрахунку - [(Показник 1.1/Показник 1.2)*100%] де, Показник 1.1 - Кількість одиниць комп'ютерної техніки в ОМС, на якій регулярно (1 раз на квартал) проводиться контроль оновлень ПЗ до останньої версії, одиниць комп'ютерної техніки Показник 1.2 - Загальна кількість одиниць комп'ютерної техніки в ОМС, одиниць комп'ютерної техніки | T90: Комп'ютерна техніка – пристрої та системи пристроїв, що є компонентами комп'ютера, а також самі комп'ютери та обладнання, яке працює спільно з комп'ютерами (периферійні пристрої) і забезпечує певну додаткову функціональність. Програмне забезпечення – сукупність програм, необхідних для виконання всіх основних і додаткових функцій системи (її компонента), які зберігаються в пам'яті та/або в програмувальних електронних пристроях, що входять до складу цієї системи (компонента), а також програм на зовнішніх носіях і програмної документації | U90: станом на 01.01.2022 | V90: Потребує визначення в законодавстві | W90: Дані структурного підрозділу ОМС
B91: Цифрова інфраструктура в ТГ | C91: Кібербезпека | D91: С.2.3 | E91: % комп'ютерної техніки в ОМС, на якій регулярно (1 раз на квартал) проводиться контроль оновлень ПЗ до останньої версії | G91: % | H91: Базовий | I91: Обов'язковий для вимірювання | J91: Кількісні дані | K91: 1 | L91: =VLOOKUP(D91,'Перелік Iндикаторiв'!$D$4:$M$99,8,FALSE) -> 1 | M91: =VLOOKUP(D91,'Перелік Iндикаторiв'!$D$4:$M$99,9,FALSE) -> 0.22077922 | O91: С.2.3.2 | P91: Загальна кількість одиниць комп'ютерної техніки в ОМС, якою користуються службові особи (ОВ: одиниць комп'ютерної техніки) | Q91: Бал індикатора присвоюється пропорційно до розрахованого значення у відношенні до цільового з кроком 1 бал, де 100 - максимальний бал, коли розраховане значення дорівнює цільовому, 0 - мінімальний бал | R91: Формула розрахунку - [(Показник 1.1/Показник 1.2)*100%] де, Показник 1.1 - Кількість одиниць комп'ютерної техніки в ОМС, на якій регулярно (1 раз на квартал) проводиться контроль оновлень ПЗ до останньої версії, одиниць комп'ютерної техніки Показник 1.2 - Загальна кількість одиниць комп'ютерної техніки в ОМС, одиниць комп'ютерної техніки | T91: Комп'ютерна техніка – пристрої та системи пристроїв, що є компонентами комп'ютера, а також самі комп'ютери та обладнання, яке працює спільно з комп'ютерами (периферійні пристрої) і забезпечує певну додаткову функціональність. | U91: станом на 01.01.2022 | V91: Потребує визначення в законодавстві | W91: Дані структурного підрозділу ОМС
B92: Цифрова інфраструктура в ТГ | C92: Кібербезпека | D92: С.2.4 | E92: Наявність Політики (ВНД) щодо кібербезпеки на рівні ОМС | F92: Наявність Політики (ВНД) щодо кібербезпеки на рівні ОМС | G92: Балів | H92: Базовий | I92: Обов'язковий для вимірювання | J92: Якісні дані | K92: 1 | L92: =VLOOKUP(D92,'Перелік Iндикаторiв'!$D$4:$M$99,8,FALSE) -> 1 | M92: =VLOOKUP(D92,'Перелік Iндикаторiв'!$D$4:$M$99,9,FALSE) -> 0.27272727 | O92: С.2.4.1 | P92: Наявність затвердженої політики щодо кібербезпеки (ОВ: Так/Нi) | Q92: 1 бал, якщо є затверджена Політика щодо кібербезпеки 0 балів, якщо відсутня затверджена Політика щодо кібербезпеки | R92: Формула розрахунку - [Показник 1.1] де, Показник 1.1 - Наявність затвердженої політики щодо кібербезпеки, Так -1 бал, Ні - 0 балів | T92: Затверджена політика щодо кібербезпеки – документ, затверджений сесією ради, який встановлює правила, загальні принципи та характеристики заходів, що підвищують захищеність даних ОМС під час використання кіберпростору, визначає правила та норми поведінки посадових осіб ОМС під час використання цифрового комунікативного середовища, сприяє своєчасному виявленню, запобіганню і нейтралізації реальних і потенційних загроз у кіберпросторі. | U92: станом на 01.01.2022 | V92: Закон України "Про основні засади забезпечення кібербезпеки України" https://zakon.rada.gov.ua/laws/show/2163-19#Text | W92: Дані структурного підрозділу ОМС
B93: Цифрова інфраструктура в ТГ | C93: Кібербезпека | D93: С.2.5 | E93: ТГ підключена до системи інформування про кіберінциденти MISP-UA та MISP CERT UA | F93: ТГ підключена до системи інформування про кіберінциденти MISP-UA та MISP CERT UA | G93: Балів | H93: Базовий | I93: Обов'язковий для вимірювання | J93: Якісні дані | K93: 1 | L93: =VLOOKUP(D93,'Перелік Iндикаторiв'!$D$4:$M$99,8,FALSE) -> 1 | M93: =VLOOKUP(D93,'Перелік Iндикаторiв'!$D$4:$M$99,9,FALSE) -> 0.28571429 | O93: С.2.5.1 | P93: ТГ підключена до системи інформування про кіберінциденти MISP-UA та MISP CERT UA (ОВ: Так/Ні) | Q93: 1 бал, якщо ТГ підключена до системи інформування про кіберінциденти MISP-UA та MISP CERT UA 0 балів, якщо ТГ не підключена до системи інформування про кіберінциденти MISP-UA та MISP CERT UA | R93: Формула розрахунку - [Показник 1.1] де, Показник 1.1. ТГ підключена до системи інформування про кіберінциденти MISP-UA та MISP CERT UA, Так - 1 бал, Нi - 0 балів | T93: Інформаційна платформа MISP-UA – онлайн-майданчик для обміну даними про кібератаки та кіберінциденти на об’єктах критичної інфраструктури і державних електронних інформаційних ресурсах. https://misp.cert.gov.ua/ | U93: станом на 01.01.2022 | V93: Закон України "Про основні засади забезпечення кібербезпеки України" https://zakon.rada.gov.ua/laws/show/2163-19#Text | W93: Дані структурного підрозділу ОМС
B94: Цифрова інфраструктура в ТГ | C94: Кібербезпека | D94: С.2.6 | E94: % населення, що пройшло створені ОМС навчальні програми з кібербезпеки для населення ТГ, від загальної чисельності наявного населення ТГ | G94: % | I94: На майбутнє вимірювання | J94: Кількісні дані | L94: =VLOOKUP(D94,'Перелік Iндикаторiв'!$D$4:$M$99,8,FALSE) -> 0 | M94: =VLOOKUP(D94,'Перелік Iндикаторiв'!$D$4:$M$99,9,FALSE) -> 0 | O94: С.2.6.1 | P94: Чисельність населення, що пройшло створені ОМС навчальні програми з кібербезпеки для населення ТГ (ОВ: осіб) | Q94: Бал індикатора присвоюється пропорційно до розрахованого значення у відношенні до цільового з кроком 1 бал, де 100 - максимальний бал, коли розраховане значення дорівнює цільовому, 0 - мінімальний бал | R94: Формула розрахунку - [(Показник 1.1/Показник 1.2)*100%] де, Показник 1.1 - Чисельність населення, що пройшло створені ОМС навчальні програми з кібербезпеки для населення ТГ, осіб Показник 1.2 - Загальна кількість осіб, місце проживання яких зареєстровано у ТГ, осіб | T94: Чисельність населення, яке пройшло створені ОМС навчальні програми з кібербезпеки для населення ТГ, – населення, яке на момент перепису перебуває на території ТГ (разом з тими, хто проживає тимчасово) та відвідали заняття за навчальними програмами з кібербезпеки, що були створені та проведені ОМС | U94: станом на 01.01.2022 | V94: Потребує визначення в законодавстві | W94: Дані структурного підрозділу ОМС
B95: Цифрова інфраструктура в ТГ | C95: Кібербезпека | D95: С.2.6 | E95: % населення, що пройшло створені ОМС навчальні програми з кібербезпеки для населення ТГ, від загальної чисельності наявного населення ТГ | G95: % | I95: На майбутнє вимірювання | J95: Кількісні дані | L95: =VLOOKUP(D95,'Перелік Iндикаторiв'!$D$4:$M$99,8,FALSE) -> 0 | M95: =VLOOKUP(D95,'Перелік Iндикаторiв'!$D$4:$M$99,9,FALSE) -> 0 | O95: С.2.6.2 | P95: Загальна кількість осіб, місце проживання яких зареєстровано у ТГ (ОВ: осіб) | Q95: Бал індикатора присвоюється пропорційно до розрахованого значення у відношенні до цільового з кроком 1 бал, де 100 - максимальний бал, коли розраховане значення дорівнює цільовому, 0 - мінімальний бал | R95: Формула розрахунку - [(Показник 1.1/Показник 1.2)*100%] де, Показник 1.1 - Чисельність населення, що пройшло створені ОМС навчальні програми з кібербезпеки для населення ТГ, осіб Показник 1.2 - Загальна кількість осіб, місце проживання яких зареєстровано у ТГ, осіб | T95: Реєстрація місця проживання (перебування) особи – це внесення за заявою про реєстрацію місця проживання (перебування), поданою особою в паперовій формі, до реєстру територіальної громади інформації про місце проживання (перебування) особи. | U95: станом на 01.01.2022 | V95: Потребує визначення в законодавстві | W95: Дані підрозділу Міграційної служби
B96: Цифрова інфраструктура в ТГ | C96: Створення безпечного середовища | D96: С.3.1 | E96: Кількість активних камер відеоспостереження на площу населених пунктів у ТГ | F96: Кількість активних камер відеоспостереження на площу населених пунктів у ТГ | G96: коефіцієнт | H96: Базовий | I96: Обов'язковий для вимірювання | J96: Кількісні дані | K96: 10 | L96: =VLOOKUP(D96,'Перелік Iндикаторiв'!$D$4:$M$99,8,FALSE) -> 10 | M96: =VLOOKUP(D96,'Перелік Iндикаторiв'!$D$4:$M$99,9,FALSE) -> 0.25 | O96: С.3.1.1 | P96: Кількість активних камер відеоспостереження (ОВ: шт) | Q96: Бал індикатора присвоюється пропорційно до розрахованого значення у відношенні до цільового з кроком 1 бал, де 100 - максимальний бал, коли розраховане значення дорівнює цільовому, 0 - мінімальний бал | R96: Формула розрахунку - [(Показник 1.1/Показник 1.2], де Показник 1.1 - Кількість активних камер відеоспостереження, шт Показник 1.2 - Загальна площа населених пунктів в ТГ, км2 | T96: Кількість камер централізованої системи відеоспостереження на території ТГ – кількість камер, об'єднаних в комплекс обладнання та програмного забезпечення, призначений для спостереження за територією, діями та ситуацією в ОТГ. Активні камери – це ті, які працювали більше 75% часу у звітному періоді | U96: станом на 01.01.2022 | V96: Потребує визначення в законодавстві | W96: Дані структурного підрозділу ОМС
B97: Цифрова інфраструктура в ТГ | C97: Створення безпечного середовища | D97: С.3.1 | E97: Кількість активних камер відеоспостереження на площу населених пунктів у ТГ | G97: коефіцієнт | H97: Базовий | I97: Обов'язковий для вимірювання | J97: Кількісні дані | K97: 10 | L97: =VLOOKUP(D97,'Перелік Iндикаторiв'!$D$4:$M$99,8,FALSE) -> 10 | M97: =VLOOKUP(D97,'Перелік Iндикаторiв'!$D$4:$M$99,9,FALSE) -> 0.25 | O97: С.3.1.2 | P97: Загальна площа населених пунктів у ТГ (OB: км2) | Q97: Бал індикатора присвоюється пропорційно до розрахованого значення у відношенні до цільового з кроком 1 бал, де 100 - максимальний бал, коли розраховане значення дорівнює цільовому, 0 - мінімальний бал | R97: Формула розрахунку - [(Показник 1.1/Показник 1.2], де Показник 1.1 - Кількість активних камер відеоспостереження, шт Показник 1.2 - Загальна площа населених пунктів в ТГ, км2 | T97: Площа населених пунктів ТГ – площа земель, що входять до адміністративних територіальних одиниць населених пунктів у складі ТГ | U97: станом на 01.01.2022 | V97: Потребує визначення в законодавстві | W97: Дані структурного підрозділу ОМС
